Workbook

Sheet 1. Missing Value Summary
A1: Missing Value Summary
A3: Column Evaluated | B3: Missing Count | C3: Handling Strategy Applied
A4: Region | B4: =COUNTIF('Cleaned Orders'!AC:AC, "Missing region") -> 24 | C4: Blanks replaced with "Unknown" and flagged.
A5: Ship Mode | B5: =COUNTIF('Cleaned Orders'!AC:AC, "Missing ship_mode") -> 17 | C5: Blanks replaced with "Unknown" and flagged.
A6: Discount | B6: =COUNTIF('Cleaned Orders'!AC:AC, "Missing Date") -> 0 | C6: Empty discounts treated as 0 (valid rows only).

Sheet 2. Duplicate Summary 
A1: Duplicate Record Summary
A3: Metric | B3: Record Count | C3: Logic Used
A4: Number of exact duplicate rows found | B4: 20 | C4: Rows where every single column matched identically.
A5: Number of duplicate order IDs found | B5: =COUNTIF('Cleaned Orders'!AC:AC, "Conflicting Duplicate Order ID") -> 63 | C5: Rows sharing an order_id but containing conflicting data fields.
A6: Number of records removed | B6: =B4 -> 20 | C6: Permanently removed exact duplicate rows from the final dataset.
A7: Number of records flagged for review | B7: =B5 -> 63 | C7: Retained in the final dataset but tagged for manual business logic resolution
A8: Logic used for handling duplicates | B8: Conditional Flagging | C8: Exact duplicates dropped entirely. Conflicting duplicates retained and flagged via COUNTIF matching to prevent data loss

Sheet 3. Invalid discount summary
A1: Invalid Discount Summary
A3: Out-of-Bounds Issue | B3: Count | C3: Rule Violation Definition
A4: Negative Discounts | B4: =COUNTIFS('Cleaned Orders'!P:P, "<0") -> 16 | C4: Any rate below 0.00% (Flagged as Invalid).
A5: Exceeded Max Threshold | B5: =COUNTIFS('Cleaned Orders'!P:P, ">0.7 OR >70%") -> 9 | C5: Discounts greater than 70% (Flagged as Invalid).

Sheet 4. Date issue summary
A1: Date Sequence Issue Summary
A3: Anomaly Identified | B3: Count | C3: Operational Impact
A4: Ship Date Before Order Date | B4: =COUNTIF('Cleaned Orders'!AC:AC, "Invalid shipping record") -> 69 | C4: Timeline logic failure (Flagged as Invalid shipping record).
A5: Unparseable / Text Dates | B5: =COUNTIF('Cleaned Orders'!AC:AC, "Text Value Not Recognized as Date") -> 247 | C5: Raw strings that Excel could not transform.

Sheet 5. Order status issue summary
A1: Order Status Impact Summary
A3: Order/Payment Status | B3: Volume | C3: Completed Sales Summary Action
A4: Cancelled | B4: =COUNTIF('Cleaned Orders'!U:U, "Cancelled") -> 146 | C4: Completely excluded from completed metrics.
A5: Failed Payments | B5: =COUNTIF('Cleaned Orders'!T:T, "Failed") -> 69 | C5: Completely excluded from completed metrics.
A6: Refunded / Returned | B6: =COUNTIF('Cleaned Orders'!U:U, "Returned") -> 164 | C6: Separately summarized as a distinct bucket.

Sheet 6. Sales-profit calculation
A1: Sales/Profit Calculation Mismatch Summary
A3: Calculation Check | B3: Variance Rows Found | C3: Status Notes
A4: Sales vs Calculated Sales | B4: =SUM('Cleaned Orders'!AD:AD) -> 65 | C4: Counts rows where raw sales don't match quantity * price.
A5: Profit vs Calculated Profit | B5: =SUM('Cleaned Orders'!AE:AE) -> 66 | C5: Counts rows where profit doesn't equal sales - cost.

Sheet 7. Final clean vs flagged 
A1: Final Dataset Quality Distribution
A3: Data Quality Classification | B3: Record Count | C3: Percentage of Total
A4: Valid (Clean Records) | B4: =COUNTIF('Cleaned Orders'!AC:AC, "Valid") -> 497 | C4: =B4/SUM(B4:B5)
A5: Flagged / Invalid Records | B5: =COUNTIF('Cleaned Orders'!AC:AC, "<>Valid") - 1 -> 1048078 | C5: =B5/SUM(B4:B5)
A6: Total Active Row Count | B6: =COUNTA('Cleaned Orders'!A:A) - 1 -> 932 | C6: 1

Sheet Cleaned Orders
A1: order_id | B1: order_date | C1: ship_date | D1: customer_id | E1: customer_name | F1: segment | G1: region | H1: state | I1: city | J1: category | K1: sub_category | L1: product_name | M1: ship_mode | N1: quantity | O1: unit_price | P1: discount | Q1: sales | R1: cost | S1: profit | T1: payment_status | U1: order_status | V1: cleaned_discount | W1: calculated_sales | X1: calculated_profit | Y1: profit_margin | Z1: shipping_delay_days | AA1: order_month | AB1: order_year | AC1: data_quality_flag | AD1: Sales Mismatch Check | AE1: Profit Mismatch Check | AH1: customer_name (cleaned) | AI1: segment (cleaned) | AJ1: region (cleaned) | AK1: state (cleaned) | AL1: city (cleaned) | AM1: category (cleaned) | AN1: sub_category (cleaned) | AO1: ship_mode (cleaned) | AP1: payment_status (cleaned) | AQ1: order_status (cleaned)
A2: ORD-2024-10001 | B2: 45494 | C2: 45500 | D2: CUST-4655 | E2: Karan Malhotra | F2: Consumer | G2: North | H2: Rajasthan | I2: Jaipur | J2: Office Supplies | K2: Paper | L2: Pro Paper 122 | M2: Second Class | N2: 8 | O2: 2976.45 | P2: 0.2 | Q2: 19049.28 | R2: 15841.89 | S2: 3207.39 | T2: Paid | U2: Completed | V2: =IF(ISBLANK(P2), 0, P2) -> 0.2 | W2: =N2 * O2 * (1 - P2) -> 19049.28 | X2: =W2-R2 -> 3207.39 | Y2: =IFERROR(X2 / W2, 0) -> 0.16837329 | Z2: =IF(OR(ISBLANK(B2), ISBLANK(C2), ISTEXT(B2), ISTEXT(C2)), "", C2 - B2) -> 6 | AA2: =MONTH(B2) -> 7 | AB2: =YEAR(B2) -> 2024 | AC2: =IF(COUNTIF(A:A, A2) > 1, "Conflicting Duplicate Order ID", IF(OR(G2="Unknown", ISBLANK(G2)), "Missing region", IF(OR(M2="Unknown", ISBLANK(M2)), "Missing ship_mode", IF(OR(ISBLANK(B2), ISBLANK(C2)), "Missing Date", IF(OR(ISTEXT(B2), ISTEXT(C2)), "Text Value Not Recognized as Date", IF(C2 < B2, "Invalid shipping record", IF(P2 < 0, "Invalid", IF(P2 > 0.7, "Invalid", "Valid")))))))) -> Valid | AD2: =IF(ABS(Q2 - W2) > 0.01, 1, 0) -> 0 | AE2: =IF(ABS(S2 - X2) > 0.01, 1, 0) -> 0 | AH2: =PROPER(TRIM(E2)) -> Karan Malhotra | AI2: =PROPER(TRIM(F2)) -> Consumer | AJ2: =PROPER(TRIM(G2)) -> North | AK2: =PROPER(TRIM(H2)) -> Rajasthan | AL2: =PROPER(TRIM(I2)) -> Jaipur | AM2: =PROPER(TRIM(J2)) -> Office Supplies | AN2: =PROPER(TRIM(K2)) -> Paper | AO2: =PROPER(TRIM(M2)) -> Second Class | AP2: =PROPER(TRIM(T2)) -> Paid | AQ2: =PROPER(TRIM(U2)) -> Completed
A3: ORD-2024-10002 | B3: 45535 | C3: 45540 | D3: CUST-2054 | E3: Mira Das | F3: Small Business | G3: East | H3: Odisha | I3: Bhubaneswar | J3: Furniture | K3: Tables | L3: Pro Tables 258 | M3: Same Day | N3: 3 | O3: 2437.5 | P3: 0 | Q3: 7312.5 | R3: 4904.73 | S3: 2407.77 | T3: Paid | U3: Completed | V3: =IF(ISBLANK(P3), 0, P3) -> 0 | W3: =N3 * O3 * (1 - P3) -> 7312.5 | X3: =W3-R3 -> 2407.77 | Y3: =IFERROR(X3 / W3, 0) -> 0.32926769 | Z3: =IF(OR(ISBLANK(B3), ISBLANK(C3), ISTEXT(B3), ISTEXT(C3)), "", C3 - B3) -> 5 | AA3: =MONTH(B3) -> 8 | AB3: =YEAR(B3) -> 2024 | AC3: =IF(COUNTIF(A:A, A3) > 1, "Conflicting Duplicate Order ID", IF(OR(G3="Unknown", ISBLANK(G3)), "Missing region", IF(OR(M3="Unknown", ISBLANK(M3)), "Missing ship_mode", IF(OR(ISBLANK(B3), ISBLANK(C3)), "Missing Date", IF(OR(ISTEXT(B3), ISTEXT(C3)), "Text Value Not Recognized as Date", IF(C3 < B3, "Invalid shipping record", IF(P3 < 0, "Invalid", IF(P3 > 0.7, "Invalid", "Valid")))))))) -> Valid | AD3: =IF(ABS(Q3 - W3) > 0.01, 1, 0) -> 0 | AE3: =IF(ABS(S3 - X3) > 0.01, 1, 0) -> 0 | AH3: =PROPER(TRIM(E3)) -> Mira Das | AI3: =PROPER(TRIM(F3)) -> Small Business | AJ3: =PROPER(TRIM(G3)) -> East | AK3: =PROPER(TRIM(H3)) -> Odisha | AL3: =PROPER(TRIM(I3)) -> Bhubaneswar | AM3: =PROPER(TRIM(J3)) -> Furniture | AN3: =PROPER(TRIM(K3)) -> Tables | AO3: =PROPER(TRIM(M3)) -> Same Day | AP3: =PROPER(TRIM(T3)) -> Paid | AQ3: =PROPER(TRIM(U3)) -> Completed
A4: ORD-2024-10003 | B4: 45451 | C4: 45458 | D4: CUST-6843 | E4: Isha Nair | F4: Consumer | G4: East | H4: Odisha | I4: Bhubaneswar | J4: Office Supplies | K4: Art | L4: Elite Art 525 | M4: First Class | N4: 4 | O4: 1065.43 | P4: 0.55 | Q4: 4261.72 | R4: 2465.69 | S4: 1796.03 | T4: Paid | U4: Completed | V4: =IF(ISBLANK(P4), 0, P4) -> 0.55 | W4: =N4 * O4 * (1 - P4) -> 1917.774 | X4: =W4-R4 -> -547.916 | Y4: =IFERROR(X4 / W4, 0) -> -0.28570415 | Z4: =IF(OR(ISBLANK(B4), ISBLANK(C4), ISTEXT(B4), ISTEXT(C4)), "", C4 - B4) -> 7 | AA4: =MONTH(B4) -> 6 | AB4: =YEAR(B4) -> 2024 | AC4: =IF(COUNTIF(A:A, A4) > 1, "Conflicting Duplicate Order ID", IF(OR(G4="Unknown", ISBLANK(G4)), "Missing region", IF(OR(M4="Unknown", ISBLANK(M4)), "Missing ship_mode", IF(OR(ISBLANK(B4), ISBLANK(C4)), "Missing Date", IF(OR(ISTEXT(B4), ISTEXT(C4)), "Text Value Not Recognized as Date", IF(C4 < B4, "Invalid shipping record", IF(P4 < 0, "Invalid", IF(P4 > 0.7, "Invalid", "Valid")))))))) -> Valid | AD4: =IF(ABS(Q4 - W4) > 0.01, 1, 0) -> 1 | AE4: =IF(ABS(S4 - X4) > 0.01, 1, 0) -> 1 | AH4: =PROPER(TRIM(E4)) -> Isha Nair | AI4: =PROPER(TRIM(F4)) -> Consumer | AJ4: =PROPER(TRIM(G4)) -> East | AK4: =PROPER(TRIM(H4)) -> Odisha | AL4: =PROPER(TRIM(I4)) -> Bhubaneswar | AM4: =PROPER(TRIM(J4)) -> Office Supplies | AN4: =PROPER(TRIM(K4)) -> Art | AO4: =PROPER(TRIM(M4)) -> First Class | AP4: =PROPER(TRIM(T4)) -> Paid | AQ4: =PROPER(TRIM(U4)) -> Completed
A5: ORD-2024-10004 | B5: 28-11-2024 | C5: 45625 | D5: CUST-3722 | E5: Arjun Bose | F5: Small Business | G5: South | H5: Telangana | I5: Hyderabad | J5: Furniture | K5: Furnishings | L5: Smart Furnishings 294 | M5: Standard Class | N5: 6 | O5: 1848.43 | P5: 0.25 | Q5: 8317.93 | R5: 6796.77 | S5: 1521.16 | T5: Paid | U5: Completed | V5: =IF(ISBLANK(P5), 0, P5) -> 0.25 | W5: =N5 * O5 * (1 - P5) -> 8317.935 | X5: =W5-R5 -> 1521.165 | Y5: =IFERROR(X5 / W5, 0) -> 0.18287772 | Z5: =IF(OR(ISBLANK(B5), ISBLANK(C5), ISTEXT(B5), ISTEXT(C5)), "", C5 - B5) | AA5: =MONTH(B5) -> #VALUE! | AB5: =YEAR(B5) -> #VALUE! | AC5: =IF(COUNTIF(A:A, A5) > 1, "Conflicting Duplicate Order ID", IF(OR(G5="Unknown", ISBLANK(G5)), "Missing region", IF(OR(M5="Unknown", ISBLANK(M5)), "Missing ship_mode", IF(OR(ISBLANK(B5), ISBLANK(C5)), "Missing Date", IF(OR(ISTEXT(B5), ISTEXT(C5)), "Text Value Not Recognized as Date", IF(C5 < B5, "Invalid shipping record", IF(P5 < 0, "Invalid", IF(P5 > 0.7, "Invalid", "Valid")))))))) -> Text Value Not Recognized as Date | AD5: =IF(ABS(Q5 - W5) > 0.01, 1, 0) -> 0 | AE5: =IF(ABS(S5 - X5) > 0.01, 1, 0) -> 0 | AH5: =PROPER(TRIM(E5)) -> Arjun Bose | AI5: =PROPER(TRIM(F5)) -> Small Business | AJ5: =PROPER(TRIM(G5)) -> South | AK5: =PROPER(TRIM(H5)) -> Telangana | AL5: =PROPER(TRIM(I5)) -> Hyderabad | AM5: =PROPER(TRIM(J5)) -> Furniture | AN5: =PROPER(TRIM(K5)) -> Furnishings | AO5: =PROPER(TRIM(M5)) -> Standard Class | AP5: =PROPER(TRIM(T5)) -> Paid | AQ5: =PROPER(TRIM(U5)) -> Completed
A6: ORD-2025-10005 | B6: 45898 | C6: 45901 | D6: CUST-8130 | E6: Ananya Rao | F6: Small Business | G6: West | H6: Maharashtra | I6: Mumbai | J6: Furniture | K6: Chairs | L6: Elite Chairs 543 | M6: First Class | N6: 7 | O6: 2973.76 | P6: 0 | Q6: 20816.32 | R6: 17705.37 | S6: 3110.95 | T6: Paid | U6: Cancelled | V6: =IF(ISBLANK(P6), 0, P6) -> 0 | W6: =N6 * O6 * (1 - P6) -> 20816.32 | X6: =W6-R6 -> 3110.95 | Y6: =IFERROR(X6 / W6, 0) -> 0.14944764 | Z6: =IF(OR(ISBLANK(B6), ISBLANK(C6), ISTEXT(B6), ISTEXT(C6)), "", C6 - B6) -> 3 | AA6: =MONTH(B6) -> 8 | AB6: =YEAR(B6) -> 2025 | AC6: =IF(COUNTIF(A:A, A6) > 1, "Conflicting Duplicate Order ID", IF(OR(G6="Unknown", ISBLANK(G6)), "Missing region", IF(OR(M6="Unknown", ISBLANK(M6)), "Missing ship_mode", IF(OR(ISBLANK(B6), ISBLANK(C6)), "Missing Date", IF(OR(ISTEXT(B6), ISTEXT(C6)), "Text Value Not Recognized as Date", IF(C6 < B6, "Invalid shipping record", IF(P6 < 0, "Invalid", IF(P6 > 0.7, "Invalid", "Valid")))))))) -> Valid | AD6: =IF(ABS(Q6 - W6) > 0.01, 1, 0) -> 0 | AE6: =IF(ABS(S6 - X6) > 0.01, 1, 0) -> 0 | AH6: =PROPER(TRIM(E6)) -> Ananya Rao | AI6: =PROPER(TRIM(F6)) -> Small Business | AJ6: =PROPER(TRIM(G6)) -> West | AK6: =PROPER(TRIM(H6)) -> Maharashtra | AL6: =PROPER(TRIM(I6)) -> Mumbai | AM6: =PROPER(TRIM(J6)) -> Furniture | AN6: =PROPER(TRIM(K6)) -> Chairs | AO6: =PROPER(TRIM(M6)) -> First Class | AP6: =PROPER(TRIM(T6)) -> Paid | AQ6: =PROPER(TRIM(U6)) -> Cancelled
A7: ORD-2024-10006 | B7: 45436 | C7: 28-05-2024 | D7: CUST-6056 | E7: Vikram Iyer | F7: Small Business | G7: West | H7: Madhya Pradesh | I7: Indore | J7: Technology | K7: Accessories | L7: Pro Accessories 821 | M7: Same Day | N7: 3 | O7: 1053.11 | P7: 0.2 | Q7: 2527.46 | R7: 1533.58 | S7: 993.88 | T7: Paid | U7: Completed | V7: =IF(ISBLANK(P7), 0, P7) -> 0.2 | W7: =N7 * O7 * (1 - P7) -> 2527.464 | X7: =W7-R7 -> 993.884 | Y7: =IFERROR(X7 / W7, 0) -> 0.39323369 | Z7: =IF(OR(ISBLANK(B7), ISBLANK(C7), ISTEXT(B7), ISTEXT(C7)), "", C7 - B7) | AA7: =MONTH(B7) -> 5 | AB7: =YEAR(B7) -> 2024 | AC7: =IF(COUNTIF(A:A, A7) > 1, "Conflicting Duplicate Order ID", IF(OR(G7="Unknown", ISBLANK(G7)), "Missing region", IF(OR(M7="Unknown", ISBLANK(M7)), "Missing ship_mode", IF(OR(ISBLANK(B7), ISBLANK(C7)), "Missing Date", IF(OR(ISTEXT(B7), ISTEXT(C7)), "Text Value Not Recognized as Date", IF(C7 < B7, "Invalid shipping record", IF(P7 < 0, "Invalid", IF(P7 > 0.7, "Invalid", "Valid")))))))) -> Text Value Not Recognized as Date | AD7: =IF(ABS(Q7 - W7) > 0.01, 1, 0) -> 0 | AE7: =IF(ABS(S7 - X7) > 0.01, 1, 0) -> 0 | AH7: =PROPER(TRIM(E7)) -> Vikram Iyer | AI7: =PROPER(TRIM(F7)) -> Small Business | AJ7: =PROPER(TRIM(G7)) -> West | AK7: =PROPER(TRIM(H7)) -> Madhya Pradesh | AL7: =PROPER(TRIM(I7)) -> Indore | AM7: =PROPER(TRIM(J7)) -> Technology | AN7: =PROPER(TRIM(K7)) -> Accessories | AO7: =PROPER(TRIM(M7)) -> Same Day | AP7: =PROPER(TRIM(T7)) -> Paid | AQ7: =PROPER(TRIM(U7)) -> Completed
A8: ORD-2025-10007 | B8: 45757 | C8: 45763 | D8: CUST-3656 | E8: Neha Gupta | F8: Consumer | G8: East | H8: Odisha | I8: Bhubaneswar | J8: Technology | K8: Copiers | L8: Eco Copiers 790 | M8: Standard Class | N8: 4 | O8: 1719.87 | P8: 0.15 | Q8: 5847.56 | R8: 4727.25 | S8: 1120.31 | T8: Paid | U8: Completed | V8: =IF(ISBLANK(P8), 0, P8) -> 0.15 | W8: =N8 * O8 * (1 - P8) -> 5847.558 | X8: =W8-R8 -> 1120.308 | Y8: =IFERROR(X8 / W8, 0) -> 0.19158562 | Z8: =IF(OR(ISBLANK(B8), ISBLANK(C8), ISTEXT(B8), ISTEXT(C8)), "", C8 - B8) -> 6 | AA8: =MONTH(B8) -> 4 | AB8: =YEAR(B8) -> 2025 | AC8: =IF(COUNTIF(A:A, A8) > 1, "Conflicting Duplicate Order ID", IF(OR(G8="Unknown", ISBLANK(G8)), "Missing region", IF(OR(M8="Unknown", ISBLANK(M8)), "Missing ship_mode", IF(OR(ISBLANK(B8), ISBLANK(C8)), "Missing Date", IF(OR(ISTEXT(B8), ISTEXT(C8)), "Text Value Not Recognized as Date", IF(C8 < B8, "Invalid shipping record", IF(P8 < 0, "Invalid", IF(P8 > 0.7, "Invalid", "Valid")))))))) -> Conflicting Duplicate Order ID | AD8: =IF(ABS(Q8 - W8) > 0.01, 1, 0) -> 0 | AE8: =IF(ABS(S8 - X8) > 0.01, 1, 0) -> 0 | AH8: =PROPER(TRIM(E8)) -> Neha Gupta | AI8: =PROPER(TRIM(F8)) -> Consumer | AJ8: =PROPER(TRIM(G8)) -> East | AK8: =PROPER(TRIM(H8)) -> Odisha | AL8: =PROPER(TRIM(I8)) -> Bhubaneswar | AM8: =PROPER(TRIM(J8)) -> Technology | AN8: =PROPER(TRIM(K8)) -> Copiers | AO8: =PROPER(TRIM(M8)) -> Standard Class | AP8: =PROPER(TRIM(T8)) -> Paid | AQ8: =PROPER(TRIM(U8)) -> Completed
A9: ORD-2025-10008 | B9: 45711 | C9: 26-02-2025 | D9: CUST-4683 | E9: Isha Nair | F9: Small Business | G9: South | H9: Andhra Pradesh | I9: Vijayawada | J9: Office Supplies | K9: Art | L9: Eco Art 848 | M9: First Class | N9: 1 | O9: 2980.71 | P9: 0 | Q9: 2980.71 | R9: 2357.22 | S9: 623.49 | T9: Paid | U9: Completed | V9: =IF(ISBLANK(P9), 0, P9) -> 0 | W9: =N9 * O9 * (1 - P9) -> 2980.71 | X9: =W9-R9 -> 623.49 | Y9: =IFERROR(X9 / W9, 0) -> 0.209175 | Z9: =IF(OR(ISBLANK(B9), ISBLANK(C9), ISTEXT(B9), ISTEXT(C9)), "", C9 - B9) | AA9: =MONTH(B9) -> 2 | AB9: =YEAR(B9) -> 2025 | AC9: =IF(COUNTIF(A:A, A9) > 1, "Conflicting Duplicate Order ID", IF(OR(G9="Unknown", ISBLANK(G9)), "Missing region", IF(OR(M9="Unknown", ISBLANK(M9)), "Missing ship_mode", IF(OR(ISBLANK(B9), ISBLANK(C9)), "Missing Date", IF(OR(ISTEXT(B9), ISTEXT(C9)), "Text Value Not Recognized as Date", IF(C9 < B9, "Invalid shipping record", IF(P9 < 0, "Invalid", IF(P9 > 0.7, "Invalid", "Valid")))))))) -> Text Value Not Recognized as Date | AD9: =IF(ABS(Q9 - W9) > 0.01, 1, 0) -> 0 | AE9: =IF(ABS(S9 - X9) > 0.01, 1, 0) -> 0 | AH9: =PROPER(TRIM(E9)) -> Isha Nair | AI9: =PROPER(TRIM(F9)) -> Small Business | AJ9: =PROPER(TRIM(G9)) -> South | AK9: =PROPER(TRIM(H9)) -> Andhra Pradesh | AL9: =PROPER(TRIM(I9)) -> Vijayawada | AM9: =PROPER(TRIM(J9)) -> Office Supplies | AN9: =PROPER(TRIM(K9)) -> Art | AO9: =PROPER(TRIM(M9)) -> First Class | AP9: =PROPER(TRIM(T9)) -> Paid | AQ9: =PROPER(TRIM(U9)) -> Completed
A10: ORD-2024-10009 | B10: 45601 | C10: 45606 | D10: CUST-2598 | E10: Aditi Sen | F10: Corporate | G10: South | H10: Telangana | I10: Hyderabad | J10: Office Supplies | K10: Labels | L10: Classic Labels 815 | M10: First Class | N10: 8 | O10: 3134.2 | P10: 0 | Q10: 25073.6 | R10: 17347.23 | S10: 7726.37 | T10: Paid | U10: Completed | V10: =IF(ISBLANK(P10), 0, P10) -> 0 | W10: =N10 * O10 * (1 - P10) -> 25073.6 | X10: =W10-R10 -> 7726.37 | Y10: =IFERROR(X10 / W10, 0) -> 0.30814761 | Z10: =IF(OR(ISBLANK(B10), ISBLANK(C10), ISTEXT(B10), ISTEXT(C10)), "", C10 - B10) -> 5 | AA10: =MONTH(B10) -> 11 | AB10: =YEAR(B10) -> 2024 | AC10: =IF(COUNTIF(A:A, A10) > 1, "Conflicting Duplicate Order ID", IF(OR(G10="Unknown", ISBLANK(G10)), "Missing region", IF(OR(M10="Unknown", ISBLANK(M10)), "Missing ship_mode", IF(OR(ISBLANK(B10), ISBLANK(C10)), "Missing Date", IF(OR(ISTEXT(B10), ISTEXT(C10)), "Text Value Not Recognized as Date", IF(C10 < B10, "Invalid shipping record", IF(P10 < 0, "Invalid", IF(P10 > 0.7, "Invalid", "Valid")))))))) -> Valid | AD10: =IF(ABS(Q10 - W10) > 0.01, 1, 0) -> 0 | AE10: =IF(ABS(S10 - X10) > 0.01, 1, 0) -> 0 | AH10: =PROPER(TRIM(E10)) -> Aditi Sen | AI10: =PROPER(TRIM(F10)) -> Corporate | AJ10: =PROPER(TRIM(G10)) -> South | AK10: =PROPER(TRIM(H10)) -> Telangana | AL10: =PROPER(TRIM(I10)) -> Hyderabad | AM10: =PROPER(TRIM(J10)) -> Office Supplies | AN10: =PROPER(TRIM(K10)) -> Labels | AO10: =PROPER(TRIM(M10)) -> First Class | AP10: =PROPER(TRIM(T10)) -> Paid | AQ10: =PROPER(TRIM(U10)) -> Completed
A11: ORD-2025-10010 | B11: 45847 | C11: 45912 | D11: CUST-2483 | E11: Mira Das | F11: Home Office | G11: South | H11: Telangana | I11: Hyderabad | J11: Office Supplies | K11: Paper | L11: Pro Paper 622 | M11: Second Class | N11: 9 | O11: 852.04 | P11: 0.2 | Q11: 6134.69 | R11: 3800.19 | S11: 2334.5 | T11: Paid | U11: Completed | V11: =IF(ISBLANK(P11), 0, P11) -> 0.2 | W11: =N11 * O11 * (1 - P11) -> 6134.688 | X11: =W11-R11 -> 2334.498 | Y11: =IFERROR(X11 / W11, 0) -> 0.38054062 | Z11: =IF(OR(ISBLANK(B11), ISBLANK(C11), ISTEXT(B11), ISTEXT(C11)), "", C11 - B11) -> 65 | AA11: =MONTH(B11) -> 7 | AB11: =YEAR(B11) -> 2025 | AC11: =IF(COUNTIF(A:A, A11) > 1, "Conflicting Duplicate Order ID", IF(OR(G11="Unknown", ISBLANK(G11)), "Missing region", IF(OR(M11="Unknown", ISBLANK(M11)), "Missing ship_mode", IF(OR(ISBLANK(B11), ISBLANK(C11)), "Missing Date", IF(OR(ISTEXT(B11), ISTEXT(C11)), "Text Value Not Recognized as Date", IF(C11 < B11, "Invalid shipping record", IF(P11 < 0, "Invalid", IF(P11 > 0.7, "Invalid", "Valid")))))))) -> Valid | AD11: =IF(ABS(Q11 - W11) > 0.01, 1, 0) -> 0 | AE11: =IF(ABS(S11 - X11) > 0.01, 1, 0) -> 0 | AH11: =PROPER(TRIM(E11)) -> Mira Das | AI11: =PROPER(TRIM(F11)) -> Home Office | AJ11: =PROPER(TRIM(G11)) -> South | AK11: =PROPER(TRIM(H11)) -> Telangana | AL11: =PROPER(TRIM(I11)) -> Hyderabad | AM11: =PROPER(TRIM(J11)) -> Office Supplies | AN11: =PROPER(TRIM(K11)) -> Paper | AO11: =PROPER(TRIM(M11)) -> Second Class | AP11: =PROPER(TRIM(T11)) -> Paid | AQ11: =PROPER(TRIM(U11)) -> Completed
A12: ORD-2025-10011 | B12: 45797 | C12: 45797 | D12: CUST-8092 | E12: Ananya Rao | F12: Corporate | G12: East | H12: West Bengal | I12: Kolkata | J12: Office Supplies | K12: Labels | L12: Prime Labels 644 | M12: Second Class | N12: 3 | O12: 3534.83 | P12: 0.05 | Q12: 10074.27 | R12: 6048.27 | S12: 4026 | T12: Refunded | U12: Returned | V12: =IF(ISBLANK(P12), 0, P12) -> 0.05 | W12: =N12 * O12 * (1 - P12) -> 10074.265 | X12: =W12-R12 -> 4025.9955 | Y12: =IFERROR(X12 / W12, 0) -> 0.39963167 | Z12: =IF(OR(ISBLANK(B12), ISBLANK(C12), ISTEXT(B12), ISTEXT(C12)), "", C12 - B12) -> 0 | AA12: =MONTH(B12) -> 5 | AB12: =YEAR(B12) -> 2025 | AC12: =IF(COUNTIF(A:A, A12) > 1, "Conflicting Duplicate Order ID", IF(OR(G12="Unknown", ISBLANK(G12)), "Missing region", IF(OR(M12="Unknown", ISBLANK(M12)), "Missing ship_mode", IF(OR(ISBLANK(B12), ISBLANK(C12)), "Missing Date", IF(OR(ISTEXT(B12), ISTEXT(C12)), "Text Value Not Recognized as Date", IF(C12 < B12, "Invalid shipping record", IF(P12 < 0, "Invalid", IF(P12 > 0.7, "Invalid", "Valid")))))))) -> Valid | AD12: =IF(ABS(Q12 - W12) > 0.01, 1, 0) -> 0 | AE12: =IF(ABS(S12 - X12) > 0.01, 1, 0) -> 0 | AH12: =PROPER(TRIM(E12)) -> Ananya Rao | AI12: =PROPER(TRIM(F12)) -> Corporate | AJ12: =PROPER(TRIM(G12)) -> East | AK12: =PROPER(TRIM(H12)) -> West Bengal | AL12: =PROPER(TRIM(I12)) -> Kolkata | AM12: =PROPER(TRIM(J12)) -> Office Supplies | AN12: =PROPER(TRIM(K12)) -> Labels | AO12: =PROPER(TRIM(M12)) -> Second Class | AP12: =PROPER(TRIM(T12)) -> Refunded | AQ12: =PROPER(TRIM(U12)) -> Returned
A13: ORD-2024-10012 | B13: 45495 | C13: 23-07-2024 | D13: CUST-6528 | E13: Vikram Iyer | F13: Small Business | G13: East | H13: Odisha | I13: Bhubaneswar | J13: Technology | K13: Accessories | L13: Smart Accessories 603 | M13: Same Day | N13: 6 | O13: 2005.95 | P13: 0.2 | Q13: 9628.56 | R13: 8038.59 | S13: 1589.97 | T13: Paid | U13: Completed | V13: =IF(ISBLANK(P13), 0, P13) -> 0.2 | W13: =N13 * O13 * (1 - P13) -> 9628.56 | X13: =W13-R13 -> 1589.97 | Y13: =IFERROR(X13 / W13, 0) -> 0.16513061 | Z13: =IF(OR(ISBLANK(B13), ISBLANK(C13), ISTEXT(B13), ISTEXT(C13)), "", C13 - B13) | AA13: =MONTH(B13) -> 7 | AB13: =YEAR(B13) -> 2024 | AC13: =IF(COUNTIF(A:A, A13) > 1, "Conflicting Duplicate Order ID", IF(OR(G13="Unknown", ISBLANK(G13)), "Missing region", IF(OR(M13="Unknown", ISBLANK(M13)), "Missing ship_mode", IF(OR(ISBLANK(B13), ISBLANK(C13)), "Missing Date", IF(OR(ISTEXT(B13), ISTEXT(C13)), "Text Value Not Recognized as Date", IF(C13 < B13, "Invalid shipping record", IF(P13 < 0, "Invalid", IF(P13 > 0.7, "Invalid", "Valid")))))))) -> Text Value Not Recognized as Date | AD13: =IF(ABS(Q13 - W13) > 0.01, 1, 0) -> 0 | AE13: =IF(ABS(S13 - X13) > 0.01, 1, 0) -> 0 | AH13: =PROPER(TRIM(E13)) -> Vikram Iyer | AI13: =PROPER(TRIM(F13)) -> Small Business | AJ13: =PROPER(TRIM(G13)) -> East | AK13: =PROPER(TRIM(H13)) -> Odisha | AL13: =PROPER(TRIM(I13)) -> Bhubaneswar | AM13: =PROPER(TRIM(J13)) -> Technology | AN13: =PROPER(TRIM(K13)) -> Accessories | AO13: =PROPER(TRIM(M13)) -> Same Day | AP13: =PROPER(TRIM(T13)) -> Paid | AQ13: =PROPER(TRIM(U13)) -> Completed
A14: ORD-2024-10013 | B14: 45646 | C14: 45647 | D14: CUST-2648 | E14: Ananya Rao | F14: Corporate | G14: West | H14: Rajasthan | I14: Udaipur | J14: Office Supplies | K14: Paper | L14: Pro Paper 481 | M14: First Class | N14: 1 | O14: 702.14 | P14: 0.15 | Q14: 596.82 | R14: 380.25 | S14: 216.57 | T14: Pending | U14: Returned | V14: =IF(ISBLANK(P14), 0, P14) -> 0.15 | W14: =N14 * O14 * (1 - P14) -> 596.819 | X14: =W14-R14 -> 216.569 | Y14: =IFERROR(X14 / W14, 0) -> 0.36287216 | Z14: =IF(OR(ISBLANK(B14), ISBLANK(C14), ISTEXT(B14), ISTEXT(C14)), "", C14 - B14) -> 1 | AA14: =MONTH(B14) -> 12 | AB14: =YEAR(B14) -> 2024 | AC14: =IF(COUNTIF(A:A, A14) > 1, "Conflicting Duplicate Order ID", IF(OR(G14="Unknown", ISBLANK(G14)), "Missing region", IF(OR(M14="Unknown", ISBLANK(M14)), "Missing ship_mode", IF(OR(ISBLANK(B14), ISBLANK(C14)), "Missing Date", IF(OR(ISTEXT(B14), ISTEXT(C14)), "Text Value Not Recognized as Date", IF(C14 < B14, "Invalid shipping record", IF(P14 < 0, "Invalid", IF(P14 > 0.7, "Invalid", "Valid")))))))) -> Valid | AD14: =IF(ABS(Q14 - W14) > 0.01, 1, 0) -> 0 | AE14: =IF(ABS(S14 - X14) > 0.01, 1, 0) -> 0 | AH14: =PROPER(TRIM(E14)) -> Ananya Rao | AI14: =PROPER(TRIM(F14)) -> Corporate | AJ14: =PROPER(TRIM(G14)) -> West | AK14: =PROPER(TRIM(H14)) -> Rajasthan | AL14: =PROPER(TRIM(I14)) -> Udaipur | AM14: =PROPER(TRIM(J14)) -> Office Supplies | AN14: =PROPER(TRIM(K14)) -> Paper | AO14: =PROPER(TRIM(M14)) -> First Class | AP14: =PROPER(TRIM(T14)) -> Pending | AQ14: =PROPER(TRIM(U14)) -> Returned
A15: ORD-2025-10014 | B15: 45942 | C15: 16-10-2025 | D15: CUST-7482 | E15: Priya Menon | F15: Small Business | G15: West | H15: Maharashtra | I15: Mumbai | J15: Office Supplies | K15: Art | L15: Smart Art 795 | M15: Second Class | N15: 7 | O15: 3964.72 | P15: 0.05 | Q15: 26365.39 | R15: 22306.24 | S15: 4059.15 | T15: Paid | U15: Completed | V15: =IF(ISBLANK(P15), 0, P15) -> 0.05 | W15: =N15 * O15 * (1 - P15) -> 26365.388 | X15: =W15-R15 -> 4059.148 | Y15: =IFERROR(X15 / W15, 0) -> 0.15395745 | Z15: =IF(OR(ISBLANK(B15), ISBLANK(C15), ISTEXT(B15), ISTEXT(C15)), "", C15 - B15) | AA15: =MONTH(B15) -> 10 | AB15: =YEAR(B15) -> 2025 | AC15: =IF(COUNTIF(A:A, A15) > 1, "Conflicting Duplicate Order ID", IF(OR(G15="Unknown", ISBLANK(G15)), "Missing region", IF(OR(M15="Unknown", ISBLANK(M15)), "Missing ship_mode", IF(OR(ISBLANK(B15), ISBLANK(C15)), "Missing Date", IF(OR(ISTEXT(B15), ISTEXT(C15)), "Text Value Not Recognized as Date", IF(C15 < B15, "Invalid shipping record", IF(P15 < 0, "Invalid", IF(P15 > 0.7, "Invalid", "Valid")))))))) -> Text Value Not Recognized as Date | AD15: =IF(ABS(Q15 - W15) > 0.01, 1, 0) -> 0 | AE15: =IF(ABS(S15 - X15) > 0.01, 1, 0) -> 0 | AH15: =PROPER(TRIM(E15)) -> Priya Menon | AI15: =PROPER(TRIM(F15)) -> Small Business | AJ15: =PROPER(TRIM(G15)) -> West | AK15: =PROPER(TRIM(H15)) -> Maharashtra | AL15: =PROPER(TRIM(I15)) -> Mumbai | AM15: =PROPER(TRIM(J15)) -> Office Supplies | AN15: =PROPER(TRIM(K15)) -> Art | AO15: =PROPER(TRIM(M15)) -> Second Class | AP15: =PROPER(TRIM(T15)) -> Paid | AQ15: =PROPER(TRIM(U15)) -> Completed
A16: ORD-2024-10015 | B16: 45653 | C16: 45654 | D16: CUST-4912 | E16: Rahul Verma | F16: Consumer | G16: West | H16: Rajasthan | I16: Udaipur | J16: Technology | K16: Copiers | L16: Max Copiers 983 | M16: Standard Class | N16: 2 | O16: 2737.83 | P16: 0.25 | Q16: 4106.74 | R16: 2666.3 | S16: 1440.44 | T16: Paid | U16: Completed | V16: =IF(ISBLANK(P16), 0, P16) -> 0.25 | W16: =N16 * O16 * (1 - P16) -> 4106.745 | X16: =W16-R16 -> 1440.445 | Y16: =IFERROR(X16 / W16, 0) -> 0.35075102 | Z16: =IF(OR(ISBLANK(B16), ISBLANK(C16), ISTEXT(B16), ISTEXT(C16)), "", C16 - B16) -> 1 | AA16: =MONTH(B16) -> 12 | AB16: =YEAR(B16) -> 2024 | AC16: =IF(COUNTIF(A:A, A16) > 1, "Conflicting Duplicate Order ID", IF(OR(G16="Unknown", ISBLANK(G16)), "Missing region", IF(OR(M16="Unknown", ISBLANK(M16)), "Missing ship_mode", IF(OR(ISBLANK(B16), ISBLANK(C16)), "Missing Date", IF(OR(ISTEXT(B16), ISTEXT(C16)), "Text Value Not Recognized as Date", IF(C16 < B16, "Invalid shipping record", IF(P16 < 0, "Invalid", IF(P16 > 0.7, "Invalid", "Valid")))))))) -> Valid | AD16: =IF(ABS(Q16 - W16) > 0.01, 1, 0) -> 0 | AE16: =IF(ABS(S16 - X16) > 0.01, 1, 0) -> 0 | AH16: =PROPER(TRIM(E16)) -> Rahul Verma | AI16: =PROPER(TRIM(F16)) -> Consumer | AJ16: =PROPER(TRIM(G16)) -> West | AK16: =PROPER(TRIM(H16)) -> Rajasthan | AL16: =PROPER(TRIM(I16)) -> Udaipur | AM16: =PROPER(TRIM(J16)) -> Technology | AN16: =PROPER(TRIM(K16)) -> Copiers | AO16: =PROPER(TRIM(M16)) -> Standard Class | AP16: =PROPER(TRIM(T16)) -> Paid | AQ16: =PROPER(TRIM(U16)) -> Completed
A17: ORD-2024-10016 | B17: 45482 | C17: 45482 | D17: CUST-7656 | E17: Karan Malhotra | F17: Small Business | G17: North | H17: Punjab | I17: Ludhiana | J17: Office Supplies | K17: Storage | L17: Classic Storage 198 | M17: Second Class | N17: 6 | O17: 3965.76 | P17: 0 | Q17: 23794.56 | R17: 15698.47 | S17: 8096.09 | T17: Paid | U17: Completed | V17: =IF(ISBLANK(P17), 0, P17) -> 0 | W17: =N17 * O17 * (1 - P17) -> 23794.56 | X17: =W17-R17 -> 8096.09 | Y17: =IFERROR(X17 / W17, 0) -> 0.34024962 | Z17: =IF(OR(ISBLANK(B17), ISBLANK(C17), ISTEXT(B17), ISTEXT(C17)), "", C17 - B17) -> 0 | AA17: =MONTH(B17) -> 7 | AB17: =YEAR(B17) -> 2024 | AC17: =IF(COUNTIF(A:A, A17) > 1, "Conflicting Duplicate Order ID", IF(OR(G17="Unknown", ISBLANK(G17)), "Missing region", IF(OR(M17="Unknown", ISBLANK(M17)), "Missing ship_mode", IF(OR(ISBLANK(B17), ISBLANK(C17)), "Missing Date", IF(OR(ISTEXT(B17), ISTEXT(C17)), "Text Value Not Recognized as Date", IF(C17 < B17, "Invalid shipping record", IF(P17 < 0, "Invalid", IF(P17 > 0.7, "Invalid", "Valid")))))))) -> Valid | AD17: =IF(ABS(Q17 - W17) > 0.01, 1, 0) -> 0 | AE17: =IF(ABS(S17 - X17) > 0.01, 1, 0) -> 0 | AH17: =PROPER(TRIM(E17)) -> Karan Malhotra | AI17: =PROPER(TRIM(F17)) -> Small Business | AJ17: =PROPER(TRIM(G17)) -> North | AK17: =PROPER(TRIM(H17)) -> Punjab | AL17: =PROPER(TRIM(I17)) -> Ludhiana | AM17: =PROPER(TRIM(J17)) -> Office Supplies | AN17: =PROPER(TRIM(K17)) -> Storage | AO17: =PROPER(TRIM(M17)) -> Second Class | AP17: =PROPER(TRIM(T17)) -> Paid | AQ17: =PROPER(TRIM(U17)) -> Completed
A18: ORD-2024-10017 | B18: 45420 | C18: 15-05-2024 | D18: CUST-6214 | E18: Aarav Sharma | F18: Consumer | G18: South | H18: Telangana | I18: Hyderabad | J18: Office Supplies | K18: Art | L18: Basic Art 204 | M18: First Class | N18: 4 | O18: 3323.51 | P18: 0.25 | Q18: 9970.53 | R18: 5668.17 | S18: 4302.36 | T18: Paid | U18: Completed | V18: =IF(ISBLANK(P18), 0, P18) -> 0.25 | W18: =N18 * O18 * (1 - P18) -> 9970.53 | X18: =W18-R18 -> 4302.36 | Y18: =IFERROR(X18 / W18, 0) -> 0.43150765 | Z18: =IF(OR(ISBLANK(B18), ISBLANK(C18), ISTEXT(B18), ISTEXT(C18)), "", C18 - B18) | AA18: =MONTH(B18) -> 5 | AB18: =YEAR(B18) -> 2024 | AC18: =IF(COUNTIF(A:A, A18) > 1, "Conflicting Duplicate Order ID", IF(OR(G18="Unknown", ISBLANK(G18)), "Missing region", IF(OR(M18="Unknown", ISBLANK(M18)), "Missing ship_mode", IF(OR(ISBLANK(B18), ISBLANK(C18)), "Missing Date", IF(OR(ISTEXT(B18), ISTEXT(C18)), "Text Value Not Recognized as Date", IF(C18 < B18, "Invalid shipping record", IF(P18 < 0, "Invalid", IF(P18 > 0.7, "Invalid", "Valid")))))))) -> Text Value Not Recognized as Date | AD18: =IF(ABS(Q18 - W18) > 0.01, 1, 0) -> 0 | AE18: =IF(ABS(S18 - X18) > 0.01, 1, 0) -> 0 | AH18: =PROPER(TRIM(E18)) -> Aarav Sharma | AI18: =PROPER(TRIM(F18)) -> Consumer | AJ18: =PROPER(TRIM(G18)) -> South | AK18: =PROPER(TRIM(H18)) -> Telangana | AL18: =PROPER(TRIM(I18)) -> Hyderabad | AM18: =PROPER(TRIM(J18)) -> Office Supplies | AN18: =PROPER(TRIM(K18)) -> Art | AO18: =PROPER(TRIM(M18)) -> First Class | AP18: =PROPER(TRIM(T18)) -> Paid | AQ18: =PROPER(TRIM(U18)) -> Completed
A19: ORD-2024-10018 | B19: 45298 | C19: 45299 | D19: CUST-1626 | E19: Sneha Kapoor | F19: Small Business | G19: North | H19: Rajasthan | I19: Jaipur | J19: Furniture | K19: Furnishings | L19: Basic Furnishings 434 | M19: Same Day | N19: 5 | O19: 1526.78 | P19: 0 | Q19: 7633.9 | R19: 4706.91 | S19: 2926.99 | T19: Paid | U19: Completed | V19: =IF(ISBLANK(P19), 0, P19) -> 0 | W19: =N19 * O19 * (1 - P19) -> 7633.9 | X19: =W19-R19 -> 2926.99 | Y19: =IFERROR(X19 / W19, 0) -> 0.38342001 | Z19: =IF(OR(ISBLANK(B19), ISBLANK(C19), ISTEXT(B19), ISTEXT(C19)), "", C19 - B19) -> 1 | AA19: =MONTH(B19) -> 1 | AB19: =YEAR(B19) -> 2024 | AC19: =IF(COUNTIF(A:A, A19) > 1, "Conflicting Duplicate Order ID", IF(OR(G19="Unknown", ISBLANK(G19)), "Missing region", IF(OR(M19="Unknown", ISBLANK(M19)), "Missing ship_mode", IF(OR(ISBLANK(B19), ISBLANK(C19)), "Missing Date", IF(OR(ISTEXT(B19), ISTEXT(C19)), "Text Value Not Recognized as Date", IF(C19 < B19, "Invalid shipping record", IF(P19 < 0, "Invalid", IF(P19 > 0.7, "Invalid", "Valid")))))))) -> Valid | AD19: =IF(ABS(Q19 - W19) > 0.01, 1, 0) -> 0 | AE19: =IF(ABS(S19 - X19) > 0.01, 1, 0) -> 0 | AH19: =PROPER(TRIM(E19)) -> Sneha Kapoor | AI19: =PROPER(TRIM(F19)) -> Small Business | AJ19: =PROPER(TRIM(G19)) -> North | AK19: =PROPER(TRIM(H19)) -> Rajasthan | AL19: =PROPER(TRIM(I19)) -> Jaipur | AM19: =PROPER(TRIM(J19)) -> Furniture | AN19: =PROPER(TRIM(K19)) -> Furnishings | AO19: =PROPER(TRIM(M19)) -> Same Day | AP19: =PROPER(TRIM(T19)) -> Paid | AQ19: =PROPER(TRIM(U19)) -> Completed
A20: ORD-2025-10019 | B20: 45853 | C20: 17-07-2025 | D20: CUST-2110 | E20: Aarav Sharma | F20: Home Office | G20: North | H20: Uttar Pradesh | I20: Noida | J20: Technology | K20: Copiers | L20: Eco Copiers 755 | M20: First Class | N20: 2 | O20: 1997.99 | P20: 0 | Q20: 3995.98 | R20: 2633.2 | S20: 1362.78 | T20: Refunded | U20: Cancelled | V20: =IF(ISBLANK(P20), 0, P20) -> 0 | W20: =N20 * O20 * (1 - P20) -> 3995.98 | X20: =W20-R20 -> 1362.78 | Y20: =IFERROR(X20 / W20, 0) -> 0.34103774 | Z20: =IF(OR(ISBLANK(B20), ISBLANK(C20), ISTEXT(B20), ISTEXT(C20)), "", C20 - B20) | AA20: =MONTH(B20) -> 7 | AB20: =YEAR(B20) -> 2025 | AC20: =IF(COUNTIF(A:A, A20) > 1, "Conflicting Duplicate Order ID", IF(OR(G20="Unknown", ISBLANK(G20)), "Missing region", IF(OR(M20="Unknown", ISBLANK(M20)), "Missing ship_mode", IF(OR(ISBLANK(B20), ISBLANK(C20)), "Missing Date", IF(OR(ISTEXT(B20), ISTEXT(C20)), "Text Value Not Recognized as Date", IF(C20 < B20, "Invalid shipping record", IF(P20 < 0, "Invalid", IF(P20 > 0.7, "Invalid", "Valid")))))))) -> Text Value Not Recognized as Date | AD20: =IF(ABS(Q20 - W20) > 0.01, 1, 0) -> 0 | AE20: =IF(ABS(S20 - X20) > 0.01, 1, 0) -> 0 | AH20: =PROPER(TRIM(E20)) -> Aarav Sharma | AI20: =PROPER(TRIM(F20)) -> Home Office | AJ20: =PROPER(TRIM(G20)) -> North | AK20: =PROPER(TRIM(H20)) -> Uttar Pradesh | AL20: =PROPER(TRIM(I20)) -> Noida | AM20: =PROPER(TRIM(J20)) -> Technology | AN20: =PROPER(TRIM(K20)) -> Copiers | AO20: =PROPER(TRIM(M20)) -> First Class | AP20: =PROPER(TRIM(T20)) -> Refunded | AQ20: =PROPER(TRIM(U20)) -> Cancelled
A21: ORD-2024-10020 | B21: 45500 | C21: 45504 | D21: CUST-3186 | E21: Rohan Mehta | F21: Home Office | G21: West | H21: Madhya Pradesh | I21: Indore | J21: Office Supplies | K21: Storage | L21: Prime Storage 121 | M21: Second Class | N21: 3 | O21: 3887.94 | P21: -0.19 | Q21: 9331.06 | R21: 7529.31 | S21: 1801.75 | T21: Paid | U21: Completed | V21: =IF(ISBLANK(P21), 0, P21) -> -0.19 | W21: =N21 * O21 * (1 - P21) -> 13879.946 | X21: =W21-R21 -> 6350.6358 | Y21: =IFERROR(X21 / W21, 0) -> 0.45754039 | Z21: =IF(OR(ISBLANK(B21), ISBLANK(C21), ISTEXT(B21), ISTEXT(C21)), "", C21 - B21) -> 4 | AA21: =MONTH(B21) -> 7 | AB21: =YEAR(B21) -> 2024 | AC21: =IF(COUNTIF(A:A, A21) > 1, "Conflicting Duplicate Order ID", IF(OR(G21="Unknown", ISBLANK(G21)), "Missing region", IF(OR(M21="Unknown", ISBLANK(M21)), "Missing ship_mode", IF(OR(ISBLANK(B21), ISBLANK(C21)), "Missing Date", IF(OR(ISTEXT(B21), ISTEXT(C21)), "Text Value Not Recognized as Date", IF(C21 < B21, "Invalid shipping record", IF(P21 < 0, "Invalid", IF(P21 > 0.7, "Invalid", "Valid")))))))) -> Invalid | AD21: =IF(ABS(Q21 - W21) > 0.01, 1, 0) -> 1 | AE21: =IF(ABS(S21 - X21) > 0.01, 1, 0) -> 1 | AH21: =PROPER(TRIM(E21)) -> Rohan Mehta | AI21: =PROPER(TRIM(F21)) -> Home Office | AJ21: =PROPER(TRIM(G21)) -> West | AK21: =PROPER(TRIM(H21)) -> Madhya Pradesh | AL21: =PROPER(TRIM(I21)) -> Indore | AM21: =PROPER(TRIM(J21)) -> Office Supplies | AN21: =PROPER(TRIM(K21)) -> Storage | AO21: =PROPER(TRIM(M21)) -> Second Class | AP21: =PROPER(TRIM(T21)) -> Paid | AQ21: =PROPER(TRIM(U21)) -> Completed
A22: ORD-2025-10021 | B22: 21-01-2025 | C22: 45680 | D22: CUST-3190 | E22: Aditi Sen | F22: Home Office | G22: East | H22: Bihar | I22: Patna | J22: Technology | K22: Copiers | L22: Elite Copiers 233 | M22: First Class | N22: 5 | O22: 4373.06 | P22: 0.25 | Q22: 16398.98 | R22: 9556.52 | S22: 6842.46 | T22: Paid | U22: Completed | V22: =IF(ISBLANK(P22), 0, P22) -> 0.25 | W22: =N22 * O22 * (1 - P22) -> 16398.975 | X22: =W22-R22 -> 6842.455 | Y22: =IFERROR(X22 / W22, 0) -> 0.41724894 | Z22: =IF(OR(ISBLANK(B22), ISBLANK(C22), ISTEXT(B22), ISTEXT(C22)), "", C22 - B22) | AA22: =MONTH(B22) -> #VALUE! | AB22: =YEAR(B22) -> #VALUE! | AC22: =IF(COUNTIF(A:A, A22) > 1, "Conflicting Duplicate Order ID", IF(OR(G22="Unknown", ISBLANK(G22)), "Missing region", IF(OR(M22="Unknown", ISBLANK(M22)), "Missing ship_mode", IF(OR(ISBLANK(B22), ISBLANK(C22)), "Missing Date", IF(OR(ISTEXT(B22), ISTEXT(C22)), "Text Value Not Recognized as Date", IF(C22 < B22, "Invalid shipping record", IF(P22 < 0, "Invalid", IF(P22 > 0.7, "Invalid", "Valid")))))))) -> Text Value Not Recognized as Date | AD22: =IF(ABS(Q22 - W22) > 0.01, 1, 0) -> 0 | AE22: =IF(ABS(S22 - X22) > 0.01, 1, 0) -> 0 | AH22: =PROPER(TRIM(E22)) -> Aditi Sen | AI22: =PROPER(TRIM(F22)) -> Home Office | AJ22: =PROPER(TRIM(G22)) -> East | AK22: =PROPER(TRIM(H22)) -> Bihar | AL22: =PROPER(TRIM(I22)) -> Patna | AM22: =PROPER(TRIM(J22)) -> Technology | AN22: =PROPER(TRIM(K22)) -> Copiers | AO22: =PROPER(TRIM(M22)) -> First Class | AP22: =PROPER(TRIM(T22)) -> Paid | AQ22: =PROPER(TRIM(U22)) -> Completed
A23: ORD-2025-10022 | B23: 24-01-2025 | C23: 45687 | D23: CUST-3036 | E23: Sneha Kapoor | F23: Consumer | G23: West | H23: Madhya Pradesh | I23: Indore | J23: Furniture | K23: Furnishings | L23: Eco Furnishings 897 | M23: Second Class | N23: 4 | O23: 697.69 | P23: -0.23 | Q23: 2790.76 | R23: 2037.71 | S23: 753.05 | T23: Paid | U23: Completed | V23: =IF(ISBLANK(P23), 0, P23) -> -0.23 | W23: =N23 * O23 * (1 - P23) -> 3432.6348 | X23: =W23-R23 -> 1394.9248 | Y23: =IFERROR(X23 / W23, 0) -> 0.40637146 | Z23: =IF(OR(ISBLANK(B23), ISBLANK(C23), ISTEXT(B23), ISTEXT(C23)), "", C23 - B23) | AA23: =MONTH(B23) -> #VALUE! | AB23: =YEAR(B23) -> #VALUE! | AC23: =IF(COUNTIF(A:A, A23) > 1, "Conflicting Duplicate Order ID", IF(OR(G23="Unknown", ISBLANK(G23)), "Missing region", IF(OR(M23="Unknown", ISBLANK(M23)), "Missing ship_mode", IF(OR(ISBLANK(B23), ISBLANK(C23)), "Missing Date", IF(OR(ISTEXT(B23), ISTEXT(C23)), "Text Value Not Recognized as Date", IF(C23 < B23, "Invalid shipping record", IF(P23 < 0, "Invalid", IF(P23 > 0.7, "Invalid", "Valid")))))))) -> Text Value Not Recognized as Date | AD23: =IF(ABS(Q23 - W23) > 0.01, 1, 0) -> 1 | AE23: =IF(ABS(S23 - X23) > 0.01, 1, 0) -> 1 | AH23: =PROPER(TRIM(E23)) -> Sneha Kapoor | AI23: =PROPER(TRIM(F23)) -> Consumer | AJ23: =PROPER(TRIM(G23)) -> West | AK23: =PROPER(TRIM(H23)) -> Madhya Pradesh | AL23: =PROPER(TRIM(I23)) -> Indore | AM23: =PROPER(TRIM(J23)) -> Furniture | AN23: =PROPER(TRIM(K23)) -> Furnishings | AO23: =PROPER(TRIM(M23)) -> Second Class | AP23: =PROPER(TRIM(T23)) -> Paid | AQ23: =PROPER(TRIM(U23)) -> Completed
A24: ORD-2025-10023 | B24: 45676 | C24: 45678 | D24: CUST-3588 | E24: Mira Das | F24: Consumer | G24: South | H24: Telangana | I24: Hyderabad | J24: Office Supplies | K24: Binders | L24: Max Binders 355 | M24: Standard Class | N24: 8 | O24: 1219.34 | P24: 0.15 | Q24: 8291.51 | R24: 6685.03 | S24: 1606.48 | T24: Failed | U24: Returned | V24: =IF(ISBLANK(P24), 0, P24) -> 0.15 | W24: =N24 * O24 * (1 - P24) -> 8291.512 | X24: =W24-R24 -> 1606.482 | Y24: =IFERROR(X24 / W24, 0) -> 0.19375019 | Z24: =IF(OR(ISBLANK(B24), ISBLANK(C24), ISTEXT(B24), ISTEXT(C24)), "", C24 - B24) -> 2 | AA24: =MONTH(B24) -> 1 | AB24: =YEAR(B24) -> 2025 | AC24: =IF(COUNTIF(A:A, A24) > 1, "Conflicting Duplicate Order ID", IF(OR(G24="Unknown", ISBLANK(G24)), "Missing region", IF(OR(M24="Unknown", ISBLANK(M24)), "Missing ship_mode", IF(OR(ISBLANK(B24), ISBLANK(C24)), "Missing Date", IF(OR(ISTEXT(B24), ISTEXT(C24)), "Text Value Not Recognized as Date", IF(C24 < B24, "Invalid shipping record", IF(P24 < 0, "Invalid", IF(P24 > 0.7, "Invalid", "Valid")))))))) -> Valid | AD24: =IF(ABS(Q24 - W24) > 0.01, 1, 0) -> 0 | AE24: =IF(ABS(S24 - X24) > 0.01, 1, 0) -> 0 | AH24: =PROPER(TRIM(E24)) -> Mira Das | AI24: =PROPER(TRIM(F24)) -> Consumer | AJ24: =PROPER(TRIM(G24)) -> South | AK24: =PROPER(TRIM(H24)) -> Telangana | AL24: =PROPER(TRIM(I24)) -> Hyderabad | AM24: =PROPER(TRIM(J24)) -> Office Supplies | AN24: =PROPER(TRIM(K24)) -> Binders | AO24: =PROPER(TRIM(M24)) -> Standard Class | AP24: =PROPER(TRIM(T24)) -> Failed | AQ24: =PROPER(TRIM(U24)) -> Returned
A25: ORD-2025-10024 | B25: 45898 | C25: 31-08-2025 | D25: CUST-7098 | E25: Rahul Verma | F25: Home Office | G25: East | H25: Bihar | I25: Patna | J25: Furniture | K25: Bookcases | L25: Pro Bookcases 394 | M25: First Class | N25: 4 | O25: 1958.01 | P25: 0.2 | Q25: 6265.63 | R25: 4321.86 | S25: 1943.77 | T25: Paid | U25: Completed | V25: =IF(ISBLANK(P25), 0, P25) -> 0.2 | W25: =N25 * O25 * (1 - P25) -> 6265.632 | X25: =W25-R25 -> 1943.772 | Y25: =IFERROR(X25 / W25, 0) -> 0.3102276 | Z25: =IF(OR(ISBLANK(B25), ISBLANK(C25), ISTEXT(B25), ISTEXT(C25)), "", C25 - B25) | AA25: =MONTH(B25) -> 8 | AB25: =YEAR(B25) -> 2025 | AC25: =IF(COUNTIF(A:A, A25) > 1, "Conflicting Duplicate Order ID", IF(OR(G25="Unknown", ISBLANK(G25)), "Missing region", IF(OR(M25="Unknown", ISBLANK(M25)), "Missing ship_mode", IF(OR(ISBLANK(B25), ISBLANK(C25)), "Missing Date", IF(OR(ISTEXT(B25), ISTEXT(C25)), "Text Value Not Recognized as Date", IF(C25 < B25, "Invalid shipping record", IF(P25 < 0, "Invalid", IF(P25 > 0.7, "Invalid", "Valid")))))))) -> Text Value Not Recognized as Date | AD25: =IF(ABS(Q25 - W25) > 0.01, 1, 0) -> 0 | AE25: =IF(ABS(S25 - X25) > 0.01, 1, 0) -> 0 | AH25: =PROPER(TRIM(E25)) -> Rahul Verma | AI25: =PROPER(TRIM(F25)) -> Home Office | AJ25: =PROPER(TRIM(G25)) -> East | AK25: =PROPER(TRIM(H25)) -> Bihar | AL25: =PROPER(TRIM(I25)) -> Patna | AM25: =PROPER(TRIM(J25)) -> Furniture | AN25: =PROPER(TRIM(K25)) -> Bookcases | AO25: =PROPER(TRIM(M25)) -> First Class | AP25: =PROPER(TRIM(T25)) -> Paid | AQ25: =PROPER(TRIM(U25)) -> Completed
A26: ORD-2024-10025 | B26: 45355 | C26: 45352 | D26: CUST-1747 | E26: Diya Patel | F26: Consumer | G26: North | H26: Punjab | I26: Ludhiana | J26: Office Supplies | K26: Art | L26: Max Art 215 | M26: Standard Class | N26: 4 | O26: 4492.94 | P26: 0.25 | Q26: 13478.82 | R26: 10937.35 | S26: 2541.47 | T26: Pending | U26: Cancelled | V26: =IF(ISBLANK(P26), 0, P26) -> 0.25 | W26: =N26 * O26 * (1 - P26) -> 13478.82 | X26: =W26-R26 -> 2541.47 | Y26: =IFERROR(X26 / W26, 0) -> 0.18855286 | Z26: =IF(OR(ISBLANK(B26), ISBLANK(C26), ISTEXT(B26), ISTEXT(C26)), "", C26 - B26) -> -3 | AA26: =MONTH(B26) -> 3 | AB26: =YEAR(B26) -> 2024 | AC26: =IF(COUNTIF(A:A, A26) > 1, "Conflicting Duplicate Order ID", IF(OR(G26="Unknown", ISBLANK(G26)), "Missing region", IF(OR(M26="Unknown", ISBLANK(M26)), "Missing ship_mode", IF(OR(ISBLANK(B26), ISBLANK(C26)), "Missing Date", IF(OR(ISTEXT(B26), ISTEXT(C26)), "Text Value Not Recognized as Date", IF(C26 < B26, "Invalid shipping record", IF(P26 < 0, "Invalid", IF(P26 > 0.7, "Invalid", "Valid")))))))) -> Invalid shipping record | AD26: =IF(ABS(Q26 - W26) > 0.01, 1, 0) -> 0 | AE26: =IF(ABS(S26 - X26) > 0.01, 1, 0) -> 0 | AH26: =PROPER(TRIM(E26)) -> Diya Patel | AI26: =PROPER(TRIM(F26)) -> Consumer | AJ26: =PROPER(TRIM(G26)) -> North | AK26: =PROPER(TRIM(H26)) -> Punjab | AL26: =PROPER(TRIM(I26)) -> Ludhiana | AM26: =PROPER(TRIM(J26)) -> Office Supplies | AN26: =PROPER(TRIM(K26)) -> Art | AO26: =PROPER(TRIM(M26)) -> Standard Class | AP26: =PROPER(TRIM(T26)) -> Pending | AQ26: =PROPER(TRIM(U26)) -> Cancelled
A27: ORD-2024-10026 | B27: 45606 | C27: 45584 | D27: CUST-1731 | E27: Arjun Bose | F27: Corporate | G27: East | H27: Assam | I27: Guwahati | J27: Technology | K27: Accessories | L27: Classic Accessories 478 | M27: First Class | N27: 2 | O27: 4315.2 | P27: 0.15 | Q27: 7335.84 | R27: 4968.41 | S27: 2367.43 | T27: Paid | U27: Completed | V27: =IF(ISBLANK(P27), 0, P27) -> 0.15 | W27: =N27 * O27 * (1 - P27) -> 7335.84 | X27: =W27-R27 -> 2367.43 | Y27: =IFERROR(X27 / W27, 0) -> 0.32272105 | Z27: =IF(OR(ISBLANK(B27), ISBLANK(C27), ISTEXT(B27), ISTEXT(C27)), "", C27 - B27) -> -22 | AA27: =MONTH(B27) -> 11 | AB27: =YEAR(B27) -> 2024 | AC27: =IF(COUNTIF(A:A, A27) > 1, "Conflicting Duplicate Order ID", IF(OR(G27="Unknown", ISBLANK(G27)), "Missing region", IF(OR(M27="Unknown", ISBLANK(M27)), "Missing ship_mode", IF(OR(ISBLANK(B27), ISBLANK(C27)), "Missing Date", IF(OR(ISTEXT(B27), ISTEXT(C27)), "Text Value Not Recognized as Date", IF(C27 < B27, "Invalid shipping record", IF(P27 < 0, "Invalid", IF(P27 > 0.7, "Invalid", "Valid")))))))) -> Invalid shipping record | AD27: =IF(ABS(Q27 - W27) > 0.01, 1, 0) -> 0 | AE27: =IF(ABS(S27 - X27) > 0.01, 1, 0) -> 0 | AH27: =PROPER(TRIM(E27)) -> Arjun Bose | AI27: =PROPER(TRIM(F27)) -> Corporate | AJ27: =PROPER(TRIM(G27)) -> East | AK27: =PROPER(TRIM(H27)) -> Assam | AL27: =PROPER(TRIM(I27)) -> Guwahati | AM27: =PROPER(TRIM(J27)) -> Technology | AN27: =PROPER(TRIM(K27)) -> Accessories | AO27: =PROPER(TRIM(M27)) -> First Class | AP27: =PROPER(TRIM(T27)) -> Paid | AQ27: =PROPER(TRIM(U27)) -> Completed
A28: ORD-2024-10027 | B28: 23-11-2024 | C28: 45619 | D28: CUST-4401 | E28: Diya Patel | F28: Corporate | G28: North | H28: Uttar Pradesh | I28: Noida | J28: Technology | K28: Phones | L28: Pro Phones 243 | M28: Standard Class | N28: 4 | O28: 716.13 | P28: 0.1 | Q28: 2578.07 | R28: 1527.55 | S28: 1050.52 | T28: Paid | U28: Returned | V28: =IF(ISBLANK(P28), 0, P28) -> 0.1 | W28: =N28 * O28 * (1 - P28) -> 2578.068 | X28: =W28-R28 -> 1050.518 | Y28: =IFERROR(X28 / W28, 0) -> 0.40748266 | Z28: =IF(OR(ISBLANK(B28), ISBLANK(C28), ISTEXT(B28), ISTEXT(C28)), "", C28 - B28) | AA28: =MONTH(B28) -> #VALUE! | AB28: =YEAR(B28) -> #VALUE! | AC28: =IF(COUNTIF(A:A, A28) > 1, "Conflicting Duplicate Order ID", IF(OR(G28="Unknown", ISBLANK(G28)), "Missing region", IF(OR(M28="Unknown", ISBLANK(M28)), "Missing ship_mode", IF(OR(ISBLANK(B28), ISBLANK(C28)), "Missing Date", IF(OR(ISTEXT(B28), ISTEXT(C28)), "Text Value Not Recognized as Date", IF(C28 < B28, "Invalid shipping record", IF(P28 < 0, "Invalid", IF(P28 > 0.7, "Invalid", "Valid")))))))) -> Text Value Not Recognized as Date | AD28: =IF(ABS(Q28 - W28) > 0.01, 1, 0) -> 0 | AE28: =IF(ABS(S28 - X28) > 0.01, 1, 0) -> 0 | AH28: =PROPER(TRIM(E28)) -> Diya Patel | AI28: =PROPER(TRIM(F28)) -> Corporate | AJ28: =PROPER(TRIM(G28)) -> North | AK28: =PROPER(TRIM(H28)) -> Uttar Pradesh | AL28: =PROPER(TRIM(I28)) -> Noida | AM28: =PROPER(TRIM(J28)) -> Technology | AN28: =PROPER(TRIM(K28)) -> Phones | AO28: =PROPER(TRIM(M28)) -> Standard Class | AP28: =PROPER(TRIM(T28)) -> Paid | AQ28: =PROPER(TRIM(U28)) -> Returned
A29: ORD-2025-10028 | B29: 45929 | C29: 45787 | D29: CUST-9875 | E29: Arjun Bose | F29: Small Business | G29: South | H29: Karnataka | I29: Bengaluru | J29: Office Supplies | K29: Paper | L29: Basic Paper 613 | M29: Second Class | N29: 5 | O29: 1806.51 | P29: 0.25 | Q29: 6774.41 | R29: 4710.36 | S29: 2064.05 | T29: Failed | U29: Returned | V29: =IF(ISBLANK(P29), 0, P29) -> 0.25 | W29: =N29 * O29 * (1 - P29) -> 6774.4125 | X29: =W29-R29 -> 2064.0525 | Y29: =IFERROR(X29 / W29, 0) -> 0.30468362 | Z29: =IF(OR(ISBLANK(B29), ISBLANK(C29), ISTEXT(B29), ISTEXT(C29)), "", C29 - B29) -> -142 | AA29: =MONTH(B29) -> 9 | AB29: =YEAR(B29) -> 2025 | AC29: =IF(COUNTIF(A:A, A29) > 1, "Conflicting Duplicate Order ID", IF(OR(G29="Unknown", ISBLANK(G29)), "Missing region", IF(OR(M29="Unknown", ISBLANK(M29)), "Missing ship_mode", IF(OR(ISBLANK(B29), ISBLANK(C29)), "Missing Date", IF(OR(ISTEXT(B29), ISTEXT(C29)), "Text Value Not Recognized as Date", IF(C29 < B29, "Invalid shipping record", IF(P29 < 0, "Invalid", IF(P29 > 0.7, "Invalid", "Valid")))))))) -> Invalid shipping record | AD29: =IF(ABS(Q29 - W29) > 0.01, 1, 0) -> 0 | AE29: =IF(ABS(S29 - X29) > 0.01, 1, 0) -> 0 | AH29: =PROPER(TRIM(E29)) -> Arjun Bose | AI29: =PROPER(TRIM(F29)) -> Small Business | AJ29: =PROPER(TRIM(G29)) -> South | AK29: =PROPER(TRIM(H29)) -> Karnataka | AL29: =PROPER(TRIM(I29)) -> Bengaluru | AM29: =PROPER(TRIM(J29)) -> Office Supplies | AN29: =PROPER(TRIM(K29)) -> Paper | AO29: =PROPER(TRIM(M29)) -> Second Class | AP29: =PROPER(TRIM(T29)) -> Failed | AQ29: =PROPER(TRIM(U29)) -> Returned
A30: ORD-2024-10029 | B30: 45606 | C30: 18-10-2024 | D30: CUST-1569 | E30: Ananya Rao | F30: Home Office | G30: West | H30: Gujarat | I30: Ahmedabad | J30: Technology | K30: Phones | L30: Prime Phones 698 | M30: Second Class | N30: 2 | O30: 1942.22 | P30: 0.25 | Q30: 2913.33 | R30: 2122.33 | S30: 791 | T30: Refunded | U30: Cancelled | V30: =IF(ISBLANK(P30), 0, P30) -> 0.25 | W30: =N30 * O30 * (1 - P30) -> 2913.33 | X30: =W30-R30 -> 791 | Y30: =IFERROR(X30 / W30, 0) -> 0.27151061 | Z30: =IF(OR(ISBLANK(B30), ISBLANK(C30), ISTEXT(B30), ISTEXT(C30)), "", C30 - B30) | AA30: =MONTH(B30) -> 11 | AB30: =YEAR(B30) -> 2024 | AC30: =IF(COUNTIF(A:A, A30) > 1, "Conflicting Duplicate Order ID", IF(OR(G30="Unknown", ISBLANK(G30)), "Missing region", IF(OR(M30="Unknown", ISBLANK(M30)), "Missing ship_mode", IF(OR(ISBLANK(B30), ISBLANK(C30)), "Missing Date", IF(OR(ISTEXT(B30), ISTEXT(C30)), "Text Value Not Recognized as Date", IF(C30 < B30, "Invalid shipping record", IF(P30 < 0, "Invalid", IF(P30 > 0.7, "Invalid", "Valid")))))))) -> Text Value Not Recognized as Date | AD30: =IF(ABS(Q30 - W30) > 0.01, 1, 0) -> 0 | AE30: =IF(ABS(S30 - X30) > 0.01, 1, 0) -> 0 | AH30: =PROPER(TRIM(E30)) -> Ananya Rao | AI30: =PROPER(TRIM(F30)) -> Home Office | AJ30: =PROPER(TRIM(G30)) -> West | AK30: =PROPER(TRIM(H30)) -> Gujarat | AL30: =PROPER(TRIM(I30)) -> Ahmedabad | AM30: =PROPER(TRIM(J30)) -> Technology | AN30: =PROPER(TRIM(K30)) -> Phones | AO30: =PROPER(TRIM(M30)) -> Second Class | AP30: =PROPER(TRIM(T30)) -> Refunded | AQ30: =PROPER(TRIM(U30)) -> Cancelled
A31: ORD-2025-10030 | B31: 45882 | C31: 13-08-2025 | D31: CUST-5936 | E31: Rohan Mehta | F31: Home Office | G31: South | H31: Kerala | I31: Kochi | J31: Technology | K31: Phones | L31: Pro Phones 442 | M31: Standard Class | N31: 1 | O31: 256.01 | P31: 0.15 | Q31: 217.61 | R31: 119.77 | S31: 97.84 | T31: Paid | U31: Completed | V31: =IF(ISBLANK(P31), 0, P31) -> 0.15 | W31: =N31 * O31 * (1 - P31) -> 217.6085 | X31: =W31-R31 -> 97.8385 | Y31: =IFERROR(X31 / W31, 0) -> 0.4496079 | Z31: =IF(OR(ISBLANK(B31), ISBLANK(C31), ISTEXT(B31), ISTEXT(C31)), "", C31 - B31) | AA31: =MONTH(B31) -> 8 | AB31: =YEAR(B31) -> 2025 | AC31: =IF(COUNTIF(A:A, A31) > 1, "Conflicting Duplicate Order ID", IF(OR(G31="Unknown", ISBLANK(G31)), "Missing region", IF(OR(M31="Unknown", ISBLANK(M31)), "Missing ship_mode", IF(OR(ISBLANK(B31), ISBLANK(C31)), "Missing Date", IF(OR(ISTEXT(B31), ISTEXT(C31)), "Text Value Not Recognized as Date", IF(C31 < B31, "Invalid shipping record", IF(P31 < 0, "Invalid", IF(P31 > 0.7, "Invalid", "Valid")))))))) -> Text Value Not Recognized as Date | AD31: =IF(ABS(Q31 - W31) > 0.01, 1, 0) -> 0 | AE31: =IF(ABS(S31 - X31) > 0.01, 1, 0) -> 0 | AH31: =PROPER(TRIM(E31)) -> Rohan Mehta | AI31: =PROPER(TRIM(F31)) -> Home Office | AJ31: =PROPER(TRIM(G31)) -> South | AK31: =PROPER(TRIM(H31)) -> Kerala | AL31: =PROPER(TRIM(I31)) -> Kochi | AM31: =PROPER(TRIM(J31)) -> Technology | AN31: =PROPER(TRIM(K31)) -> Phones | AO31: =PROPER(TRIM(M31)) -> Standard Class | AP31: =PROPER(TRIM(T31)) -> Paid | AQ31: =PROPER(TRIM(U31)) -> Completed
A32: ORD-2024-10031 | B32: 45331 | C32: 45334 | D32: CUST-8759 | E32: Ananya Rao | F32: Corporate | G32: West | H32: Goa | I32: Panaji | J32: Office Supplies | K32: Labels | L32: Pro Labels 355 | M32: First Class | N32: 1 | O32: 3421.77 | P32: 0.1 | Q32: 3079.59 | R32: 2001.89 | S32: 1077.7 | T32: Paid | U32: Completed | V32: =IF(ISBLANK(P32), 0, P32) -> 0.1 | W32: =N32 * O32 * (1 - P32) -> 3079.593 | X32: =W32-R32 -> 1077.703 | Y32: =IFERROR(X32 / W32, 0) -> 0.34994981 | Z32: =IF(OR(ISBLANK(B32), ISBLANK(C32), ISTEXT(B32), ISTEXT(C32)), "", C32 - B32) -> 3 | AA32: =MONTH(B32) -> 2 | AB32: =YEAR(B32) -> 2024 | AC32: =IF(COUNTIF(A:A, A32) > 1, "Conflicting Duplicate Order ID", IF(OR(G32="Unknown", ISBLANK(G32)), "Missing region", IF(OR(M32="Unknown", ISBLANK(M32)), "Missing ship_mode", IF(OR(ISBLANK(B32), ISBLANK(C32)), "Missing Date", IF(OR(ISTEXT(B32), ISTEXT(C32)), "Text Value Not Recognized as Date", IF(C32 < B32, "Invalid shipping record", IF(P32 < 0, "Invalid", IF(P32 > 0.7, "Invalid", "Valid")))))))) -> Valid | AD32: =IF(ABS(Q32 - W32) > 0.01, 1, 0) -> 0 | AE32: =IF(ABS(S32 - X32) > 0.01, 1, 0) -> 0 | AH32: =PROPER(TRIM(E32)) -> Ananya Rao | AI32: =PROPER(TRIM(F32)) -> Corporate | AJ32: =PROPER(TRIM(G32)) -> West | AK32: =PROPER(TRIM(H32)) -> Goa | AL32: =PROPER(TRIM(I32)) -> Panaji | AM32: =PROPER(TRIM(J32)) -> Office Supplies | AN32: =PROPER(TRIM(K32)) -> Labels | AO32: =PROPER(TRIM(M32)) -> First Class | AP32: =PROPER(TRIM(T32)) -> Paid | AQ32: =PROPER(TRIM(U32)) -> Completed
A33: ORD-2025-10032 | B33: 15-06-2025 | C33: 19-06-2025 | D33: CUST-7867 | E33: Karan Malhotra | F33: Small Business | G33: West | H33: Madhya Pradesh | I33: Indore | J33: Office Supplies | K33: Paper | L33: Pro Paper 959 | M33: Second Class | N33: 9 | O33: 3092.55 | P33: 0 | Q33: 27832.95 | R33: 17769.75 | S33: 10063.2 | T33: Failed | U33: Returned | V33: =IF(ISBLANK(P33), 0, P33) -> 0 | W33: =N33 * O33 * (1 - P33) -> 27832.95 | X33: =W33-R33 -> 10063.2 | Y33: =IFERROR(X33 / W33, 0) -> 0.36155708 | Z33: =IF(OR(ISBLANK(B33), ISBLANK(C33), ISTEXT(B33), ISTEXT(C33)), "", C33 - B33) | AA33: =MONTH(B33) -> #VALUE! | AB33: =YEAR(B33) -> #VALUE! | AC33: =IF(COUNTIF(A:A, A33) > 1, "Conflicting Duplicate Order ID", IF(OR(G33="Unknown", ISBLANK(G33)), "Missing region", IF(OR(M33="Unknown", ISBLANK(M33)), "Missing ship_mode", IF(OR(ISBLANK(B33), ISBLANK(C33)), "Missing Date", IF(OR(ISTEXT(B33), ISTEXT(C33)), "Text Value Not Recognized as Date", IF(C33 < B33, "Invalid shipping record", IF(P33 < 0, "Invalid", IF(P33 > 0.7, "Invalid", "Valid")))))))) -> Text Value Not Recognized as Date | AD33: =IF(ABS(Q33 - W33) > 0.01, 1, 0) -> 0 | AE33: =IF(ABS(S33 - X33) > 0.01, 1, 0) -> 0 | AH33: =PROPER(TRIM(E33)) -> Karan Malhotra | AI33: =PROPER(TRIM(F33)) -> Small Business | AJ33: =PROPER(TRIM(G33)) -> West | AK33: =PROPER(TRIM(H33)) -> Madhya Pradesh | AL33: =PROPER(TRIM(I33)) -> Indore | AM33: =PROPER(TRIM(J33)) -> Office Supplies | AN33: =PROPER(TRIM(K33)) -> Paper | AO33: =PROPER(TRIM(M33)) -> Second Class | AP33: =PROPER(TRIM(T33)) -> Failed | AQ33: =PROPER(TRIM(U33)) -> Returned
A34: ORD-2024-10033 | B34: 22-11-2024 | C34: 45622 | D34: CUST-6509 | E34: Aarav Sharma | F34: Corporate | G34: South | H34: Andhra Pradesh | I34: Vijayawada | J34: Technology | K34: Phones | L34: Basic Phones 242 | M34: Second Class | N34: 3 | O34: 4001.25 | Q34: 9002.81 | R34: 7529.92 | S34: 1472.89 | T34: Paid | U34: Completed | V34: =IF(ISBLANK(P34), 0, P34) -> 0 | W34: =N34 * O34 * (1 - P34) -> 12003.75 | X34: =W34-R34 -> 4473.83 | Y34: =IFERROR(X34 / W34, 0) -> 0.3727027 | Z34: =IF(OR(ISBLANK(B34), ISBLANK(C34), ISTEXT(B34), ISTEXT(C34)), "", C34 - B34) | AA34: =MONTH(B34) -> #VALUE! | AB34: =YEAR(B34) -> #VALUE! | AC34: =IF(COUNTIF(A:A, A34) > 1, "Conflicting Duplicate Order ID", IF(OR(G34="Unknown", ISBLANK(G34)), "Missing region", IF(OR(M34="Unknown", ISBLANK(M34)), "Missing ship_mode", IF(OR(ISBLANK(B34), ISBLANK(C34)), "Missing Date", IF(OR(ISTEXT(B34), ISTEXT(C34)), "Text Value Not Recognized as Date", IF(C34 < B34, "Invalid shipping record", IF(P34 < 0, "Invalid", IF(P34 > 0.7, "Invalid", "Valid")))))))) -> Text Value Not Recognized as Date | AD34: =IF(ABS(Q34 - W34) > 0.01, 1, 0) -> 1 | AE34: =IF(ABS(S34 - X34) > 0.01, 1, 0) -> 1 | AH34: =PROPER(TRIM(E34)) -> Aarav Sharma | AI34: =PROPER(TRIM(F34)) -> Corporate | AJ34: =PROPER(TRIM(G34)) -> South | AK34: =PROPER(TRIM(H34)) -> Andhra Pradesh | AL34: =PROPER(TRIM(I34)) -> Vijayawada | AM34: =PROPER(TRIM(J34)) -> Technology | AN34: =PROPER(TRIM(K34)) -> Phones | AO34: =PROPER(TRIM(M34)) -> Second Class | AP34: =PROPER(TRIM(T34)) -> Paid | AQ34: =PROPER(TRIM(U34)) -> Completed
A35: ORD-2024-10034 | B35: 45495 | C35: 27-07-2024 | D35: CUST-6660 | E35: Priya Menon | F35: Home Office | G35: West | H35: Goa | I35: Panaji | J35: Furniture | K35: Tables | L35: Max Tables 836 | M35: Same Day | N35: 7 | O35: 492.41 | P35: 0.25 | Q35: 2585.15 | R35: 2070.73 | S35: 514.42 | T35: Paid | U35: Completed | V35: =IF(ISBLANK(P35), 0, P35) -> 0.25 | W35: =N35 * O35 * (1 - P35) -> 2585.1525 | X35: =W35-R35 -> 514.4225 | Y35: =IFERROR(X35 / W35, 0) -> 0.19899116 | Z35: =IF(OR(ISBLANK(B35), ISBLANK(C35), ISTEXT(B35), ISTEXT(C35)), "", C35 - B35) | AA35: =MONTH(B35) -> 7 | AB35: =YEAR(B35) -> 2024 | AC35: =IF(COUNTIF(A:A, A35) > 1, "Conflicting Duplicate Order ID", IF(OR(G35="Unknown", ISBLANK(G35)), "Missing region", IF(OR(M35="Unknown", ISBLANK(M35)), "Missing ship_mode", IF(OR(ISBLANK(B35), ISBLANK(C35)), "Missing Date", IF(OR(ISTEXT(B35), ISTEXT(C35)), "Text Value Not Recognized as Date", IF(C35 < B35, "Invalid shipping record", IF(P35 < 0, "Invalid", IF(P35 > 0.7, "Invalid", "Valid")))))))) -> Text Value Not Recognized as Date | AD35: =IF(ABS(Q35 - W35) > 0.01, 1, 0) -> 0 | AE35: =IF(ABS(S35 - X35) > 0.01, 1, 0) -> 0 | AH35: =PROPER(TRIM(E35)) -> Priya Menon | AI35: =PROPER(TRIM(F35)) -> Home Office | AJ35: =PROPER(TRIM(G35)) -> West | AK35: =PROPER(TRIM(H35)) -> Goa | AL35: =PROPER(TRIM(I35)) -> Panaji | AM35: =PROPER(TRIM(J35)) -> Furniture | AN35: =PROPER(TRIM(K35)) -> Tables | AO35: =PROPER(TRIM(M35)) -> Same Day | AP35: =PROPER(TRIM(T35)) -> Paid | AQ35: =PROPER(TRIM(U35)) -> Completed
A36: ORD-2025-10035 | B36: 45688 | C36: 45693 | D36: CUST-2392 | E36: Priya Menon | F36: Home Office | G36: East | H36: West Bengal | I36: Kolkata | J36: Furniture | K36: Chairs | L36: Elite Chairs 862 | N36: 2 | O36: 4159.69 | P36: 0.2 | Q36: 6655.5 | R36: 4340.21 | S36: 2607.32 | T36: Paid | U36: Completed | V36: =IF(ISBLANK(P36), 0, P36) -> 0.2 | W36: =N36 * O36 * (1 - P36) -> 6655.504 | X36: =W36-R36 -> 2315.294 | Y36: =IFERROR(X36 / W36, 0) -> 0.34787658 | Z36: =IF(OR(ISBLANK(B36), ISBLANK(C36), ISTEXT(B36), ISTEXT(C36)), "", C36 - B36) -> 5 | AA36: =MONTH(B36) -> 1 | AB36: =YEAR(B36) -> 2025 | AC36: =IF(COUNTIF(A:A, A36) > 1, "Conflicting Duplicate Order ID", IF(OR(G36="Unknown", ISBLANK(G36)), "Missing region", IF(OR(M36="Unknown", ISBLANK(M36)), "Missing ship_mode", IF(OR(ISBLANK(B36), ISBLANK(C36)), "Missing Date", IF(OR(ISTEXT(B36), ISTEXT(C36)), "Text Value Not Recognized as Date", IF(C36 < B36, "Invalid shipping record", IF(P36 < 0, "Invalid", IF(P36 > 0.7, "Invalid", "Valid")))))))) -> Missing ship_mode | AD36: =IF(ABS(Q36 - W36) > 0.01, 1, 0) -> 0 | AE36: =IF(ABS(S36 - X36) > 0.01, 1, 0) -> 1 | AH36: =PROPER(TRIM(E36)) -> Priya Menon | AI36: =PROPER(TRIM(F36)) -> Home Office | AJ36: =PROPER(TRIM(G36)) -> East | AK36: =PROPER(TRIM(H36)) -> West Bengal | AL36: =PROPER(TRIM(I36)) -> Kolkata | AM36: =PROPER(TRIM(J36)) -> Furniture | AN36: =PROPER(TRIM(K36)) -> Chairs | AO36: Unknown | AP36: =PROPER(TRIM(T36)) -> Paid | AQ36: =PROPER(TRIM(U36)) -> Completed
A37: ORD-2024-10036 | B37: 29-05-2024 | C37: 45441 | D37: CUST-1611 | E37: Sneha Kapoor | F37: Small Business | G37: West | H37: Gujarat | I37: Ahmedabad | J37: Furniture | K37: Bookcases | L37: Prime Bookcases 414 | M37: Second Class | N37: 8 | O37: 2507.12 | P37: 0.05 | Q37: 19054.11 | R37: 15313.83 | S37: 3740.28 | T37: Pending | U37: Returned | V37: =IF(ISBLANK(P37), 0, P37) -> 0.05 | W37: =N37 * O37 * (1 - P37) -> 19054.112 | X37: =W37-R37 -> 3740.282 | Y37: =IFERROR(X37 / W37, 0) -> 0.19629789 | Z37: =IF(OR(ISBLANK(B37), ISBLANK(C37), ISTEXT(B37), ISTEXT(C37)), "", C37 - B37) | AA37: =MONTH(B37) -> #VALUE! | AB37: =YEAR(B37) -> #VALUE! | AC37: =IF(COUNTIF(A:A, A37) > 1, "Conflicting Duplicate Order ID", IF(OR(G37="Unknown", ISBLANK(G37)), "Missing region", IF(OR(M37="Unknown", ISBLANK(M37)), "Missing ship_mode", IF(OR(ISBLANK(B37), ISBLANK(C37)), "Missing Date", IF(OR(ISTEXT(B37), ISTEXT(C37)), "Text Value Not Recognized as Date", IF(C37 < B37, "Invalid shipping record", IF(P37 < 0, "Invalid", IF(P37 > 0.7, "Invalid", "Valid")))))))) -> Text Value Not Recognized as Date | AD37: =IF(ABS(Q37 - W37) > 0.01, 1, 0) -> 0 | AE37: =IF(ABS(S37 - X37) > 0.01, 1, 0) -> 0 | AH37: =PROPER(TRIM(E37)) -> Sneha Kapoor | AI37: =PROPER(TRIM(F37)) -> Small Business | AJ37: =PROPER(TRIM(G37)) -> West | AK37: =PROPER(TRIM(H37)) -> Gujarat | AL37: =PROPER(TRIM(I37)) -> Ahmedabad | AM37: =PROPER(TRIM(J37)) -> Furniture | AN37: =PROPER(TRIM(K37)) -> Bookcases | AO37: =PROPER(TRIM(M37)) -> Second Class | AP37: =PROPER(TRIM(T37)) -> Pending | AQ37: =PROPER(TRIM(U37)) -> Returned
A38: ORD-2024-10037 | B38: 45590 | C38: 45593 | D38: CUST-8296 | E38: Rohan Mehta | F38: Corporate | G38: West | H38: Maharashtra | I38: Mumbai | J38: Furniture | K38: Bookcases | L38: Eco Bookcases 220 | M38: Second Class | N38: 3 | O38: 3126.47 | P38: 0 | Q38: 9379.41 | R38: 6670.85 | S38: 2708.56 | T38: Paid | U38: Returned | V38: =IF(ISBLANK(P38), 0, P38) -> 0 | W38: =N38 * O38 * (1 - P38) -> 9379.41 | X38: =W38-R38 -> 2708.56 | Y38: =IFERROR(X38 / W38, 0) -> 0.28877723 | Z38: =IF(OR(ISBLANK(B38), ISBLANK(C38), ISTEXT(B38), ISTEXT(C38)), "", C38 - B38) -> 3 | AA38: =MONTH(B38) -> 10 | AB38: =YEAR(B38) -> 2024 | AC38: =IF(COUNTIF(A:A, A38) > 1, "Conflicting Duplicate Order ID", IF(OR(G38="Unknown", ISBLANK(G38)), "Missing region", IF(OR(M38="Unknown", ISBLANK(M38)), "Missing ship_mode", IF(OR(ISBLANK(B38), ISBLANK(C38)), "Missing Date", IF(OR(ISTEXT(B38), ISTEXT(C38)), "Text Value Not Recognized as Date", IF(C38 < B38, "Invalid shipping record", IF(P38 < 0, "Invalid", IF(P38 > 0.7, "Invalid", "Valid")))))))) -> Valid | AD38: =IF(ABS(Q38 - W38) > 0.01, 1, 0) -> 0 | AE38: =IF(ABS(S38 - X38) > 0.01, 1, 0) -> 0 | AH38: =PROPER(TRIM(E38)) -> Rohan Mehta | AI38: =PROPER(TRIM(F38)) -> Corporate | AJ38: =PROPER(TRIM(G38)) -> West | AK38: =PROPER(TRIM(H38)) -> Maharashtra | AL38: =PROPER(TRIM(I38)) -> Mumbai | AM38: =PROPER(TRIM(J38)) -> Furniture | AN38: =PROPER(TRIM(K38)) -> Bookcases | AO38: =PROPER(TRIM(M38)) -> Second Class | AP38: =PROPER(TRIM(T38)) -> Paid | AQ38: =PROPER(TRIM(U38)) -> Returned
A39: ORD-2025-10038 | B39: 29-07-2025 | C39: 29-07-2025 | D39: CUST-4646 | E39: Diya Patel | F39: Consumer | G39: West | H39: Maharashtra | I39: Mumbai | J39: Technology | K39: Copiers | L39: Pro Copiers 830 | M39: STANDARD CLASS | N39: 4 | O39: 1327.54 | P39: 0.2 | Q39: 4248.13 | R39: 3321.09 | S39: 927.04 | T39: Paid | U39: Completed | V39: =IF(ISBLANK(P39), 0, P39) -> 0.2 | W39: =N39 * O39 * (1 - P39) -> 4248.128 | X39: =W39-R39 -> 927.038 | Y39: =IFERROR(X39 / W39, 0) -> 0.21822271 | Z39: =IF(OR(ISBLANK(B39), ISBLANK(C39), ISTEXT(B39), ISTEXT(C39)), "", C39 - B39) | AA39: =MONTH(B39) -> #VALUE! | AB39: =YEAR(B39) -> #VALUE! | AC39: =IF(COUNTIF(A:A, A39) > 1, "Conflicting Duplicate Order ID", IF(OR(G39="Unknown", ISBLANK(G39)), "Missing region", IF(OR(M39="Unknown", ISBLANK(M39)), "Missing ship_mode", IF(OR(ISBLANK(B39), ISBLANK(C39)), "Missing Date", IF(OR(ISTEXT(B39), ISTEXT(C39)), "Text Value Not Recognized as Date", IF(C39 < B39, "Invalid shipping record", IF(P39 < 0, "Invalid", IF(P39 > 0.7, "Invalid", "Valid")))))))) -> Text Value Not Recognized as Date | AD39: =IF(ABS(Q39 - W39) > 0.01, 1, 0) -> 0 | AE39: =IF(ABS(S39 - X39) > 0.01, 1, 0) -> 0 | AH39: =PROPER(TRIM(E39)) -> Diya Patel | AI39: =PROPER(TRIM(F39)) -> Consumer | AJ39: =PROPER(TRIM(G39)) -> West | AK39: =PROPER(TRIM(H39)) -> Maharashtra | AL39: =PROPER(TRIM(I39)) -> Mumbai | AM39: =PROPER(TRIM(J39)) -> Technology | AN39: =PROPER(TRIM(K39)) -> Copiers | AO39: =PROPER(TRIM(M39)) -> Standard Class | AP39: =PROPER(TRIM(T39)) -> Paid | AQ39: =PROPER(TRIM(U39)) -> Completed
A40: ORD-2024-10039 | B40: 45460 | C40: 22-06-2024 | D40: CUST-8235 | E40: Aarav Sharma | F40: Corporate | G40: West | H40: Gujarat | I40: Ahmedabad | J40: Technology | K40: Phones | L40: Prime Phones 507 | M40: First Class | N40: 7 | O40: 2210.68 | P40: 0.1 | Q40: 13927.28 | R40: 10504.87 | S40: 3422.41 | T40: Paid | U40: Completed | V40: =IF(ISBLANK(P40), 0, P40) -> 0.1 | W40: =N40 * O40 * (1 - P40) -> 13927.284 | X40: =W40-R40 -> 3422.414 | Y40: =IFERROR(X40 / W40, 0) -> 0.24573449 | Z40: =IF(OR(ISBLANK(B40), ISBLANK(C40), ISTEXT(B40), ISTEXT(C40)), "", C40 - B40) | AA40: =MONTH(B40) -> 6 | AB40: =YEAR(B40) -> 2024 | AC40: =IF(COUNTIF(A:A, A40) > 1, "Conflicting Duplicate Order ID", IF(OR(G40="Unknown", ISBLANK(G40)), "Missing region", IF(OR(M40="Unknown", ISBLANK(M40)), "Missing ship_mode", IF(OR(ISBLANK(B40), ISBLANK(C40)), "Missing Date", IF(OR(ISTEXT(B40), ISTEXT(C40)), "Text Value Not Recognized as Date", IF(C40 < B40, "Invalid shipping record", IF(P40 < 0, "Invalid", IF(P40 > 0.7, "Invalid", "Valid")))))))) -> Text Value Not Recognized as Date | AD40: =IF(ABS(Q40 - W40) > 0.01, 1, 0) -> 0 | AE40: =IF(ABS(S40 - X40) > 0.01, 1, 0) -> 0 | AH40: =PROPER(TRIM(E40)) -> Aarav Sharma | AI40: =PROPER(TRIM(F40)) -> Corporate | AJ40: =PROPER(TRIM(G40)) -> West | AK40: =PROPER(TRIM(H40)) -> Gujarat | AL40: =PROPER(TRIM(I40)) -> Ahmedabad | AM40: =PROPER(TRIM(J40)) -> Technology | AN40: =PROPER(TRIM(K40)) -> Phones | AO40: =PROPER(TRIM(M40)) -> First Class | AP40: =PROPER(TRIM(T40)) -> Paid | AQ40: =PROPER(TRIM(U40)) -> Completed
A41: ORD-2024-10040 | B41: 45637 | C41: 45637 | D41: CUST-5830 | E41: Mira Das | F41: Small Business | G41: West | H41: Madhya Pradesh | I41: Indore | J41: Technology | K41: Copiers | L41: Classic Copiers 590 | M41: First Class | N41: 4 | O41: 1370.92 | P41: 0.1 | Q41: 4935.31 | R41: 3374.77 | S41: 1560.54 | T41: Pending | U41: Returned | V41: =IF(ISBLANK(P41), 0, P41) -> 0.1 | W41: =N41 * O41 * (1 - P41) -> 4935.312 | X41: =W41-R41 -> 1560.542 | Y41: =IFERROR(X41 / W41, 0) -> 0.31619926 | Z41: =IF(OR(ISBLANK(B41), ISBLANK(C41), ISTEXT(B41), ISTEXT(C41)), "", C41 - B41) -> 0 | AA41: =MONTH(B41) -> 12 | AB41: =YEAR(B41) -> 2024 | AC41: =IF(COUNTIF(A:A, A41) > 1, "Conflicting Duplicate Order ID", IF(OR(G41="Unknown", ISBLANK(G41)), "Missing region", IF(OR(M41="Unknown", ISBLANK(M41)), "Missing ship_mode", IF(OR(ISBLANK(B41), ISBLANK(C41)), "Missing Date", IF(OR(ISTEXT(B41), ISTEXT(C41)), "Text Value Not Recognized as Date", IF(C41 < B41, "Invalid shipping record", IF(P41 < 0, "Invalid", IF(P41 > 0.7, "Invalid", "Valid")))))))) -> Valid | AD41: =IF(ABS(Q41 - W41) > 0.01, 1, 0) -> 0 | AE41: =IF(ABS(S41 - X41) > 0.01, 1, 0) -> 0 | AH41: =PROPER(TRIM(E41)) -> Mira Das | AI41: =PROPER(TRIM(F41)) -> Small Business | AJ41: =PROPER(TRIM(G41)) -> West | AK41: =PROPER(TRIM(H41)) -> Madhya Pradesh | AL41: =PROPER(TRIM(I41)) -> Indore | AM41: =PROPER(TRIM(J41)) -> Technology | AN41: =PROPER(TRIM(K41)) -> Copiers | AO41: =PROPER(TRIM(M41)) -> First Class | AP41: =PROPER(TRIM(T41)) -> Pending | AQ41: =PROPER(TRIM(U41)) -> Returned
A42: ORD-2024-10041 | B42: 45575 | C42: 45581 | D42: CUST-7178 | E42: Isha Nair | F42: Home Office | G42: West | H42: Rajasthan | I42: Udaipur | J42: Technology | K42: Copiers | L42: Eco Copiers 865 | M42: Standard Class | N42: 7 | O42: 2509.27 | P42: 0.2 | Q42: 14051.91 | R42: 11990.37 | S42: 2061.54 | T42: Paid | U42: Completed | V42: =IF(ISBLANK(P42), 0, P42) -> 0.2 | W42: =N42 * O42 * (1 - P42) -> 14051.912 | X42: =W42-R42 -> 2061.542 | Y42: =IFERROR(X42 / W42, 0) -> 0.146709 | Z42: =IF(OR(ISBLANK(B42), ISBLANK(C42), ISTEXT(B42), ISTEXT(C42)), "", C42 - B42) -> 6 | AA42: =MONTH(B42) -> 10 | AB42: =YEAR(B42) -> 2024 | AC42: =IF(COUNTIF(A:A, A42) > 1, "Conflicting Duplicate Order ID", IF(OR(G42="Unknown", ISBLANK(G42)), "Missing region", IF(OR(M42="Unknown", ISBLANK(M42)), "Missing ship_mode", IF(OR(ISBLANK(B42), ISBLANK(C42)), "Missing Date", IF(OR(ISTEXT(B42), ISTEXT(C42)), "Text Value Not Recognized as Date", IF(C42 < B42, "Invalid shipping record", IF(P42 < 0, "Invalid", IF(P42 > 0.7, "Invalid", "Valid")))))))) -> Valid | AD42: =IF(ABS(Q42 - W42) > 0.01, 1, 0) -> 0 | AE42: =IF(ABS(S42 - X42) > 0.01, 1, 0) -> 0 | AH42: =PROPER(TRIM(E42)) -> Isha Nair | AI42: =PROPER(TRIM(F42)) -> Home Office | AJ42: =PROPER(TRIM(G42)) -> West | AK42: =PROPER(TRIM(H42)) -> Rajasthan | AL42: =PROPER(TRIM(I42)) -> Udaipur | AM42: =PROPER(TRIM(J42)) -> Technology | AN42: =PROPER(TRIM(K42)) -> Copiers | AO42: =PROPER(TRIM(M42)) -> Standard Class | AP42: =PROPER(TRIM(T42)) -> Paid | AQ42: =PROPER(TRIM(U42)) -> Completed
A43: ORD-2024-10042 | B43: 45363 | C43: 17-03-2024 | D43: CUST-3829 | E43: Aarav Sharma | F43: Small Business | G43: East | H43: Odisha | I43: Bhubaneswar | J43: Furniture | K43: Bookcases | L43: Classic Bookcases 835 | M43: Same Day | N43: 8 | O43: 855.81 | P43: 0 | Q43: 6846.48 | R43: 4239.89 | S43: 2606.59 | T43: Pending | U43: Cancelled | V43: =IF(ISBLANK(P43), 0, P43) -> 0 | W43: =N43 * O43 * (1 - P43) -> 6846.48 | X43: =W43-R43 -> 2606.59 | Y43: =IFERROR(X43 / W43, 0) -> 0.38071973 | Z43: =IF(OR(ISBLANK(B43), ISBLANK(C43), ISTEXT(B43), ISTEXT(C43)), "", C43 - B43) | AA43: =MONTH(B43) -> 3 | AB43: =YEAR(B43) -> 2024 | AC43: =IF(COUNTIF(A:A, A43) > 1, "Conflicting Duplicate Order ID", IF(OR(G43="Unknown", ISBLANK(G43)), "Missing region", IF(OR(M43="Unknown", ISBLANK(M43)), "Missing ship_mode", IF(OR(ISBLANK(B43), ISBLANK(C43)), "Missing Date", IF(OR(ISTEXT(B43), ISTEXT(C43)), "Text Value Not Recognized as Date", IF(C43 < B43, "Invalid shipping record", IF(P43 < 0, "Invalid", IF(P43 > 0.7, "Invalid", "Valid")))))))) -> Text Value Not Recognized as Date | AD43: =IF(ABS(Q43 - W43) > 0.01, 1, 0) -> 0 | AE43: =IF(ABS(S43 - X43) > 0.01, 1, 0) -> 0 | AH43: =PROPER(TRIM(E43)) -> Aarav Sharma | AI43: =PROPER(TRIM(F43)) -> Small Business | AJ43: =PROPER(TRIM(G43)) -> East | AK43: =PROPER(TRIM(H43)) -> Odisha | AL43: =PROPER(TRIM(I43)) -> Bhubaneswar | AM43: =PROPER(TRIM(J43)) -> Furniture | AN43: =PROPER(TRIM(K43)) -> Bookcases | AO43: =PROPER(TRIM(M43)) -> Same Day | AP43: =PROPER(TRIM(T43)) -> Pending | AQ43: =PROPER(TRIM(U43)) -> Cancelled
A44: ORD-2025-10043 | B44: 45940 | C44: 45945 | D44: CUST-6708 | E44: Arjun Bose | F44: Corporate | G44: East | H44: Jharkhand | I44: Ranchi | J44: Technology | K44: Phones | L44: Eco Phones 702 | M44: Standard Class | N44: 8 | O44: 979.87 | P44: 0.05 | Q44: 7447.01 | R44: 4496.22 | S44: 2950.79 | T44: Paid | U44: Completed | V44: =IF(ISBLANK(P44), 0, P44) -> 0.05 | W44: =N44 * O44 * (1 - P44) -> 7447.012 | X44: =W44-R44 -> 2950.792 | Y44: =IFERROR(X44 / W44, 0) -> 0.39623838 | Z44: =IF(OR(ISBLANK(B44), ISBLANK(C44), ISTEXT(B44), ISTEXT(C44)), "", C44 - B44) -> 5 | AA44: =MONTH(B44) -> 10 | AB44: =YEAR(B44) -> 2025 | AC44: =IF(COUNTIF(A:A, A44) > 1, "Conflicting Duplicate Order ID", IF(OR(G44="Unknown", ISBLANK(G44)), "Missing region", IF(OR(M44="Unknown", ISBLANK(M44)), "Missing ship_mode", IF(OR(ISBLANK(B44), ISBLANK(C44)), "Missing Date", IF(OR(ISTEXT(B44), ISTEXT(C44)), "Text Value Not Recognized as Date", IF(C44 < B44, "Invalid shipping record", IF(P44 < 0, "Invalid", IF(P44 > 0.7, "Invalid", "Valid")))))))) -> Valid | AD44: =IF(ABS(Q44 - W44) > 0.01, 1, 0) -> 0 | AE44: =IF(ABS(S44 - X44) > 0.01, 1, 0) -> 0 | AH44: =PROPER(TRIM(E44)) -> Arjun Bose | AI44: =PROPER(TRIM(F44)) -> Corporate | AJ44: =PROPER(TRIM(G44)) -> East | AK44: =PROPER(TRIM(H44)) -> Jharkhand | AL44: =PROPER(TRIM(I44)) -> Ranchi | AM44: =PROPER(TRIM(J44)) -> Technology | AN44: =PROPER(TRIM(K44)) -> Phones | AO44: =PROPER(TRIM(M44)) -> Standard Class | AP44: =PROPER(TRIM(T44)) -> Paid | AQ44: =PROPER(TRIM(U44)) -> Completed
A45: ORD-2024-10044 | B45: 45481 | C45: 45487 | D45: CUST-7119 | E45: Priya Menon | F45: Small Business | G45: East | H45: Odisha | I45: Bhubaneswar | J45: Furniture | K45: Furnishings | L45: Smart Furnishings 956 | M45: Same Day | N45: 3 | O45: 1010.23 | P45: 0 | Q45: 3030.69 | R45: 1721.08 | S45: 1309.61 | T45: Paid | U45: Completed | V45: =IF(ISBLANK(P45), 0, P45) -> 0 | W45: =N45 * O45 * (1 - P45) -> 3030.69 | X45: =W45-R45 -> 1309.61 | Y45: =IFERROR(X45 / W45, 0) -> 0.43211612 | Z45: =IF(OR(ISBLANK(B45), ISBLANK(C45), ISTEXT(B45), ISTEXT(C45)), "", C45 - B45) -> 6 | AA45: =MONTH(B45) -> 7 | AB45: =YEAR(B45) -> 2024 | AC45: =IF(COUNTIF(A:A, A45) > 1, "Conflicting Duplicate Order ID", IF(OR(G45="Unknown", ISBLANK(G45)), "Missing region", IF(OR(M45="Unknown", ISBLANK(M45)), "Missing ship_mode", IF(OR(ISBLANK(B45), ISBLANK(C45)), "Missing Date", IF(OR(ISTEXT(B45), ISTEXT(C45)), "Text Value Not Recognized as Date", IF(C45 < B45, "Invalid shipping record", IF(P45 < 0, "Invalid", IF(P45 > 0.7, "Invalid", "Valid")))))))) -> Valid | AD45: =IF(ABS(Q45 - W45) > 0.01, 1, 0) -> 0 | AE45: =IF(ABS(S45 - X45) > 0.01, 1, 0) -> 0 | AH45: =PROPER(TRIM(E45)) -> Priya Menon | AI45: =PROPER(TRIM(F45)) -> Small Business | AJ45: =PROPER(TRIM(G45)) -> East | AK45: =PROPER(TRIM(H45)) -> Odisha | AL45: =PROPER(TRIM(I45)) -> Bhubaneswar | AM45: =PROPER(TRIM(J45)) -> Furniture | AN45: =PROPER(TRIM(K45)) -> Furnishings | AO45: =PROPER(TRIM(M45)) -> Same Day | AP45: =PROPER(TRIM(T45)) -> Paid | AQ45: =PROPER(TRIM(U45)) -> Completed
A46: ORD-2024-10045 | B46: 45465 | C46: 25-06-2024 | D46: CUST-3373 | E46: Rohan Mehta | F46: Small Business | G46: North | H46: Haryana | I46: Gurugram | J46: Furniture | K46: Chairs | L46: Max Chairs 393 | M46: Standard Class | N46: 9 | O46: 3329.77 | P46: 0.1 | Q46: 26971.14 | R46: 17376.2 | S46: 9594.94 | T46: Paid | U46: Completed | V46: =IF(ISBLANK(P46), 0, P46) -> 0.1 | W46: =N46 * O46 * (1 - P46) -> 26971.137 | X46: =W46-R46 -> 9594.937 | Y46: =IFERROR(X46 / W46, 0) -> 0.35574833 | Z46: =IF(OR(ISBLANK(B46), ISBLANK(C46), ISTEXT(B46), ISTEXT(C46)), "", C46 - B46) | AA46: =MONTH(B46) -> 6 | AB46: =YEAR(B46) -> 2024 | AC46: =IF(COUNTIF(A:A, A46) > 1, "Conflicting Duplicate Order ID", IF(OR(G46="Unknown", ISBLANK(G46)), "Missing region", IF(OR(M46="Unknown", ISBLANK(M46)), "Missing ship_mode", IF(OR(ISBLANK(B46), ISBLANK(C46)), "Missing Date", IF(OR(ISTEXT(B46), ISTEXT(C46)), "Text Value Not Recognized as Date", IF(C46 < B46, "Invalid shipping record", IF(P46 < 0, "Invalid", IF(P46 > 0.7, "Invalid", "Valid")))))))) -> Text Value Not Recognized as Date | AD46: =IF(ABS(Q46 - W46) > 0.01, 1, 0) -> 0 | AE46: =IF(ABS(S46 - X46) > 0.01, 1, 0) -> 0 | AH46: =PROPER(TRIM(E46)) -> Rohan Mehta | AI46: =PROPER(TRIM(F46)) -> Small Business | AJ46: =PROPER(TRIM(G46)) -> North | AK46: =PROPER(TRIM(H46)) -> Haryana | AL46: =PROPER(TRIM(I46)) -> Gurugram | AM46: =PROPER(TRIM(J46)) -> Furniture | AN46: =PROPER(TRIM(K46)) -> Chairs | AO46: =PROPER(TRIM(M46)) -> Standard Class | AP46: =PROPER(TRIM(T46)) -> Paid | AQ46: =PROPER(TRIM(U46)) -> Completed
A47: ORD-2024-10046 | B47: 45309 | C47: 24-01-2024 | D47: CUST-8896 | E47: Isha Nair | F47: Home Office | G47: East | H47: Bihar | I47: Patna | J47: Office Supplies | K47: Art | L47: Prime Art 221 | M47: Second Class | N47: 8 | O47: 3927.82 | P47: 0.05 | Q47: 29851.43 | R47: 17487.48 | S47: 12363.95 | T47: Pending | U47: Returned | V47: =IF(ISBLANK(P47), 0, P47) -> 0.05 | W47: =N47 * O47 * (1 - P47) -> 29851.432 | X47: =W47-R47 -> 12363.952 | Y47: =IFERROR(X47 / W47, 0) -> 0.41418288 | Z47: =IF(OR(ISBLANK(B47), ISBLANK(C47), ISTEXT(B47), ISTEXT(C47)), "", C47 - B47) | AA47: =MONTH(B47) -> 1 | AB47: =YEAR(B47) -> 2024 | AC47: =IF(COUNTIF(A:A, A47) > 1, "Conflicting Duplicate Order ID", IF(OR(G47="Unknown", ISBLANK(G47)), "Missing region", IF(OR(M47="Unknown", ISBLANK(M47)), "Missing ship_mode", IF(OR(ISBLANK(B47), ISBLANK(C47)), "Missing Date", IF(OR(ISTEXT(B47), ISTEXT(C47)), "Text Value Not Recognized as Date", IF(C47 < B47, "Invalid shipping record", IF(P47 < 0, "Invalid", IF(P47 > 0.7, "Invalid", "Valid")))))))) -> Text Value Not Recognized as Date | AD47: =IF(ABS(Q47 - W47) > 0.01, 1, 0) -> 0 | AE47: =IF(ABS(S47 - X47) > 0.01, 1, 0) -> 0 | AH47: =PROPER(TRIM(E47)) -> Isha Nair | AI47: =PROPER(TRIM(F47)) -> Home Office | AJ47: =PROPER(TRIM(G47)) -> East | AK47: =PROPER(TRIM(H47)) -> Bihar | AL47: =PROPER(TRIM(I47)) -> Patna | AM47: =PROPER(TRIM(J47)) -> Office Supplies | AN47: =PROPER(TRIM(K47)) -> Art | AO47: =PROPER(TRIM(M47)) -> Second Class | AP47: =PROPER(TRIM(T47)) -> Pending | AQ47: =PROPER(TRIM(U47)) -> Returned
A48: ORD-2024-10047 | B48: 19-07-2024 | C48: 19-07-2024 | D48: CUST-8517 | E48: Ananya Rao | F48: Small Business | G48: South | H48: Kerala | I48: Kochi | J48: Furniture | K48: Bookcases | L48: Elite Bookcases 671 | M48: Standard Class | N48: 9 | O48: 2386.79 | P48: 0.25 | Q48: 16110.83 | R48: 10680.03 | S48: 5430.8 | T48: Refunded | U48: Returned | V48: =IF(ISBLANK(P48), 0, P48) -> 0.25 | W48: =N48 * O48 * (1 - P48) -> 16110.833 | X48: =W48-R48 -> 5430.8025 | Y48: =IFERROR(X48 / W48, 0) -> 0.33709012 | Z48: =IF(OR(ISBLANK(B48), ISBLANK(C48), ISTEXT(B48), ISTEXT(C48)), "", C48 - B48) | AA48: =MONTH(B48) -> #VALUE! | AB48: =YEAR(B48) -> #VALUE! | AC48: =IF(COUNTIF(A:A, A48) > 1, "Conflicting Duplicate Order ID", IF(OR(G48="Unknown", ISBLANK(G48)), "Missing region", IF(OR(M48="Unknown", ISBLANK(M48)), "Missing ship_mode", IF(OR(ISBLANK(B48), ISBLANK(C48)), "Missing Date", IF(OR(ISTEXT(B48), ISTEXT(C48)), "Text Value Not Recognized as Date", IF(C48 < B48, "Invalid shipping record", IF(P48 < 0, "Invalid", IF(P48 > 0.7, "Invalid", "Valid")))))))) -> Text Value Not Recognized as Date | AD48: =IF(ABS(Q48 - W48) > 0.01, 1, 0) -> 0 | AE48: =IF(ABS(S48 - X48) > 0.01, 1, 0) -> 0 | AH48: =PROPER(TRIM(E48)) -> Ananya Rao | AI48: =PROPER(TRIM(F48)) -> Small Business | AJ48: =PROPER(TRIM(G48)) -> South | AK48: =PROPER(TRIM(H48)) -> Kerala | AL48: =PROPER(TRIM(I48)) -> Kochi | AM48: =PROPER(TRIM(J48)) -> Furniture | AN48: =PROPER(TRIM(K48)) -> Bookcases | AO48: =PROPER(TRIM(M48)) -> Standard Class | AP48: =PROPER(TRIM(T48)) -> Refunded | AQ48: =PROPER(TRIM(U48)) -> Returned
A49: ORD-2024-10048 | B49: 45634 | C49: 45516 | D49: CUST-1987 | E49: Rahul Verma | F49: Corporate | G49: South | H49: Tamil Nadu | I49: Chennai | J49: Office Supplies | K49: Storage | L49: Max Storage 432 | M49: Standard Class | N49: 8 | O49: 2445.31 | P49: 0.1 | Q49: 17606.23 | R49: 12438.96 | S49: 5167.27 | T49: Paid | U49: Completed | V49: =IF(ISBLANK(P49), 0, P49) -> 0.1 | W49: =N49 * O49 * (1 - P49) -> 17606.232 | X49: =W49-R49 -> 5167.272 | Y49: =IFERROR(X49 / W49, 0) -> 0.29349108 | Z49: =IF(OR(ISBLANK(B49), ISBLANK(C49), ISTEXT(B49), ISTEXT(C49)), "", C49 - B49) -> -118 | AA49: =MONTH(B49) -> 12 | AB49: =YEAR(B49) -> 2024 | AC49: =IF(COUNTIF(A:A, A49) > 1, "Conflicting Duplicate Order ID", IF(OR(G49="Unknown", ISBLANK(G49)), "Missing region", IF(OR(M49="Unknown", ISBLANK(M49)), "Missing ship_mode", IF(OR(ISBLANK(B49), ISBLANK(C49)), "Missing Date", IF(OR(ISTEXT(B49), ISTEXT(C49)), "Text Value Not Recognized as Date", IF(C49 < B49, "Invalid shipping record", IF(P49 < 0, "Invalid", IF(P49 > 0.7, "Invalid", "Valid")))))))) -> Invalid shipping record | AD49: =IF(ABS(Q49 - W49) > 0.01, 1, 0) -> 0 | AE49: =IF(ABS(S49 - X49) > 0.01, 1, 0) -> 0 | AH49: =PROPER(TRIM(E49)) -> Rahul Verma | AI49: =PROPER(TRIM(F49)) -> Corporate | AJ49: =PROPER(TRIM(G49)) -> South | AK49: =PROPER(TRIM(H49)) -> Tamil Nadu | AL49: =PROPER(TRIM(I49)) -> Chennai | AM49: =PROPER(TRIM(J49)) -> Office Supplies | AN49: =PROPER(TRIM(K49)) -> Storage | AO49: =PROPER(TRIM(M49)) -> Standard Class | AP49: =PROPER(TRIM(T49)) -> Paid | AQ49: =PROPER(TRIM(U49)) -> Completed
A50: ORD-2025-10049 | B50: 45687 | C50: 45693 | D50: CUST-8183 | E50: Neha Gupta | F50: Corporate | G50: West | H50: Maharashtra | I50: Mumbai | J50: Furniture | K50: Chairs | L50: Basic Chairs 837 | M50: Second Class | N50: 7 | O50: 4063.66 | P50: 0 | Q50: 28445.62 | R50: 20938.59 | S50: 7507.03 | T50: Paid | U50: Completed | V50: =IF(ISBLANK(P50), 0, P50) -> 0 | W50: =N50 * O50 * (1 - P50) -> 28445.62 | X50: =W50-R50 -> 7507.03 | Y50: =IFERROR(X50 / W50, 0) -> 0.26390812 | Z50: =IF(OR(ISBLANK(B50), ISBLANK(C50), ISTEXT(B50), ISTEXT(C50)), "", C50 - B50) -> 6 | AA50: =MONTH(B50) -> 1 | AB50: =YEAR(B50) -> 2025 | AC50: =IF(COUNTIF(A:A, A50) > 1, "Conflicting Duplicate Order ID", IF(OR(G50="Unknown", ISBLANK(G50)), "Missing region", IF(OR(M50="Unknown", ISBLANK(M50)), "Missing ship_mode", IF(OR(ISBLANK(B50), ISBLANK(C50)), "Missing Date", IF(OR(ISTEXT(B50), ISTEXT(C50)), "Text Value Not Recognized as Date", IF(C50 < B50, "Invalid shipping record", IF(P50 < 0, "Invalid", IF(P50 > 0.7, "Invalid", "Valid")))))))) -> Valid | AD50: =IF(ABS(Q50 - W50) > 0.01, 1, 0) -> 0 | AE50: =IF(ABS(S50 - X50) > 0.01, 1, 0) -> 0 | AH50: =PROPER(TRIM(E50)) -> Neha Gupta | AI50: =PROPER(TRIM(F50)) -> Corporate | AJ50: =PROPER(TRIM(G50)) -> West | AK50: =PROPER(TRIM(H50)) -> Maharashtra | AL50: =PROPER(TRIM(I50)) -> Mumbai | AM50: =PROPER(TRIM(J50)) -> Furniture | AN50: =PROPER(TRIM(K50)) -> Chairs | AO50: =PROPER(TRIM(M50)) -> Second Class | AP50: =PROPER(TRIM(T50)) -> Paid | AQ50: =PROPER(TRIM(U50)) -> Completed
A51: ORD-2024-10050 | B51: 45388 | C51: 45395 | D51: CUST-2380 | E51: Aarav Sharma | F51: Home Office | G51: North | H51: Uttar Pradesh | I51: Noida | J51: Technology | K51: Copiers | L51: Classic Copiers 295 | M51: Second Class | N51: 9 | O51: 792.11 | P51: 0.05 | Q51: 6772.54 | R51: 5755.46 | S51: 1017.08 | T51: Paid | U51: Completed | V51: =IF(ISBLANK(P51), 0, P51) -> 0.05 | W51: =N51 * O51 * (1 - P51) -> 6772.5405 | X51: =W51-R51 -> 1017.0805 | Y51: =IFERROR(X51 / W51, 0) -> 0.1501771 | Z51: =IF(OR(ISBLANK(B51), ISBLANK(C51), ISTEXT(B51), ISTEXT(C51)), "", C51 - B51) -> 7 | AA51: =MONTH(B51) -> 4 | AB51: =YEAR(B51) -> 2024 | AC51: =IF(COUNTIF(A:A, A51) > 1, "Conflicting Duplicate Order ID", IF(OR(G51="Unknown", ISBLANK(G51)), "Missing region", IF(OR(M51="Unknown", ISBLANK(M51)), "Missing ship_mode", IF(OR(ISBLANK(B51), ISBLANK(C51)), "Missing Date", IF(OR(ISTEXT(B51), ISTEXT(C51)), "Text Value Not Recognized as Date", IF(C51 < B51, "Invalid shipping record", IF(P51 < 0, "Invalid", IF(P51 > 0.7, "Invalid", "Valid")))))))) -> Valid | AD51: =IF(ABS(Q51 - W51) > 0.01, 1, 0) -> 0 | AE51: =IF(ABS(S51 - X51) > 0.01, 1, 0) -> 0 | AH51: =PROPER(TRIM(E51)) -> Aarav Sharma | AI51: =PROPER(TRIM(F51)) -> Home Office | AJ51: =PROPER(TRIM(G51)) -> North | AK51: =PROPER(TRIM(H51)) -> Uttar Pradesh | AL51: =PROPER(TRIM(I51)) -> Noida | AM51: =PROPER(TRIM(J51)) -> Technology | AN51: =PROPER(TRIM(K51)) -> Copiers | AO51: =PROPER(TRIM(M51)) -> Second Class | AP51: =PROPER(TRIM(T51)) -> Paid | AQ51: =PROPER(TRIM(U51)) -> Completed
A52: ORD-2025-10051 | B52: 45788 | C52: 45796 | D52: CUST-8787 | E52: Sneha Kapoor | F52: Consumer | G52: East | H52: West Bengal | I52: Kolkata | J52: Technology | K52: Copiers | L52: Pro Copiers 963 | M52: Standard Class | N52: 1 | O52: 2382.8 | P52: 0.15 | Q52: 2025.38 | R52: 1140.65 | S52: 884.73 | T52: Paid | U52: Completed | V52: =IF(ISBLANK(P52), 0, P52) -> 0.15 | W52: =N52 * O52 * (1 - P52) -> 2025.38 | X52: =W52-R52 -> 884.73 | Y52: =IFERROR(X52 / W52, 0) -> 0.43682173 | Z52: =IF(OR(ISBLANK(B52), ISBLANK(C52), ISTEXT(B52), ISTEXT(C52)), "", C52 - B52) -> 8 | AA52: =MONTH(B52) -> 5 | AB52: =YEAR(B52) -> 2025 | AC52: =IF(COUNTIF(A:A, A52) > 1, "Conflicting Duplicate Order ID", IF(OR(G52="Unknown", ISBLANK(G52)), "Missing region", IF(OR(M52="Unknown", ISBLANK(M52)), "Missing ship_mode", IF(OR(ISBLANK(B52), ISBLANK(C52)), "Missing Date", IF(OR(ISTEXT(B52), ISTEXT(C52)), "Text Value Not Recognized as Date", IF(C52 < B52, "Invalid shipping record", IF(P52 < 0, "Invalid", IF(P52 > 0.7, "Invalid", "Valid")))))))) -> Valid | AD52: =IF(ABS(Q52 - W52) > 0.01, 1, 0) -> 0 | AE52: =IF(ABS(S52 - X52) > 0.01, 1, 0) -> 0 | AH52: =PROPER(TRIM(E52)) -> Sneha Kapoor | AI52: =PROPER(TRIM(F52)) -> Consumer | AJ52: =PROPER(TRIM(G52)) -> East | AK52: =PROPER(TRIM(H52)) -> West Bengal | AL52: =PROPER(TRIM(I52)) -> Kolkata | AM52: =PROPER(TRIM(J52)) -> Technology | AN52: =PROPER(TRIM(K52)) -> Copiers | AO52: =PROPER(TRIM(M52)) -> Standard Class | AP52: =PROPER(TRIM(T52)) -> Paid | AQ52: =PROPER(TRIM(U52)) -> Completed
A53: ORD-2024-10052 | B53: 45406 | C53: 45411 | D53: CUST-3557 | E53: Ananya Rao | F53: Corporate | G53: South | H53: Telangana | I53: Hyderabad | J53: Office Supplies | K53: Art | L53: Pro Art 907 | M53: Standard Class | N53: 6 | O53: 1528.08 | P53: 0 | Q53: 9168.48 | R53: 7439.77 | S53: 1728.71 | T53: Paid | U53: Completed | V53: =IF(ISBLANK(P53), 0, P53) -> 0 | W53: =N53 * O53 * (1 - P53) -> 9168.48 | X53: =W53-R53 -> 1728.71 | Y53: =IFERROR(X53 / W53, 0) -> 0.18854925 | Z53: =IF(OR(ISBLANK(B53), ISBLANK(C53), ISTEXT(B53), ISTEXT(C53)), "", C53 - B53) -> 5 | AA53: =MONTH(B53) -> 4 | AB53: =YEAR(B53) -> 2024 | AC53: =IF(COUNTIF(A:A, A53) > 1, "Conflicting Duplicate Order ID", IF(OR(G53="Unknown", ISBLANK(G53)), "Missing region", IF(OR(M53="Unknown", ISBLANK(M53)), "Missing ship_mode", IF(OR(ISBLANK(B53), ISBLANK(C53)), "Missing Date", IF(OR(ISTEXT(B53), ISTEXT(C53)), "Text Value Not Recognized as Date", IF(C53 < B53, "Invalid shipping record", IF(P53 < 0, "Invalid", IF(P53 > 0.7, "Invalid", "Valid")))))))) -> Valid | AD53: =IF(ABS(Q53 - W53) > 0.01, 1, 0) -> 0 | AE53: =IF(ABS(S53 - X53) > 0.01, 1, 0) -> 0 | AH53: =PROPER(TRIM(E53)) -> Ananya Rao | AI53: =PROPER(TRIM(F53)) -> Corporate | AJ53: =PROPER(TRIM(G53)) -> South | AK53: =PROPER(TRIM(H53)) -> Telangana | AL53: =PROPER(TRIM(I53)) -> Hyderabad | AM53: =PROPER(TRIM(J53)) -> Office Supplies | AN53: =PROPER(TRIM(K53)) -> Art | AO53: =PROPER(TRIM(M53)) -> Standard Class | AP53: =PROPER(TRIM(T53)) -> Paid | AQ53: =PROPER(TRIM(U53)) -> Completed
A54: ORD-2024-10053 | B54: 26-10-2024 | C54: 45593 | D54: CUST-2778 | E54: Kabir Singh | F54: Small Business | G54: North | H54: Rajasthan | I54: Jaipur | J54: Furniture | K54: Chairs | L54: Pro Chairs 526 | M54: First Class | N54: 9 | O54: 1399.63 | P54: 0 | Q54: 12596.67 | R54: 10603.29 | S54: 1993.38 | T54: Failed | U54: Cancelled | V54: =IF(ISBLANK(P54), 0, P54) -> 0 | W54: =N54 * O54 * (1 - P54) -> 12596.67 | X54: =W54-R54 -> 1993.38 | Y54: =IFERROR(X54 / W54, 0) -> 0.15824658 | Z54: =IF(OR(ISBLANK(B54), ISBLANK(C54), ISTEXT(B54), ISTEXT(C54)), "", C54 - B54) | AA54: =MONTH(B54) -> #VALUE! | AB54: =YEAR(B54) -> #VALUE! | AC54: =IF(COUNTIF(A:A, A54) > 1, "Conflicting Duplicate Order ID", IF(OR(G54="Unknown", ISBLANK(G54)), "Missing region", IF(OR(M54="Unknown", ISBLANK(M54)), "Missing ship_mode", IF(OR(ISBLANK(B54), ISBLANK(C54)), "Missing Date", IF(OR(ISTEXT(B54), ISTEXT(C54)), "Text Value Not Recognized as Date", IF(C54 < B54, "Invalid shipping record", IF(P54 < 0, "Invalid", IF(P54 > 0.7, "Invalid", "Valid")))))))) -> Text Value Not Recognized as Date | AD54: =IF(ABS(Q54 - W54) > 0.01, 1, 0) -> 0 | AE54: =IF(ABS(S54 - X54) > 0.01, 1, 0) -> 0 | AH54: =PROPER(TRIM(E54)) -> Kabir Singh | AI54: =PROPER(TRIM(F54)) -> Small Business | AJ54: =PROPER(TRIM(G54)) -> North | AK54: =PROPER(TRIM(H54)) -> Rajasthan | AL54: =PROPER(TRIM(I54)) -> Jaipur | AM54: =PROPER(TRIM(J54)) -> Furniture | AN54: =PROPER(TRIM(K54)) -> Chairs | AO54: =PROPER(TRIM(M54)) -> First Class | AP54: =PROPER(TRIM(T54)) -> Failed | AQ54: =PROPER(TRIM(U54)) -> Cancelled
A55: ORD-2025-10054 | B55: 45747 | C55: 45747 | D55: CUST-7195 | E55: Kabir Singh | F55: Home Office | G55: West | H55: Gujarat | I55: Ahmedabad | J55: Office Supplies | K55: Storage | L55: Elite Storage 924 | M55: First Class | N55: 5 | O55: 1207.47 | P55: 0.15 | Q55: 5131.75 | R55: 2838.68 | S55: 2293.07 | T55: Paid | U55: Completed | V55: =IF(ISBLANK(P55), 0, P55) -> 0.15 | W55: =N55 * O55 * (1 - P55) -> 5131.7475 | X55: =W55-R55 -> 2293.0675 | Y55: =IFERROR(X55 / W55, 0) -> 0.4468395 | Z55: =IF(OR(ISBLANK(B55), ISBLANK(C55), ISTEXT(B55), ISTEXT(C55)), "", C55 - B55) -> 0 | AA55: =MONTH(B55) -> 3 | AB55: =YEAR(B55) -> 2025 | AC55: =IF(COUNTIF(A:A, A55) > 1, "Conflicting Duplicate Order ID", IF(OR(G55="Unknown", ISBLANK(G55)), "Missing region", IF(OR(M55="Unknown", ISBLANK(M55)), "Missing ship_mode", IF(OR(ISBLANK(B55), ISBLANK(C55)), "Missing Date", IF(OR(ISTEXT(B55), ISTEXT(C55)), "Text Value Not Recognized as Date", IF(C55 < B55, "Invalid shipping record", IF(P55 < 0, "Invalid", IF(P55 > 0.7, "Invalid", "Valid")))))))) -> Valid | AD55: =IF(ABS(Q55 - W55) > 0.01, 1, 0) -> 0 | AE55: =IF(ABS(S55 - X55) > 0.01, 1, 0) -> 0 | AH55: =PROPER(TRIM(E55)) -> Kabir Singh | AI55: =PROPER(TRIM(F55)) -> Home Office | AJ55: =PROPER(TRIM(G55)) -> West | AK55: =PROPER(TRIM(H55)) -> Gujarat | AL55: =PROPER(TRIM(I55)) -> Ahmedabad | AM55: =PROPER(TRIM(J55)) -> Office Supplies | AN55: =PROPER(TRIM(K55)) -> Storage | AO55: =PROPER(TRIM(M55)) -> First Class | AP55: =PROPER(TRIM(T55)) -> Paid | AQ55: =PROPER(TRIM(U55)) -> Completed
A56: ORD-2025-10055 | B56: 45807 | C56: 45810 | D56: CUST-9039 | E56: Arjun Bose | F56: Corporate | G56: South | H56: Tamil Nadu | I56: Chennai | J56: Office Supplies | K56: Labels | L56: Pro Labels 957 | M56: Same Day | N56: 8 | O56: 474.37 | P56: 0.1 | Q56: 3415.46 | R56: 1993.23 | S56: 1422.23 | T56: Failed | U56: Cancelled | V56: =IF(ISBLANK(P56), 0, P56) -> 0.1 | W56: =N56 * O56 * (1 - P56) -> 3415.464 | X56: =W56-R56 -> 1422.234 | Y56: =IFERROR(X56 / W56, 0) -> 0.41641019 | Z56: =IF(OR(ISBLANK(B56), ISBLANK(C56), ISTEXT(B56), ISTEXT(C56)), "", C56 - B56) -> 3 | AA56: =MONTH(B56) -> 5 | AB56: =YEAR(B56) -> 2025 | AC56: =IF(COUNTIF(A:A, A56) > 1, "Conflicting Duplicate Order ID", IF(OR(G56="Unknown", ISBLANK(G56)), "Missing region", IF(OR(M56="Unknown", ISBLANK(M56)), "Missing ship_mode", IF(OR(ISBLANK(B56), ISBLANK(C56)), "Missing Date", IF(OR(ISTEXT(B56), ISTEXT(C56)), "Text Value Not Recognized as Date", IF(C56 < B56, "Invalid shipping record", IF(P56 < 0, "Invalid", IF(P56 > 0.7, "Invalid", "Valid")))))))) -> Valid | AD56: =IF(ABS(Q56 - W56) > 0.01, 1, 0) -> 0 | AE56: =IF(ABS(S56 - X56) > 0.01, 1, 0) -> 0 | AH56: =PROPER(TRIM(E56)) -> Arjun Bose | AI56: =PROPER(TRIM(F56)) -> Corporate | AJ56: =PROPER(TRIM(G56)) -> South | AK56: =PROPER(TRIM(H56)) -> Tamil Nadu | AL56: =PROPER(TRIM(I56)) -> Chennai | AM56: =PROPER(TRIM(J56)) -> Office Supplies | AN56: =PROPER(TRIM(K56)) -> Labels | AO56: =PROPER(TRIM(M56)) -> Same Day | AP56: =PROPER(TRIM(T56)) -> Failed | AQ56: =PROPER(TRIM(U56)) -> Cancelled
A57: ORD-2025-10056 | B57: 45664 | C57: 45723 | D57: CUST-9821 | E57: Mira Das | F57: Small Business | G57: South | H57: Andhra Pradesh | I57: Vijayawada | J57: Technology | K57: Machines | L57: Classic Machines 310 | M57: Same Day | N57: 3 | O57: 1516.24 | P57: 0.25 | Q57: 3411.54 | R57: 2803.13 | S57: 608.41 | T57: Paid | U57: Completed | V57: =IF(ISBLANK(P57), 0, P57) -> 0.25 | W57: =N57 * O57 * (1 - P57) -> 3411.54 | X57: =W57-R57 -> 608.41 | Y57: =IFERROR(X57 / W57, 0) -> 0.17833881 | Z57: =IF(OR(ISBLANK(B57), ISBLANK(C57), ISTEXT(B57), ISTEXT(C57)), "", C57 - B57) -> 59 | AA57: =MONTH(B57) -> 1 | AB57: =YEAR(B57) -> 2025 | AC57: =IF(COUNTIF(A:A, A57) > 1, "Conflicting Duplicate Order ID", IF(OR(G57="Unknown", ISBLANK(G57)), "Missing region", IF(OR(M57="Unknown", ISBLANK(M57)), "Missing ship_mode", IF(OR(ISBLANK(B57), ISBLANK(C57)), "Missing Date", IF(OR(ISTEXT(B57), ISTEXT(C57)), "Text Value Not Recognized as Date", IF(C57 < B57, "Invalid shipping record", IF(P57 < 0, "Invalid", IF(P57 > 0.7, "Invalid", "Valid")))))))) -> Valid | AD57: =IF(ABS(Q57 - W57) > 0.01, 1, 0) -> 0 | AE57: =IF(ABS(S57 - X57) > 0.01, 1, 0) -> 0 | AH57: =PROPER(TRIM(E57)) -> Mira Das | AI57: =PROPER(TRIM(F57)) -> Small Business | AJ57: =PROPER(TRIM(G57)) -> South | AK57: =PROPER(TRIM(H57)) -> Andhra Pradesh | AL57: =PROPER(TRIM(I57)) -> Vijayawada | AM57: =PROPER(TRIM(J57)) -> Technology | AN57: =PROPER(TRIM(K57)) -> Machines | AO57: =PROPER(TRIM(M57)) -> Same Day | AP57: =PROPER(TRIM(T57)) -> Paid | AQ57: =PROPER(TRIM(U57)) -> Completed
A58: ORD-2025-10057 | B58: 45662 | C58: 45809 | D58: CUST-8701 | E58: Karan Malhotra | F58: Consumer | G58: South | H58: Karnataka | I58: Bengaluru | J58: Office Supplies | K58: Binders | L58: Smart Binders 393 | M58: Second Class | N58: 3 | O58: 3155.61 | P58: 0 | Q58: 9466.83 | R58: 6557.83 | S58: 2909 | T58: Refunded | U58: Cancelled | V58: =IF(ISBLANK(P58), 0, P58) -> 0 | W58: =N58 * O58 * (1 - P58) -> 9466.83 | X58: =W58-R58 -> 2909 | Y58: =IFERROR(X58 / W58, 0) -> 0.30728343 | Z58: =IF(OR(ISBLANK(B58), ISBLANK(C58), ISTEXT(B58), ISTEXT(C58)), "", C58 - B58) -> 147 | AA58: =MONTH(B58) -> 1 | AB58: =YEAR(B58) -> 2025 | AC58: =IF(COUNTIF(A:A, A58) > 1, "Conflicting Duplicate Order ID", IF(OR(G58="Unknown", ISBLANK(G58)), "Missing region", IF(OR(M58="Unknown", ISBLANK(M58)), "Missing ship_mode", IF(OR(ISBLANK(B58), ISBLANK(C58)), "Missing Date", IF(OR(ISTEXT(B58), ISTEXT(C58)), "Text Value Not Recognized as Date", IF(C58 < B58, "Invalid shipping record", IF(P58 < 0, "Invalid", IF(P58 > 0.7, "Invalid", "Valid")))))))) -> Valid | AD58: =IF(ABS(Q58 - W58) > 0.01, 1, 0) -> 0 | AE58: =IF(ABS(S58 - X58) > 0.01, 1, 0) -> 0 | AH58: =PROPER(TRIM(E58)) -> Karan Malhotra | AI58: =PROPER(TRIM(F58)) -> Consumer | AJ58: =PROPER(TRIM(G58)) -> South | AK58: =PROPER(TRIM(H58)) -> Karnataka | AL58: =PROPER(TRIM(I58)) -> Bengaluru | AM58: =PROPER(TRIM(J58)) -> Office Supplies | AN58: =PROPER(TRIM(K58)) -> Binders | AO58: =PROPER(TRIM(M58)) -> Second Class | AP58: =PROPER(TRIM(T58)) -> Refunded | AQ58: =PROPER(TRIM(U58)) -> Cancelled
A59: ORD-2024-10058 | B59: 45329 | C59: 45337 | D59: CUST-9941 | E59: Priya Menon | F59: Consumer | G59: West | H59: Goa | I59: Panaji | J59: Furniture | K59: Chairs | L59: Max Chairs 813 | M59: Same Day | N59: 5 | O59: 255.87 | P59: 0 | Q59: 1279.35 | R59: 1091.54 | S59: 187.81 | T59: Paid | U59: Completed | V59: =IF(ISBLANK(P59), 0, P59) -> 0 | W59: =N59 * O59 * (1 - P59) -> 1279.35 | X59: =W59-R59 -> 187.81 | Y59: =IFERROR(X59 / W59, 0) -> 0.14680111 | Z59: =IF(OR(ISBLANK(B59), ISBLANK(C59), ISTEXT(B59), ISTEXT(C59)), "", C59 - B59) -> 8 | AA59: =MONTH(B59) -> 2 | AB59: =YEAR(B59) -> 2024 | AC59: =IF(COUNTIF(A:A, A59) > 1, "Conflicting Duplicate Order ID", IF(OR(G59="Unknown", ISBLANK(G59)), "Missing region", IF(OR(M59="Unknown", ISBLANK(M59)), "Missing ship_mode", IF(OR(ISBLANK(B59), ISBLANK(C59)), "Missing Date", IF(OR(ISTEXT(B59), ISTEXT(C59)), "Text Value Not Recognized as Date", IF(C59 < B59, "Invalid shipping record", IF(P59 < 0, "Invalid", IF(P59 > 0.7, "Invalid", "Valid")))))))) -> Valid | AD59: =IF(ABS(Q59 - W59) > 0.01, 1, 0) -> 0 | AE59: =IF(ABS(S59 - X59) > 0.01, 1, 0) -> 0 | AH59: =PROPER(TRIM(E59)) -> Priya Menon | AI59: =PROPER(TRIM(F59)) -> Consumer | AJ59: =PROPER(TRIM(G59)) -> West | AK59: =PROPER(TRIM(H59)) -> Goa | AL59: =PROPER(TRIM(I59)) -> Panaji | AM59: =PROPER(TRIM(J59)) -> Furniture | AN59: =PROPER(TRIM(K59)) -> Chairs | AO59: =PROPER(TRIM(M59)) -> Same Day | AP59: =PROPER(TRIM(T59)) -> Paid | AQ59: =PROPER(TRIM(U59)) -> Completed
A60: ORD-2024-10059 | B60: 45536 | C60: 45542 | D60: CUST-3983 | E60: Isha Nair | F60: Home Office | G60: North | H60: Rajasthan | I60: Jaipur | J60: Office Supplies | K60: Storage | L60: Basic Storage 872 | N60: 9 | O60: 1389.48 | P60: 0.1 | Q60: 11254.79 | R60: 6578.06 | S60: 4676.73 | T60: Pending | U60: Returned | V60: =IF(ISBLANK(P60), 0, P60) -> 0.1 | W60: =N60 * O60 * (1 - P60) -> 11254.788 | X60: =W60-R60 -> 4676.728 | Y60: =IFERROR(X60 / W60, 0) -> 0.41553231 | Z60: =IF(OR(ISBLANK(B60), ISBLANK(C60), ISTEXT(B60), ISTEXT(C60)), "", C60 - B60) -> 6 | AA60: =MONTH(B60) -> 9 | AB60: =YEAR(B60) -> 2024 | AC60: =IF(COUNTIF(A:A, A60) > 1, "Conflicting Duplicate Order ID", IF(OR(G60="Unknown", ISBLANK(G60)), "Missing region", IF(OR(M60="Unknown", ISBLANK(M60)), "Missing ship_mode", IF(OR(ISBLANK(B60), ISBLANK(C60)), "Missing Date", IF(OR(ISTEXT(B60), ISTEXT(C60)), "Text Value Not Recognized as Date", IF(C60 < B60, "Invalid shipping record", IF(P60 < 0, "Invalid", IF(P60 > 0.7, "Invalid", "Valid")))))))) -> Missing ship_mode | AD60: =IF(ABS(Q60 - W60) > 0.01, 1, 0) -> 0 | AE60: =IF(ABS(S60 - X60) > 0.01, 1, 0) -> 0 | AH60: =PROPER(TRIM(E60)) -> Isha Nair | AI60: =PROPER(TRIM(F60)) -> Home Office | AJ60: =PROPER(TRIM(G60)) -> North | AK60: =PROPER(TRIM(H60)) -> Rajasthan | AL60: =PROPER(TRIM(I60)) -> Jaipur | AM60: =PROPER(TRIM(J60)) -> Office Supplies | AN60: =PROPER(TRIM(K60)) -> Storage | AO60: Unknown | AP60: =PROPER(TRIM(T60)) -> Pending | AQ60: =PROPER(TRIM(U60)) -> Returned
A61: ORD-2024-10060 | B61: 20-07-2024 | C61: 45498 | D61: CUST-2418 | E61: Priya Menon | F61: Corporate | G61: East | H61: Assam | I61: Guwahati | J61: Office Supplies | K61: Labels | L61: Smart Labels 655 | M61: Same Day | N61: 5 | O61: 4133.85 | P61: 0.2 | Q61: 16535.4 | R61: 12990.21 | S61: 3545.19 | T61: Paid | U61: Cancelled | V61: =IF(ISBLANK(P61), 0, P61) -> 0.2 | W61: =N61 * O61 * (1 - P61) -> 16535.4 | X61: =W61-R61 -> 3545.19 | Y61: =IFERROR(X61 / W61, 0) -> 0.21440001 | Z61: =IF(OR(ISBLANK(B61), ISBLANK(C61), ISTEXT(B61), ISTEXT(C61)), "", C61 - B61) | AA61: =MONTH(B61) -> #VALUE! | AB61: =YEAR(B61) -> #VALUE! | AC61: =IF(COUNTIF(A:A, A61) > 1, "Conflicting Duplicate Order ID", IF(OR(G61="Unknown", ISBLANK(G61)), "Missing region", IF(OR(M61="Unknown", ISBLANK(M61)), "Missing ship_mode", IF(OR(ISBLANK(B61), ISBLANK(C61)), "Missing Date", IF(OR(ISTEXT(B61), ISTEXT(C61)), "Text Value Not Recognized as Date", IF(C61 < B61, "Invalid shipping record", IF(P61 < 0, "Invalid", IF(P61 > 0.7, "Invalid", "Valid")))))))) -> Text Value Not Recognized as Date | AD61: =IF(ABS(Q61 - W61) > 0.01, 1, 0) -> 0 | AE61: =IF(ABS(S61 - X61) > 0.01, 1, 0) -> 0 | AH61: =PROPER(TRIM(E61)) -> Priya Menon | AI61: =PROPER(TRIM(F61)) -> Corporate | AJ61: =PROPER(TRIM(G61)) -> East | AK61: =PROPER(TRIM(H61)) -> Assam | AL61: =PROPER(TRIM(I61)) -> Guwahati | AM61: =PROPER(TRIM(J61)) -> Office Supplies | AN61: =PROPER(TRIM(K61)) -> Labels | AO61: =PROPER(TRIM(M61)) -> Same Day | AP61: =PROPER(TRIM(T61)) -> Paid | AQ61: =PROPER(TRIM(U61)) -> Cancelled
A62: ORD-2024-10061 | B62: 45486 | C62: 45492 | D62: CUST-2892 | E62: Ananya Rao | F62: Corporate | G62: East | H62: Assam | I62: Guwahati | J62: Office Supplies | K62: Labels | L62: Eco Labels 210 | M62: Same Day | N62: 3 | O62: 275.76 | P62: 0.2 | Q62: 661.82 | R62: 481.47 | S62: 180.35 | T62: Refunded | U62: Cancelled | V62: =IF(ISBLANK(P62), 0, P62) -> 0.2 | W62: =N62 * O62 * (1 - P62) -> 661.824 | X62: =W62-R62 -> 180.354 | Y62: =IFERROR(X62 / W62, 0) -> 0.27251052 | Z62: =IF(OR(ISBLANK(B62), ISBLANK(C62), ISTEXT(B62), ISTEXT(C62)), "", C62 - B62) -> 6 | AA62: =MONTH(B62) -> 7 | AB62: =YEAR(B62) -> 2024 | AC62: =IF(COUNTIF(A:A, A62) > 1, "Conflicting Duplicate Order ID", IF(OR(G62="Unknown", ISBLANK(G62)), "Missing region", IF(OR(M62="Unknown", ISBLANK(M62)), "Missing ship_mode", IF(OR(ISBLANK(B62), ISBLANK(C62)), "Missing Date", IF(OR(ISTEXT(B62), ISTEXT(C62)), "Text Value Not Recognized as Date", IF(C62 < B62, "Invalid shipping record", IF(P62 < 0, "Invalid", IF(P62 > 0.7, "Invalid", "Valid")))))))) -> Valid | AD62: =IF(ABS(Q62 - W62) > 0.01, 1, 0) -> 0 | AE62: =IF(ABS(S62 - X62) > 0.01, 1, 0) -> 0 | AH62: =PROPER(TRIM(E62)) -> Ananya Rao | AI62: =PROPER(TRIM(F62)) -> Corporate | AJ62: =PROPER(TRIM(G62)) -> East | AK62: =PROPER(TRIM(H62)) -> Assam | AL62: =PROPER(TRIM(I62)) -> Guwahati | AM62: =PROPER(TRIM(J62)) -> Office Supplies | AN62: =PROPER(TRIM(K62)) -> Labels | AO62: =PROPER(TRIM(M62)) -> Same Day | AP62: =PROPER(TRIM(T62)) -> Refunded | AQ62: =PROPER(TRIM(U62)) -> Cancelled
A63: ORD-2024-10062 | B63: 45398 | C63: 45398 | D63: CUST-7008 | E63: Vikram Iyer | F63: Home Office | G63: East | H63: Bihar | I63: Patna | J63: Furniture | K63: Bookcases | L63: Classic Bookcases 296 | M63: Standard Class | N63: 1 | O63: 949.59 | P63: 0 | Q63: 949.59 | R63: 751.25 | S63: 198.34 | T63: Paid | U63: Completed | V63: =IF(ISBLANK(P63), 0, P63) -> 0 | W63: =N63 * O63 * (1 - P63) -> 949.59 | X63: =W63-R63 -> 198.34 | Y63: =IFERROR(X63 / W63, 0) -> 0.20886909 | Z63: =IF(OR(ISBLANK(B63), ISBLANK(C63), ISTEXT(B63), ISTEXT(C63)), "", C63 - B63) -> 0 | AA63: =MONTH(B63) -> 4 | AB63: =YEAR(B63) -> 2024 | AC63: =IF(COUNTIF(A:A, A63) > 1, "Conflicting Duplicate Order ID", IF(OR(G63="Unknown", ISBLANK(G63)), "Missing region", IF(OR(M63="Unknown", ISBLANK(M63)), "Missing ship_mode", IF(OR(ISBLANK(B63), ISBLANK(C63)), "Missing Date", IF(OR(ISTEXT(B63), ISTEXT(C63)), "Text Value Not Recognized as Date", IF(C63 < B63, "Invalid shipping record", IF(P63 < 0, "Invalid", IF(P63 > 0.7, "Invalid", "Valid")))))))) -> Valid | AD63: =IF(ABS(Q63 - W63) > 0.01, 1, 0) -> 0 | AE63: =IF(ABS(S63 - X63) > 0.01, 1, 0) -> 0 | AH63: =PROPER(TRIM(E63)) -> Vikram Iyer | AI63: =PROPER(TRIM(F63)) -> Home Office | AJ63: =PROPER(TRIM(G63)) -> East | AK63: =PROPER(TRIM(H63)) -> Bihar | AL63: =PROPER(TRIM(I63)) -> Patna | AM63: =PROPER(TRIM(J63)) -> Furniture | AN63: =PROPER(TRIM(K63)) -> Bookcases | AO63: =PROPER(TRIM(M63)) -> Standard Class | AP63: =PROPER(TRIM(T63)) -> Paid | AQ63: =PROPER(TRIM(U63)) -> Completed
A64: ORD-2024-10063 | B64: 45595 | C64: 45333 | D64: CUST-4900 | E64: Sneha Kapoor | F64: Home Office | G64: North | H64: Rajasthan | I64: Jaipur | J64: Technology | K64: Phones | L64: Basic Phones 230 | M64: Standard Class | N64: 9 | O64: 3042.29 | P64: 0.2 | Q64: 21904.49 | R64: 13570.55 | S64: 8333.94 | T64: Paid | U64: Completed | V64: =IF(ISBLANK(P64), 0, P64) -> 0.2 | W64: =N64 * O64 * (1 - P64) -> 21904.488 | X64: =W64-R64 -> 8333.938 | Y64: =IFERROR(X64 / W64, 0) -> 0.38046714 | Z64: =IF(OR(ISBLANK(B64), ISBLANK(C64), ISTEXT(B64), ISTEXT(C64)), "", C64 - B64) -> -262 | AA64: =MONTH(B64) -> 10 | AB64: =YEAR(B64) -> 2024 | AC64: =IF(COUNTIF(A:A, A64) > 1, "Conflicting Duplicate Order ID", IF(OR(G64="Unknown", ISBLANK(G64)), "Missing region", IF(OR(M64="Unknown", ISBLANK(M64)), "Missing ship_mode", IF(OR(ISBLANK(B64), ISBLANK(C64)), "Missing Date", IF(OR(ISTEXT(B64), ISTEXT(C64)), "Text Value Not Recognized as Date", IF(C64 < B64, "Invalid shipping record", IF(P64 < 0, "Invalid", IF(P64 > 0.7, "Invalid", "Valid")))))))) -> Invalid shipping record | AD64: =IF(ABS(Q64 - W64) > 0.01, 1, 0) -> 0 | AE64: =IF(ABS(S64 - X64) > 0.01, 1, 0) -> 0 | AH64: =PROPER(TRIM(E64)) -> Sneha Kapoor | AI64: =PROPER(TRIM(F64)) -> Home Office | AJ64: =PROPER(TRIM(G64)) -> North | AK64: =PROPER(TRIM(H64)) -> Rajasthan | AL64: =PROPER(TRIM(I64)) -> Jaipur | AM64: =PROPER(TRIM(J64)) -> Technology | AN64: =PROPER(TRIM(K64)) -> Phones | AO64: =PROPER(TRIM(M64)) -> Standard Class | AP64: =PROPER(TRIM(T64)) -> Paid | AQ64: =PROPER(TRIM(U64)) -> Completed
A65: ORD-2024-10064 | B65: 45316 | C65: 45293 | D65: CUST-5382 | E65: Sneha Kapoor | F65: Home Office | G65: North | H65: Haryana | I65: Gurugram | J65: Office Supplies | K65: Binders | L65: Pro Binders 690 | M65: Same Day | N65: 2 | O65: 2832.77 | P65: 0.15 | Q65: 4815.71 | R65: 3027.75 | S65: 1917.47 | T65: Paid | U65: Completed | V65: =IF(ISBLANK(P65), 0, P65) -> 0.15 | W65: =N65 * O65 * (1 - P65) -> 4815.709 | X65: =W65-R65 -> 1787.959 | Y65: =IFERROR(X65 / W65, 0) -> 0.37127638 | Z65: =IF(OR(ISBLANK(B65), ISBLANK(C65), ISTEXT(B65), ISTEXT(C65)), "", C65 - B65) -> -23 | AA65: =MONTH(B65) -> 1 | AB65: =YEAR(B65) -> 2024 | AC65: =IF(COUNTIF(A:A, A65) > 1, "Conflicting Duplicate Order ID", IF(OR(G65="Unknown", ISBLANK(G65)), "Missing region", IF(OR(M65="Unknown", ISBLANK(M65)), "Missing ship_mode", IF(OR(ISBLANK(B65), ISBLANK(C65)), "Missing Date", IF(OR(ISTEXT(B65), ISTEXT(C65)), "Text Value Not Recognized as Date", IF(C65 < B65, "Invalid shipping record", IF(P65 < 0, "Invalid", IF(P65 > 0.7, "Invalid", "Valid")))))))) -> Invalid shipping record | AD65: =IF(ABS(Q65 - W65) > 0.01, 1, 0) -> 0 | AE65: =IF(ABS(S65 - X65) > 0.01, 1, 0) -> 1 | AH65: =PROPER(TRIM(E65)) -> Sneha Kapoor | AI65: =PROPER(TRIM(F65)) -> Home Office | AJ65: =PROPER(TRIM(G65)) -> North | AK65: =PROPER(TRIM(H65)) -> Haryana | AL65: =PROPER(TRIM(I65)) -> Gurugram | AM65: =PROPER(TRIM(J65)) -> Office Supplies | AN65: =PROPER(TRIM(K65)) -> Binders | AO65: =PROPER(TRIM(M65)) -> Same Day | AP65: =PROPER(TRIM(T65)) -> Paid | AQ65: =PROPER(TRIM(U65)) -> Completed
A66: ORD-2024-10065 | B66: 45649 | C66: 45655 | D66: CUST-2749 | E66: Aarav Sharma | F66: Corporate | G66: East | H66: Jharkhand | I66: Ranchi | J66: Office Supplies | K66: Paper | L66: Classic Paper 458 | M66: First Class | N66: 7 | O66: 447.84 | P66: 0 | Q66: 3134.88 | R66: 2367.63 | S66: 767.25 | T66: Refunded | U66: Returned | V66: =IF(ISBLANK(P66), 0, P66) -> 0 | W66: =N66 * O66 * (1 - P66) -> 3134.88 | X66: =W66-R66 -> 767.25 | Y66: =IFERROR(X66 / W66, 0) -> 0.24474621 | Z66: =IF(OR(ISBLANK(B66), ISBLANK(C66), ISTEXT(B66), ISTEXT(C66)), "", C66 - B66) -> 6 | AA66: =MONTH(B66) -> 12 | AB66: =YEAR(B66) -> 2024 | AC66: =IF(COUNTIF(A:A, A66) > 1, "Conflicting Duplicate Order ID", IF(OR(G66="Unknown", ISBLANK(G66)), "Missing region", IF(OR(M66="Unknown", ISBLANK(M66)), "Missing ship_mode", IF(OR(ISBLANK(B66), ISBLANK(C66)), "Missing Date", IF(OR(ISTEXT(B66), ISTEXT(C66)), "Text Value Not Recognized as Date", IF(C66 < B66, "Invalid shipping record", IF(P66 < 0, "Invalid", IF(P66 > 0.7, "Invalid", "Valid")))))))) -> Valid | AD66: =IF(ABS(Q66 - W66) > 0.01, 1, 0) -> 0 | AE66: =IF(ABS(S66 - X66) > 0.01, 1, 0) -> 0 | AH66: =PROPER(TRIM(E66)) -> Aarav Sharma | AI66: =PROPER(TRIM(F66)) -> Corporate | AJ66: =PROPER(TRIM(G66)) -> East | AK66: =PROPER(TRIM(H66)) -> Jharkhand | AL66: =PROPER(TRIM(I66)) -> Ranchi | AM66: =PROPER(TRIM(J66)) -> Office Supplies | AN66: =PROPER(TRIM(K66)) -> Paper | AO66: =PROPER(TRIM(M66)) -> First Class | AP66: =PROPER(TRIM(T66)) -> Refunded | AQ66: =PROPER(TRIM(U66)) -> Returned
A67: ORD-2024-10066 | B67: 45404 | C67: 45409 | D67: CUST-2463 | E67: Mira Das | F67: Home Office | G67: West | H67: Maharashtra | I67: Mumbai | J67: Office Supplies | K67: Paper | L67: Pro Paper 552 | M67: Second Class | N67: 1 | O67: 4280.19 | P67: 0.05 | Q67: 4066.18 | R67: 2628.92 | S67: 1437.26 | T67: Paid | U67: Completed | V67: =IF(ISBLANK(P67), 0, P67) -> 0.05 | W67: =N67 * O67 * (1 - P67) -> 4066.1805 | X67: =W67-R67 -> 1437.2605 | Y67: =IFERROR(X67 / W67, 0) -> 0.35346697 | Z67: =IF(OR(ISBLANK(B67), ISBLANK(C67), ISTEXT(B67), ISTEXT(C67)), "", C67 - B67) -> 5 | AA67: =MONTH(B67) -> 4 | AB67: =YEAR(B67) -> 2024 | AC67: =IF(COUNTIF(A:A, A67) > 1, "Conflicting Duplicate Order ID", IF(OR(G67="Unknown", ISBLANK(G67)), "Missing region", IF(OR(M67="Unknown", ISBLANK(M67)), "Missing ship_mode", IF(OR(ISBLANK(B67), ISBLANK(C67)), "Missing Date", IF(OR(ISTEXT(B67), ISTEXT(C67)), "Text Value Not Recognized as Date", IF(C67 < B67, "Invalid shipping record", IF(P67 < 0, "Invalid", IF(P67 > 0.7, "Invalid", "Valid")))))))) -> Valid | AD67: =IF(ABS(Q67 - W67) > 0.01, 1, 0) -> 0 | AE67: =IF(ABS(S67 - X67) > 0.01, 1, 0) -> 0 | AH67: =PROPER(TRIM(E67)) -> Mira Das | AI67: =PROPER(TRIM(F67)) -> Home Office | AJ67: =PROPER(TRIM(G67)) -> West | AK67: =PROPER(TRIM(H67)) -> Maharashtra | AL67: =PROPER(TRIM(I67)) -> Mumbai | AM67: =PROPER(TRIM(J67)) -> Office Supplies | AN67: =PROPER(TRIM(K67)) -> Paper | AO67: =PROPER(TRIM(M67)) -> Second Class | AP67: =PROPER(TRIM(T67)) -> Paid | AQ67: =PROPER(TRIM(U67)) -> Completed
A68: ORD-2025-10067 | B68: 45897 | C68: 45901 | D68: CUST-1504 | E68: Karan Malhotra | F68: Small Business | G68: South | H68: Tamil Nadu | I68: Chennai | J68: Technology | K68: Accessories | L68: Elite Accessories 187 | M68: Same Day | N68: 7 | O68: 1057.46 | P68: 0.05 | Q68: 7032.11 | R68: 4610.34 | S68: 2421.77 | T68: Paid | U68: Completed | V68: =IF(ISBLANK(P68), 0, P68) -> 0.05 | W68: =N68 * O68 * (1 - P68) -> 7032.109 | X68: =W68-R68 -> 2421.769 | Y68: =IFERROR(X68 / W68, 0) -> 0.3443873 | Z68: =IF(OR(ISBLANK(B68), ISBLANK(C68), ISTEXT(B68), ISTEXT(C68)), "", C68 - B68) -> 4 | AA68: =MONTH(B68) -> 8 | AB68: =YEAR(B68) -> 2025 | AC68: =IF(COUNTIF(A:A, A68) > 1, "Conflicting Duplicate Order ID", IF(OR(G68="Unknown", ISBLANK(G68)), "Missing region", IF(OR(M68="Unknown", ISBLANK(M68)), "Missing ship_mode", IF(OR(ISBLANK(B68), ISBLANK(C68)), "Missing Date", IF(OR(ISTEXT(B68), ISTEXT(C68)), "Text Value Not Recognized as Date", IF(C68 < B68, "Invalid shipping record", IF(P68 < 0, "Invalid", IF(P68 > 0.7, "Invalid", "Valid")))))))) -> Valid | AD68: =IF(ABS(Q68 - W68) > 0.01, 1, 0) -> 0 | AE68: =IF(ABS(S68 - X68) > 0.01, 1, 0) -> 0 | AH68: =PROPER(TRIM(E68)) -> Karan Malhotra | AI68: =PROPER(TRIM(F68)) -> Small Business | AJ68: =PROPER(TRIM(G68)) -> South | AK68: =PROPER(TRIM(H68)) -> Tamil Nadu | AL68: =PROPER(TRIM(I68)) -> Chennai | AM68: =PROPER(TRIM(J68)) -> Technology | AN68: =PROPER(TRIM(K68)) -> Accessories | AO68: =PROPER(TRIM(M68)) -> Same Day | AP68: =PROPER(TRIM(T68)) -> Paid | AQ68: =PROPER(TRIM(U68)) -> Completed
A69: ORD-2025-10068 | B69: 45691 | C69: 45840 | D69: CUST-8282 | E69: Kabir Singh | F69: Consumer | G69: North | H69: Haryana | I69: Gurugram | J69: Office Supplies | K69: Paper | L69: Eco Paper 922 | M69: First Class | N69: 7 | O69: 3609.34 | P69: 0.05 | Q69: 24002.11 | R69: 18707.57 | S69: 5294.54 | T69: Paid | U69: Completed | V69: =IF(ISBLANK(P69), 0, P69) -> 0.05 | W69: =N69 * O69 * (1 - P69) -> 24002.111 | X69: =W69-R69 -> 5294.541 | Y69: =IFERROR(X69 / W69, 0) -> 0.22058647 | Z69: =IF(OR(ISBLANK(B69), ISBLANK(C69), ISTEXT(B69), ISTEXT(C69)), "", C69 - B69) -> 149 | AA69: =MONTH(B69) -> 2 | AB69: =YEAR(B69) -> 2025 | AC69: =IF(COUNTIF(A:A, A69) > 1, "Conflicting Duplicate Order ID", IF(OR(G69="Unknown", ISBLANK(G69)), "Missing region", IF(OR(M69="Unknown", ISBLANK(M69)), "Missing ship_mode", IF(OR(ISBLANK(B69), ISBLANK(C69)), "Missing Date", IF(OR(ISTEXT(B69), ISTEXT(C69)), "Text Value Not Recognized as Date", IF(C69 < B69, "Invalid shipping record", IF(P69 < 0, "Invalid", IF(P69 > 0.7, "Invalid", "Valid")))))))) -> Valid | AD69: =IF(ABS(Q69 - W69) > 0.01, 1, 0) -> 0 | AE69: =IF(ABS(S69 - X69) > 0.01, 1, 0) -> 0 | AH69: =PROPER(TRIM(E69)) -> Kabir Singh | AI69: =PROPER(TRIM(F69)) -> Consumer | AJ69: =PROPER(TRIM(G69)) -> North | AK69: =PROPER(TRIM(H69)) -> Haryana | AL69: =PROPER(TRIM(I69)) -> Gurugram | AM69: =PROPER(TRIM(J69)) -> Office Supplies | AN69: =PROPER(TRIM(K69)) -> Paper | AO69: =PROPER(TRIM(M69)) -> First Class | AP69: =PROPER(TRIM(T69)) -> Paid | AQ69: =PROPER(TRIM(U69)) -> Completed
A70: ORD-2024-10069 | B70: 45606 | C70: 45609 | D70: CUST-6054 | E70: Isha Nair | F70: Corporate | G70: East | H70: Jharkhand | I70: Ranchi | J70: Office Supplies | K70: Storage | L70: Pro Storage 975 | M70: Second Class | N70: 9 | O70: 2211.12 | P70: 0 | Q70: 19900.08 | R70: 10962.66 | S70: 8937.42 | T70: Failed | U70: Returned | V70: =IF(ISBLANK(P70), 0, P70) -> 0 | W70: =N70 * O70 * (1 - P70) -> 19900.08 | X70: =W70-R70 -> 8937.42 | Y70: =IFERROR(X70 / W70, 0) -> 0.44911478 | Z70: =IF(OR(ISBLANK(B70), ISBLANK(C70), ISTEXT(B70), ISTEXT(C70)), "", C70 - B70) -> 3 | AA70: =MONTH(B70) -> 11 | AB70: =YEAR(B70) -> 2024 | AC70: =IF(COUNTIF(A:A, A70) > 1, "Conflicting Duplicate Order ID", IF(OR(G70="Unknown", ISBLANK(G70)), "Missing region", IF(OR(M70="Unknown", ISBLANK(M70)), "Missing ship_mode", IF(OR(ISBLANK(B70), ISBLANK(C70)), "Missing Date", IF(OR(ISTEXT(B70), ISTEXT(C70)), "Text Value Not Recognized as Date", IF(C70 < B70, "Invalid shipping record", IF(P70 < 0, "Invalid", IF(P70 > 0.7, "Invalid", "Valid")))))))) -> Valid | AD70: =IF(ABS(Q70 - W70) > 0.01, 1, 0) -> 0 | AE70: =IF(ABS(S70 - X70) > 0.01, 1, 0) -> 0 | AH70: =PROPER(TRIM(E70)) -> Isha Nair | AI70: =PROPER(TRIM(F70)) -> Corporate | AJ70: =PROPER(TRIM(G70)) -> East | AK70: =PROPER(TRIM(H70)) -> Jharkhand | AL70: =PROPER(TRIM(I70)) -> Ranchi | AM70: =PROPER(TRIM(J70)) -> Office Supplies | AN70: =PROPER(TRIM(K70)) -> Storage | AO70: =PROPER(TRIM(M70)) -> Second Class | AP70: =PROPER(TRIM(T70)) -> Failed | AQ70: =PROPER(TRIM(U70)) -> Returned
A71: ORD-2024-10070 | B71: 45391 | C71: 45396 | D71: CUST-5979 | E71: Neha Gupta | F71: Small Business | G71: West | H71: Gujarat | I71: Ahmedabad | J71: Technology | K71: Machines | L71: Prime Machines 782 | M71: Same Day | N71: 7 | O71: 3417.09 | P71: 0.1 | Q71: 21527.67 | R71: 18287.58 | S71: 3240.09 | T71: Refunded | U71: Returned | V71: =IF(ISBLANK(P71), 0, P71) -> 0.1 | W71: =N71 * O71 * (1 - P71) -> 21527.667 | X71: =W71-R71 -> 3240.087 | Y71: =IFERROR(X71 / W71, 0) -> 0.15050804 | Z71: =IF(OR(ISBLANK(B71), ISBLANK(C71), ISTEXT(B71), ISTEXT(C71)), "", C71 - B71) -> 5 | AA71: =MONTH(B71) -> 4 | AB71: =YEAR(B71) -> 2024 | AC71: =IF(COUNTIF(A:A, A71) > 1, "Conflicting Duplicate Order ID", IF(OR(G71="Unknown", ISBLANK(G71)), "Missing region", IF(OR(M71="Unknown", ISBLANK(M71)), "Missing ship_mode", IF(OR(ISBLANK(B71), ISBLANK(C71)), "Missing Date", IF(OR(ISTEXT(B71), ISTEXT(C71)), "Text Value Not Recognized as Date", IF(C71 < B71, "Invalid shipping record", IF(P71 < 0, "Invalid", IF(P71 > 0.7, "Invalid", "Valid")))))))) -> Valid | AD71: =IF(ABS(Q71 - W71) > 0.01, 1, 0) -> 0 | AE71: =IF(ABS(S71 - X71) > 0.01, 1, 0) -> 0 | AH71: =PROPER(TRIM(E71)) -> Neha Gupta | AI71: =PROPER(TRIM(F71)) -> Small Business | AJ71: =PROPER(TRIM(G71)) -> West | AK71: =PROPER(TRIM(H71)) -> Gujarat | AL71: =PROPER(TRIM(I71)) -> Ahmedabad | AM71: =PROPER(TRIM(J71)) -> Technology | AN71: =PROPER(TRIM(K71)) -> Machines | AO71: =PROPER(TRIM(M71)) -> Same Day | AP71: =PROPER(TRIM(T71)) -> Refunded | AQ71: =PROPER(TRIM(U71)) -> Returned
A72: ORD-2025-10071 | B72: 45891 | C72: 45896 | D72: CUST-5582 | E72: Karan Malhotra | F72: Corporate | G72: South | H72: Andhra Pradesh | I72: Vijayawada | J72: Technology | K72: Phones | L72: Max Phones 661 | M72: First Class | N72: 2 | O72: 905.87 | P72: 0.15 | Q72: 1539.98 | R72: 1070.2 | S72: 469.78 | T72: Paid | U72: Completed | V72: =IF(ISBLANK(P72), 0, P72) -> 0.15 | W72: =N72 * O72 * (1 - P72) -> 1539.979 | X72: =W72-R72 -> 469.779 | Y72: =IFERROR(X72 / W72, 0) -> 0.30505546 | Z72: =IF(OR(ISBLANK(B72), ISBLANK(C72), ISTEXT(B72), ISTEXT(C72)), "", C72 - B72) -> 5 | AA72: =MONTH(B72) -> 8 | AB72: =YEAR(B72) -> 2025 | AC72: =IF(COUNTIF(A:A, A72) > 1, "Conflicting Duplicate Order ID", IF(OR(G72="Unknown", ISBLANK(G72)), "Missing region", IF(OR(M72="Unknown", ISBLANK(M72)), "Missing ship_mode", IF(OR(ISBLANK(B72), ISBLANK(C72)), "Missing Date", IF(OR(ISTEXT(B72), ISTEXT(C72)), "Text Value Not Recognized as Date", IF(C72 < B72, "Invalid shipping record", IF(P72 < 0, "Invalid", IF(P72 > 0.7, "Invalid", "Valid")))))))) -> Valid | AD72: =IF(ABS(Q72 - W72) > 0.01, 1, 0) -> 0 | AE72: =IF(ABS(S72 - X72) > 0.01, 1, 0) -> 0 | AH72: =PROPER(TRIM(E72)) -> Karan Malhotra | AI72: =PROPER(TRIM(F72)) -> Corporate | AJ72: =PROPER(TRIM(G72)) -> South | AK72: =PROPER(TRIM(H72)) -> Andhra Pradesh | AL72: =PROPER(TRIM(I72)) -> Vijayawada | AM72: =PROPER(TRIM(J72)) -> Technology | AN72: =PROPER(TRIM(K72)) -> Phones | AO72: =PROPER(TRIM(M72)) -> First Class | AP72: =PROPER(TRIM(T72)) -> Paid | AQ72: =PROPER(TRIM(U72)) -> Completed
A73: ORD-2025-10072 | B73: 45763 | C73: 45770 | D73: CUST-3308 | E73: Mira Das | F73: Small Business | G73: West | H73: Goa | I73: Panaji | J73: Technology | K73: Machines | L73: Elite Machines 836 | M73: Standard Class | N73: 6 | O73: 2027.32 | P73: 0.1 | Q73: 10947.53 | R73: 6447.36 | S73: 4500.17 | T73: Paid | U73: Completed | V73: =IF(ISBLANK(P73), 0, P73) -> 0.1 | W73: =N73 * O73 * (1 - P73) -> 10947.528 | X73: =W73-R73 -> 4500.168 | Y73: =IFERROR(X73 / W73, 0) -> 0.41106705 | Z73: =IF(OR(ISBLANK(B73), ISBLANK(C73), ISTEXT(B73), ISTEXT(C73)), "", C73 - B73) -> 7 | AA73: =MONTH(B73) -> 4 | AB73: =YEAR(B73) -> 2025 | AC73: =IF(COUNTIF(A:A, A73) > 1, "Conflicting Duplicate Order ID", IF(OR(G73="Unknown", ISBLANK(G73)), "Missing region", IF(OR(M73="Unknown", ISBLANK(M73)), "Missing ship_mode", IF(OR(ISBLANK(B73), ISBLANK(C73)), "Missing Date", IF(OR(ISTEXT(B73), ISTEXT(C73)), "Text Value Not Recognized as Date", IF(C73 < B73, "Invalid shipping record", IF(P73 < 0, "Invalid", IF(P73 > 0.7, "Invalid", "Valid")))))))) -> Valid | AD73: =IF(ABS(Q73 - W73) > 0.01, 1, 0) -> 0 | AE73: =IF(ABS(S73 - X73) > 0.01, 1, 0) -> 0 | AH73: =PROPER(TRIM(E73)) -> Mira Das | AI73: =PROPER(TRIM(F73)) -> Small Business | AJ73: =PROPER(TRIM(G73)) -> West | AK73: =PROPER(TRIM(H73)) -> Goa | AL73: =PROPER(TRIM(I73)) -> Panaji | AM73: =PROPER(TRIM(J73)) -> Technology | AN73: =PROPER(TRIM(K73)) -> Machines | AO73: =PROPER(TRIM(M73)) -> Standard Class | AP73: =PROPER(TRIM(T73)) -> Paid | AQ73: =PROPER(TRIM(U73)) -> Completed
A74: ORD-2024-10073 | B74: 45333 | C74: 45329 | D74: CUST-5018 | E74: Karan Malhotra | F74: Home Office | G74: South | H74: Tamil Nadu | I74: Chennai | J74: Furniture | K74: Tables | L74: Prime Tables 902 | M74: First Class | N74: 7 | O74: 2287.47 | P74: 0.15 | Q74: 13610.45 | R74: 10039.05 | S74: 3571.4 | T74: Paid | U74: Completed | V74: =IF(ISBLANK(P74), 0, P74) -> 0.15 | W74: =N74 * O74 * (1 - P74) -> 13610.446 | X74: =W74-R74 -> 3571.3965 | Y74: =IFERROR(X74 / W74, 0) -> 0.26240113 | Z74: =IF(OR(ISBLANK(B74), ISBLANK(C74), ISTEXT(B74), ISTEXT(C74)), "", C74 - B74) -> -4 | AA74: =MONTH(B74) -> 2 | AB74: =YEAR(B74) -> 2024 | AC74: =IF(COUNTIF(A:A, A74) > 1, "Conflicting Duplicate Order ID", IF(OR(G74="Unknown", ISBLANK(G74)), "Missing region", IF(OR(M74="Unknown", ISBLANK(M74)), "Missing ship_mode", IF(OR(ISBLANK(B74), ISBLANK(C74)), "Missing Date", IF(OR(ISTEXT(B74), ISTEXT(C74)), "Text Value Not Recognized as Date", IF(C74 < B74, "Invalid shipping record", IF(P74 < 0, "Invalid", IF(P74 > 0.7, "Invalid", "Valid")))))))) -> Invalid shipping record | AD74: =IF(ABS(Q74 - W74) > 0.01, 1, 0) -> 0 | AE74: =IF(ABS(S74 - X74) > 0.01, 1, 0) -> 0 | AH74: =PROPER(TRIM(E74)) -> Karan Malhotra | AI74: =PROPER(TRIM(F74)) -> Home Office | AJ74: =PROPER(TRIM(G74)) -> South | AK74: =PROPER(TRIM(H74)) -> Tamil Nadu | AL74: =PROPER(TRIM(I74)) -> Chennai | AM74: =PROPER(TRIM(J74)) -> Furniture | AN74: =PROPER(TRIM(K74)) -> Tables | AO74: =PROPER(TRIM(M74)) -> First Class | AP74: =PROPER(TRIM(T74)) -> Paid | AQ74: =PROPER(TRIM(U74)) -> Completed
A75: ORD-2025-10074 | B75: 29-03-2025 | C75: 45750 | D75: CUST-2342 | E75: Sneha Kapoor | F75: Corporate | G75: East | H75: West Bengal | I75: Kolkata | J75: Furniture | K75: Bookcases | L75: Smart Bookcases 167 | M75: First Class | N75: 5 | O75: 1425.74 | P75: 0 | Q75: 7128.7 | R75: 4382.15 | S75: 2746.55 | T75: Paid | U75: Completed | V75: =IF(ISBLANK(P75), 0, P75) -> 0 | W75: =N75 * O75 * (1 - P75) -> 7128.7 | X75: =W75-R75 -> 2746.55 | Y75: =IFERROR(X75 / W75, 0) -> 0.38528063 | Z75: =IF(OR(ISBLANK(B75), ISBLANK(C75), ISTEXT(B75), ISTEXT(C75)), "", C75 - B75) | AA75: =MONTH(B75) -> #VALUE! | AB75: =YEAR(B75) -> #VALUE! | AC75: =IF(COUNTIF(A:A, A75) > 1, "Conflicting Duplicate Order ID", IF(OR(G75="Unknown", ISBLANK(G75)), "Missing region", IF(OR(M75="Unknown", ISBLANK(M75)), "Missing ship_mode", IF(OR(ISBLANK(B75), ISBLANK(C75)), "Missing Date", IF(OR(ISTEXT(B75), ISTEXT(C75)), "Text Value Not Recognized as Date", IF(C75 < B75, "Invalid shipping record", IF(P75 < 0, "Invalid", IF(P75 > 0.7, "Invalid", "Valid")))))))) -> Text Value Not Recognized as Date | AD75: =IF(ABS(Q75 - W75) > 0.01, 1, 0) -> 0 | AE75: =IF(ABS(S75 - X75) > 0.01, 1, 0) -> 0 | AH75: =PROPER(TRIM(E75)) -> Sneha Kapoor | AI75: =PROPER(TRIM(F75)) -> Corporate | AJ75: =PROPER(TRIM(G75)) -> East | AK75: =PROPER(TRIM(H75)) -> West Bengal | AL75: =PROPER(TRIM(I75)) -> Kolkata | AM75: =PROPER(TRIM(J75)) -> Furniture | AN75: =PROPER(TRIM(K75)) -> Bookcases | AO75: =PROPER(TRIM(M75)) -> First Class | AP75: =PROPER(TRIM(T75)) -> Paid | AQ75: =PROPER(TRIM(U75)) -> Completed
A76: ORD-2025-10075 | B76: 45715 | C76: 45717 | D76: CUST-6201 | E76: Vikram Iyer | F76: Small Business | G76: East | H76: West Bengal | I76: Kolkata | J76: Furniture | K76: Chairs | L76: Max Chairs 244 | M76: Standard Class | N76: 6 | O76: 551.64 | P76: 0 | Q76: 3309.84 | R76: 2671.08 | S76: 638.76 | T76: Paid | U76: Completed | V76: =IF(ISBLANK(P76), 0, P76) -> 0 | W76: =N76 * O76 * (1 - P76) -> 3309.84 | X76: =W76-R76 -> 638.76 | Y76: =IFERROR(X76 / W76, 0) -> 0.19298818 | Z76: =IF(OR(ISBLANK(B76), ISBLANK(C76), ISTEXT(B76), ISTEXT(C76)), "", C76 - B76) -> 2 | AA76: =MONTH(B76) -> 2 | AB76: =YEAR(B76) -> 2025 | AC76: =IF(COUNTIF(A:A, A76) > 1, "Conflicting Duplicate Order ID", IF(OR(G76="Unknown", ISBLANK(G76)), "Missing region", IF(OR(M76="Unknown", ISBLANK(M76)), "Missing ship_mode", IF(OR(ISBLANK(B76), ISBLANK(C76)), "Missing Date", IF(OR(ISTEXT(B76), ISTEXT(C76)), "Text Value Not Recognized as Date", IF(C76 < B76, "Invalid shipping record", IF(P76 < 0, "Invalid", IF(P76 > 0.7, "Invalid", "Valid")))))))) -> Valid | AD76: =IF(ABS(Q76 - W76) > 0.01, 1, 0) -> 0 | AE76: =IF(ABS(S76 - X76) > 0.01, 1, 0) -> 0 | AH76: =PROPER(TRIM(E76)) -> Vikram Iyer | AI76: =PROPER(TRIM(F76)) -> Small Business | AJ76: =PROPER(TRIM(G76)) -> East | AK76: =PROPER(TRIM(H76)) -> West Bengal | AL76: =PROPER(TRIM(I76)) -> Kolkata | AM76: =PROPER(TRIM(J76)) -> Furniture | AN76: =PROPER(TRIM(K76)) -> Chairs | AO76: =PROPER(TRIM(M76)) -> Standard Class | AP76: =PROPER(TRIM(T76)) -> Paid | AQ76: =PROPER(TRIM(U76)) -> Completed
A77: ORD-2025-10076 | B77: 22-08-2025 | C77: 45896 | D77: CUST-5808 | E77: Priya Menon | F77: Small Business | G77: East | H77: Odisha | I77: Bhubaneswar | J77: Office Supplies | K77: Labels | L77: Eco Labels 653 | M77: First Class | N77: 3 | O77: 3294.82 | P77: 0.2 | Q77: 7907.57 | R77: 5391.18 | S77: 2516.39 | T77: Paid | U77: Completed | V77: =IF(ISBLANK(P77), 0, P77) -> 0.2 | W77: =N77 * O77 * (1 - P77) -> 7907.568 | X77: =W77-R77 -> 2516.388 | Y77: =IFERROR(X77 / W77, 0) -> 0.31822527 | Z77: =IF(OR(ISBLANK(B77), ISBLANK(C77), ISTEXT(B77), ISTEXT(C77)), "", C77 - B77) | AA77: =MONTH(B77) -> #VALUE! | AB77: =YEAR(B77) -> #VALUE! | AC77: =IF(COUNTIF(A:A, A77) > 1, "Conflicting Duplicate Order ID", IF(OR(G77="Unknown", ISBLANK(G77)), "Missing region", IF(OR(M77="Unknown", ISBLANK(M77)), "Missing ship_mode", IF(OR(ISBLANK(B77), ISBLANK(C77)), "Missing Date", IF(OR(ISTEXT(B77), ISTEXT(C77)), "Text Value Not Recognized as Date", IF(C77 < B77, "Invalid shipping record", IF(P77 < 0, "Invalid", IF(P77 > 0.7, "Invalid", "Valid")))))))) -> Text Value Not Recognized as Date | AD77: =IF(ABS(Q77 - W77) > 0.01, 1, 0) -> 0 | AE77: =IF(ABS(S77 - X77) > 0.01, 1, 0) -> 0 | AH77: =PROPER(TRIM(E77)) -> Priya Menon | AI77: =PROPER(TRIM(F77)) -> Small Business | AJ77: =PROPER(TRIM(G77)) -> East | AK77: =PROPER(TRIM(H77)) -> Odisha | AL77: =PROPER(TRIM(I77)) -> Bhubaneswar | AM77: =PROPER(TRIM(J77)) -> Office Supplies | AN77: =PROPER(TRIM(K77)) -> Labels | AO77: =PROPER(TRIM(M77)) -> First Class | AP77: =PROPER(TRIM(T77)) -> Paid | AQ77: =PROPER(TRIM(U77)) -> Completed
A78: ORD-2024-10077 | B78: 45599 | C78: 45607 | D78: CUST-2642 | E78: Ananya Rao | F78: Corporate | G78: East | H78: Jharkhand | I78: Ranchi | J78: Office Supplies | K78: Labels | L78: Max Labels 617 | M78: Second Class | N78: 3 | O78: 3406.27 | P78: 0 | Q78: 10218.81 | R78: 7616.97 | S78: 2601.84 | T78: Paid | U78: Completed | V78: =IF(ISBLANK(P78), 0, P78) -> 0 | W78: =N78 * O78 * (1 - P78) -> 10218.81 | X78: =W78-R78 -> 2601.84 | Y78: =IFERROR(X78 / W78, 0) -> 0.25461282 | Z78: =IF(OR(ISBLANK(B78), ISBLANK(C78), ISTEXT(B78), ISTEXT(C78)), "", C78 - B78) -> 8 | AA78: =MONTH(B78) -> 11 | AB78: =YEAR(B78) -> 2024 | AC78: =IF(COUNTIF(A:A, A78) > 1, "Conflicting Duplicate Order ID", IF(OR(G78="Unknown", ISBLANK(G78)), "Missing region", IF(OR(M78="Unknown", ISBLANK(M78)), "Missing ship_mode", IF(OR(ISBLANK(B78), ISBLANK(C78)), "Missing Date", IF(OR(ISTEXT(B78), ISTEXT(C78)), "Text Value Not Recognized as Date", IF(C78 < B78, "Invalid shipping record", IF(P78 < 0, "Invalid", IF(P78 > 0.7, "Invalid", "Valid")))))))) -> Valid | AD78: =IF(ABS(Q78 - W78) > 0.01, 1, 0) -> 0 | AE78: =IF(ABS(S78 - X78) > 0.01, 1, 0) -> 0 | AH78: =PROPER(TRIM(E78)) -> Ananya Rao | AI78: =PROPER(TRIM(F78)) -> Corporate | AJ78: =PROPER(TRIM(G78)) -> East | AK78: =PROPER(TRIM(H78)) -> Jharkhand | AL78: =PROPER(TRIM(I78)) -> Ranchi | AM78: =PROPER(TRIM(J78)) -> Office Supplies | AN78: =PROPER(TRIM(K78)) -> Labels | AO78: =PROPER(TRIM(M78)) -> Second Class | AP78: =PROPER(TRIM(T78)) -> Paid | AQ78: =PROPER(TRIM(U78)) -> Completed
A79: ORD-2025-10078 | B79: 45846 | C79: 45998 | D79: CUST-4385 | E79: Rohan Mehta | F79: Home Office | G79: North | H79: Uttar Pradesh | I79: Noida | J79: Furniture | K79: Furnishings | L79: Pro Furnishings 529 | M79: Standard Class | N79: 1 | O79: 2582.2 | P79: 0.15 | Q79: 2194.87 | R79: 1223.17 | S79: 971.7 | T79: Refunded | U79: Cancelled | V79: =IF(ISBLANK(P79), 0, P79) -> 0.15 | W79: =N79 * O79 * (1 - P79) -> 2194.87 | X79: =W79-R79 -> 971.7 | Y79: =IFERROR(X79 / W79, 0) -> 0.44271415 | Z79: =IF(OR(ISBLANK(B79), ISBLANK(C79), ISTEXT(B79), ISTEXT(C79)), "", C79 - B79) -> 152 | AA79: =MONTH(B79) -> 7 | AB79: =YEAR(B79) -> 2025 | AC79: =IF(COUNTIF(A:A, A79) > 1, "Conflicting Duplicate Order ID", IF(OR(G79="Unknown", ISBLANK(G79)), "Missing region", IF(OR(M79="Unknown", ISBLANK(M79)), "Missing ship_mode", IF(OR(ISBLANK(B79), ISBLANK(C79)), "Missing Date", IF(OR(ISTEXT(B79), ISTEXT(C79)), "Text Value Not Recognized as Date", IF(C79 < B79, "Invalid shipping record", IF(P79 < 0, "Invalid", IF(P79 > 0.7, "Invalid", "Valid")))))))) -> Valid | AD79: =IF(ABS(Q79 - W79) > 0.01, 1, 0) -> 0 | AE79: =IF(ABS(S79 - X79) > 0.01, 1, 0) -> 0 | AH79: =PROPER(TRIM(E79)) -> Rohan Mehta | AI79: =PROPER(TRIM(F79)) -> Home Office | AJ79: =PROPER(TRIM(G79)) -> North | AK79: =PROPER(TRIM(H79)) -> Uttar Pradesh | AL79: =PROPER(TRIM(I79)) -> Noida | AM79: =PROPER(TRIM(J79)) -> Furniture | AN79: =PROPER(TRIM(K79)) -> Furnishings | AO79: =PROPER(TRIM(M79)) -> Standard Class | AP79: =PROPER(TRIM(T79)) -> Refunded | AQ79: =PROPER(TRIM(U79)) -> Cancelled
A80: ORD-2025-10079 | B80: 45854 | C80: 21-07-2025 | D80: CUST-8043 | E80: Sneha Kapoor | F80: Corporate | G80: East | H80: West Bengal | I80: Kolkata | J80: Furniture | K80: Tables | L80: Smart Tables 561 | M80: First Class | N80: 5 | O80: 2129.51 | P80: 0.15 | Q80: 9050.42 | R80: 6778.85 | S80: 2271.57 | T80: Paid | U80: Completed | V80: =IF(ISBLANK(P80), 0, P80) -> 0.15 | W80: =N80 * O80 * (1 - P80) -> 9050.4175 | X80: =W80-R80 -> 2271.5675 | Y80: =IFERROR(X80 / W80, 0) -> 0.25099035 | Z80: =IF(OR(ISBLANK(B80), ISBLANK(C80), ISTEXT(B80), ISTEXT(C80)), "", C80 - B80) | AA80: =MONTH(B80) -> 7 | AB80: =YEAR(B80) -> 2025 | AC80: =IF(COUNTIF(A:A, A80) > 1, "Conflicting Duplicate Order ID", IF(OR(G80="Unknown", ISBLANK(G80)), "Missing region", IF(OR(M80="Unknown", ISBLANK(M80)), "Missing ship_mode", IF(OR(ISBLANK(B80), ISBLANK(C80)), "Missing Date", IF(OR(ISTEXT(B80), ISTEXT(C80)), "Text Value Not Recognized as Date", IF(C80 < B80, "Invalid shipping record", IF(P80 < 0, "Invalid", IF(P80 > 0.7, "Invalid", "Valid")))))))) -> Text Value Not Recognized as Date | AD80: =IF(ABS(Q80 - W80) > 0.01, 1, 0) -> 0 | AE80: =IF(ABS(S80 - X80) > 0.01, 1, 0) -> 0 | AH80: =PROPER(TRIM(E80)) -> Sneha Kapoor | AI80: =PROPER(TRIM(F80)) -> Corporate | AJ80: =PROPER(TRIM(G80)) -> East | AK80: =PROPER(TRIM(H80)) -> West Bengal | AL80: =PROPER(TRIM(I80)) -> Kolkata | AM80: =PROPER(TRIM(J80)) -> Furniture | AN80: =PROPER(TRIM(K80)) -> Tables | AO80: =PROPER(TRIM(M80)) -> First Class | AP80: =PROPER(TRIM(T80)) -> Paid | AQ80: =PROPER(TRIM(U80)) -> Completed
A81: ORD-2025-10080 | B81: 45927 | C81: 45933 | D81: CUST-9978 | E81: Diya Patel | F81: Home Office | G81: South | H81: Tamil Nadu | I81: Chennai | J81: Furniture | K81: Chairs | L81: Prime Chairs 838 | M81: Same Day | N81: 9 | O81: 4131.52 | P81: 0.1 | Q81: 33465.31 | R81: 24781.26 | S81: 8684.05 | T81: Paid | U81: Completed | V81: =IF(ISBLANK(P81), 0, P81) -> 0.1 | W81: =N81 * O81 * (1 - P81) -> 33465.312 | X81: =W81-R81 -> 8684.052 | Y81: =IFERROR(X81 / W81, 0) -> 0.25949413 | Z81: =IF(OR(ISBLANK(B81), ISBLANK(C81), ISTEXT(B81), ISTEXT(C81)), "", C81 - B81) -> 6 | AA81: =MONTH(B81) -> 9 | AB81: =YEAR(B81) -> 2025 | AC81: =IF(COUNTIF(A:A, A81) > 1, "Conflicting Duplicate Order ID", IF(OR(G81="Unknown", ISBLANK(G81)), "Missing region", IF(OR(M81="Unknown", ISBLANK(M81)), "Missing ship_mode", IF(OR(ISBLANK(B81), ISBLANK(C81)), "Missing Date", IF(OR(ISTEXT(B81), ISTEXT(C81)), "Text Value Not Recognized as Date", IF(C81 < B81, "Invalid shipping record", IF(P81 < 0, "Invalid", IF(P81 > 0.7, "Invalid", "Valid")))))))) -> Valid | AD81: =IF(ABS(Q81 - W81) > 0.01, 1, 0) -> 0 | AE81: =IF(ABS(S81 - X81) > 0.01, 1, 0) -> 0 | AH81: =PROPER(TRIM(E81)) -> Diya Patel | AI81: =PROPER(TRIM(F81)) -> Home Office | AJ81: =PROPER(TRIM(G81)) -> South | AK81: =PROPER(TRIM(H81)) -> Tamil Nadu | AL81: =PROPER(TRIM(I81)) -> Chennai | AM81: =PROPER(TRIM(J81)) -> Furniture | AN81: =PROPER(TRIM(K81)) -> Chairs | AO81: =PROPER(TRIM(M81)) -> Same Day | AP81: =PROPER(TRIM(T81)) -> Paid | AQ81: =PROPER(TRIM(U81)) -> Completed
A82: ORD-2024-10081 | B82: 45514 | C82: 45518 | D82: CUST-2094 | E82: Aarav Sharma | F82: Small Business | G82: North | H82: Delhi | I82: New Delhi | J82: Office Supplies | K82: Storage | L82: Elite Storage 371 | M82: Second Class | N82: 4 | O82: 1182.32 | P82: 0.1 | Q82: 4256.35 | R82: 2495.33 | S82: 1761.02 | T82: Pending | U82: Returned | V82: =IF(ISBLANK(P82), 0, P82) -> 0.1 | W82: =N82 * O82 * (1 - P82) -> 4256.352 | X82: =W82-R82 -> 1761.022 | Y82: =IFERROR(X82 / W82, 0) -> 0.41373975 | Z82: =IF(OR(ISBLANK(B82), ISBLANK(C82), ISTEXT(B82), ISTEXT(C82)), "", C82 - B82) -> 4 | AA82: =MONTH(B82) -> 8 | AB82: =YEAR(B82) -> 2024 | AC82: =IF(COUNTIF(A:A, A82) > 1, "Conflicting Duplicate Order ID", IF(OR(G82="Unknown", ISBLANK(G82)), "Missing region", IF(OR(M82="Unknown", ISBLANK(M82)), "Missing ship_mode", IF(OR(ISBLANK(B82), ISBLANK(C82)), "Missing Date", IF(OR(ISTEXT(B82), ISTEXT(C82)), "Text Value Not Recognized as Date", IF(C82 < B82, "Invalid shipping record", IF(P82 < 0, "Invalid", IF(P82 > 0.7, "Invalid", "Valid")))))))) -> Valid | AD82: =IF(ABS(Q82 - W82) > 0.01, 1, 0) -> 0 | AE82: =IF(ABS(S82 - X82) > 0.01, 1, 0) -> 0 | AH82: =PROPER(TRIM(E82)) -> Aarav Sharma | AI82: =PROPER(TRIM(F82)) -> Small Business | AJ82: =PROPER(TRIM(G82)) -> North | AK82: =PROPER(TRIM(H82)) -> Delhi | AL82: =PROPER(TRIM(I82)) -> New Delhi | AM82: =PROPER(TRIM(J82)) -> Office Supplies | AN82: =PROPER(TRIM(K82)) -> Storage | AO82: =PROPER(TRIM(M82)) -> Second Class | AP82: =PROPER(TRIM(T82)) -> Pending | AQ82: =PROPER(TRIM(U82)) -> Returned
A83: ORD-2025-10082 | B83: 45732 | C83: 17-03-2025 | D83: CUST-7907 | E83: Karan Malhotra | F83: Home Office | G83: West | H83: Goa | I83: Panaji | J83: Office Supplies | K83: Labels | L83: Eco Labels 662 | M83: Same Day | N83: 3 | O83: 1841.91 | P83: 0 | Q83: 5525.73 | R83: 3093.42 | S83: 2432.31 | T83: Paid | U83: Completed | V83: =IF(ISBLANK(P83), 0, P83) -> 0 | W83: =N83 * O83 * (1 - P83) -> 5525.73 | X83: =W83-R83 -> 2432.31 | Y83: =IFERROR(X83 / W83, 0) -> 0.44017894 | Z83: =IF(OR(ISBLANK(B83), ISBLANK(C83), ISTEXT(B83), ISTEXT(C83)), "", C83 - B83) | AA83: =MONTH(B83) -> 3 | AB83: =YEAR(B83) -> 2025 | AC83: =IF(COUNTIF(A:A, A83) > 1, "Conflicting Duplicate Order ID", IF(OR(G83="Unknown", ISBLANK(G83)), "Missing region", IF(OR(M83="Unknown", ISBLANK(M83)), "Missing ship_mode", IF(OR(ISBLANK(B83), ISBLANK(C83)), "Missing Date", IF(OR(ISTEXT(B83), ISTEXT(C83)), "Text Value Not Recognized as Date", IF(C83 < B83, "Invalid shipping record", IF(P83 < 0, "Invalid", IF(P83 > 0.7, "Invalid", "Valid")))))))) -> Text Value Not Recognized as Date | AD83: =IF(ABS(Q83 - W83) > 0.01, 1, 0) -> 0 | AE83: =IF(ABS(S83 - X83) > 0.01, 1, 0) -> 0 | AH83: =PROPER(TRIM(E83)) -> Karan Malhotra | AI83: =PROPER(TRIM(F83)) -> Home Office | AJ83: =PROPER(TRIM(G83)) -> West | AK83: =PROPER(TRIM(H83)) -> Goa | AL83: =PROPER(TRIM(I83)) -> Panaji | AM83: =PROPER(TRIM(J83)) -> Office Supplies | AN83: =PROPER(TRIM(K83)) -> Labels | AO83: =PROPER(TRIM(M83)) -> Same Day | AP83: =PROPER(TRIM(T83)) -> Paid | AQ83: =PROPER(TRIM(U83)) -> Completed
A84: ORD-2024-10083 | B84: 45507 | C84: 45390 | D84: CUST-6516 | E84: Arjun Bose | F84: Consumer | G84: North | H84: Uttar Pradesh | I84: Noida | J84: Technology | K84: Copiers | L84: Smart Copiers 702 | M84: Second Class | N84: 6 | O84: 1001.73 | P84: 0 | Q84: 6010.38 | R84: 3762.85 | S84: 2247.53 | T84: Failed | U84: Returned | V84: =IF(ISBLANK(P84), 0, P84) -> 0 | W84: =N84 * O84 * (1 - P84) -> 6010.38 | X84: =W84-R84 -> 2247.53 | Y84: =IFERROR(X84 / W84, 0) -> 0.37394141 | Z84: =IF(OR(ISBLANK(B84), ISBLANK(C84), ISTEXT(B84), ISTEXT(C84)), "", C84 - B84) -> -117 | AA84: =MONTH(B84) -> 8 | AB84: =YEAR(B84) -> 2024 | AC84: =IF(COUNTIF(A:A, A84) > 1, "Conflicting Duplicate Order ID", IF(OR(G84="Unknown", ISBLANK(G84)), "Missing region", IF(OR(M84="Unknown", ISBLANK(M84)), "Missing ship_mode", IF(OR(ISBLANK(B84), ISBLANK(C84)), "Missing Date", IF(OR(ISTEXT(B84), ISTEXT(C84)), "Text Value Not Recognized as Date", IF(C84 < B84, "Invalid shipping record", IF(P84 < 0, "Invalid", IF(P84 > 0.7, "Invalid", "Valid")))))))) -> Invalid shipping record | AD84: =IF(ABS(Q84 - W84) > 0.01, 1, 0) -> 0 | AE84: =IF(ABS(S84 - X84) > 0.01, 1, 0) -> 0 | AH84: =PROPER(TRIM(E84)) -> Arjun Bose | AI84: =PROPER(TRIM(F84)) -> Consumer | AJ84: =PROPER(TRIM(G84)) -> North | AK84: =PROPER(TRIM(H84)) -> Uttar Pradesh | AL84: =PROPER(TRIM(I84)) -> Noida | AM84: =PROPER(TRIM(J84)) -> Technology | AN84: =PROPER(TRIM(K84)) -> Copiers | AO84: =PROPER(TRIM(M84)) -> Second Class | AP84: =PROPER(TRIM(T84)) -> Failed | AQ84: =PROPER(TRIM(U84)) -> Returned
A85: ORD-2024-10084 | B85: 26-10-2024 | C85: 29-10-2024 | D85: CUST-4989 | E85: Aditi Sen | F85: Home Office | G85: West | H85: Maharashtra | I85: Mumbai | J85: Furniture | K85: Tables | L85: Elite Tables 362 | M85: Second Class | N85: 9 | O85: 131.74 | P85: 0.2 | Q85: 948.53 | R85: 674.62 | S85: 273.91 | T85: Paid | U85: Completed | V85: =IF(ISBLANK(P85), 0, P85) -> 0.2 | W85: =N85 * O85 * (1 - P85) -> 948.528 | X85: =W85-R85 -> 273.908 | Y85: =IFERROR(X85 / W85, 0) -> 0.28877165 | Z85: =IF(OR(ISBLANK(B85), ISBLANK(C85), ISTEXT(B85), ISTEXT(C85)), "", C85 - B85) | AA85: =MONTH(B85) -> #VALUE! | AB85: =YEAR(B85) -> #VALUE! | AC85: =IF(COUNTIF(A:A, A85) > 1, "Conflicting Duplicate Order ID", IF(OR(G85="Unknown", ISBLANK(G85)), "Missing region", IF(OR(M85="Unknown", ISBLANK(M85)), "Missing ship_mode", IF(OR(ISBLANK(B85), ISBLANK(C85)), "Missing Date", IF(OR(ISTEXT(B85), ISTEXT(C85)), "Text Value Not Recognized as Date", IF(C85 < B85, "Invalid shipping record", IF(P85 < 0, "Invalid", IF(P85 > 0.7, "Invalid", "Valid")))))))) -> Text Value Not Recognized as Date | AD85: =IF(ABS(Q85 - W85) > 0.01, 1, 0) -> 0 | AE85: =IF(ABS(S85 - X85) > 0.01, 1, 0) -> 0 | AH85: =PROPER(TRIM(E85)) -> Aditi Sen | AI85: =PROPER(TRIM(F85)) -> Home Office | AJ85: =PROPER(TRIM(G85)) -> West | AK85: =PROPER(TRIM(H85)) -> Maharashtra | AL85: =PROPER(TRIM(I85)) -> Mumbai | AM85: =PROPER(TRIM(J85)) -> Furniture | AN85: =PROPER(TRIM(K85)) -> Tables | AO85: =PROPER(TRIM(M85)) -> Second Class | AP85: =PROPER(TRIM(T85)) -> Paid | AQ85: =PROPER(TRIM(U85)) -> Completed
A86: ORD-2024-10085 | B86: 45566 | C86: 45568 | D86: CUST-3758 | E86: Rohan Mehta | F86: Corporate | G86: South | H86: Tamil Nadu | I86: Chennai | J86: Technology | K86: Phones | L86: Elite Phones 781 | M86: Second Class | N86: 6 | O86: 570.28 | P86: 0.2 | Q86: 2737.34 | R86: 2085.44 | S86: 651.9 | T86: Paid | U86: Completed | V86: =IF(ISBLANK(P86), 0, P86) -> 0.2 | W86: =N86 * O86 * (1 - P86) -> 2737.344 | X86: =W86-R86 -> 651.904 | Y86: =IFERROR(X86 / W86, 0) -> 0.23815202 | Z86: =IF(OR(ISBLANK(B86), ISBLANK(C86), ISTEXT(B86), ISTEXT(C86)), "", C86 - B86) -> 2 | AA86: =MONTH(B86) -> 10 | AB86: =YEAR(B86) -> 2024 | AC86: =IF(COUNTIF(A:A, A86) > 1, "Conflicting Duplicate Order ID", IF(OR(G86="Unknown", ISBLANK(G86)), "Missing region", IF(OR(M86="Unknown", ISBLANK(M86)), "Missing ship_mode", IF(OR(ISBLANK(B86), ISBLANK(C86)), "Missing Date", IF(OR(ISTEXT(B86), ISTEXT(C86)), "Text Value Not Recognized as Date", IF(C86 < B86, "Invalid shipping record", IF(P86 < 0, "Invalid", IF(P86 > 0.7, "Invalid", "Valid")))))))) -> Valid | AD86: =IF(ABS(Q86 - W86) > 0.01, 1, 0) -> 0 | AE86: =IF(ABS(S86 - X86) > 0.01, 1, 0) -> 0 | AH86: =PROPER(TRIM(E86)) -> Rohan Mehta | AI86: =PROPER(TRIM(F86)) -> Corporate | AJ86: =PROPER(TRIM(G86)) -> South | AK86: =PROPER(TRIM(H86)) -> Tamil Nadu | AL86: =PROPER(TRIM(I86)) -> Chennai | AM86: =PROPER(TRIM(J86)) -> Technology | AN86: =PROPER(TRIM(K86)) -> Phones | AO86: =PROPER(TRIM(M86)) -> Second Class | AP86: =PROPER(TRIM(T86)) -> Paid | AQ86: =PROPER(TRIM(U86)) -> Completed
A87: ORD-2024-10086 | B87: 45503 | C87: 45509 | D87: CUST-6702 | E87: Kabir Singh | F87: Corporate | G87: North | H87: Delhi | I87: New Delhi | J87: Office Supplies | K87: Binders | L87: Eco Binders 456 | M87: Standard Class | N87: 1 | O87: 608.64 | P87: 0 | Q87: 608.64 | R87: 343.99 | S87: 264.65 | T87: Paid | U87: Cancelled | V87: =IF(ISBLANK(P87), 0, P87) -> 0 | W87: =N87 * O87 * (1 - P87) -> 608.64 | X87: =W87-R87 -> 264.65 | Y87: =IFERROR(X87 / W87, 0) -> 0.4348219 | Z87: =IF(OR(ISBLANK(B87), ISBLANK(C87), ISTEXT(B87), ISTEXT(C87)), "", C87 - B87) -> 6 | AA87: =MONTH(B87) -> 7 | AB87: =YEAR(B87) -> 2024 | AC87: =IF(COUNTIF(A:A, A87) > 1, "Conflicting Duplicate Order ID", IF(OR(G87="Unknown", ISBLANK(G87)), "Missing region", IF(OR(M87="Unknown", ISBLANK(M87)), "Missing ship_mode", IF(OR(ISBLANK(B87), ISBLANK(C87)), "Missing Date", IF(OR(ISTEXT(B87), ISTEXT(C87)), "Text Value Not Recognized as Date", IF(C87 < B87, "Invalid shipping record", IF(P87 < 0, "Invalid", IF(P87 > 0.7, "Invalid", "Valid")))))))) -> Valid | AD87: =IF(ABS(Q87 - W87) > 0.01, 1, 0) -> 0 | AE87: =IF(ABS(S87 - X87) > 0.01, 1, 0) -> 0 | AH87: =PROPER(TRIM(E87)) -> Kabir Singh | AI87: =PROPER(TRIM(F87)) -> Corporate | AJ87: =PROPER(TRIM(G87)) -> North | AK87: =PROPER(TRIM(H87)) -> Delhi | AL87: =PROPER(TRIM(I87)) -> New Delhi | AM87: =PROPER(TRIM(J87)) -> Office Supplies | AN87: =PROPER(TRIM(K87)) -> Binders | AO87: =PROPER(TRIM(M87)) -> Standard Class | AP87: =PROPER(TRIM(T87)) -> Paid | AQ87: =PROPER(TRIM(U87)) -> Cancelled
A88: ORD-2024-10087 | B88: 45474 | C88: 45474 | D88: CUST-9148 | E88: Ananya Rao | F88: Small Business | G88: North | H88: Delhi | I88: New Delhi | J88: Technology | K88: Copiers | L88: Basic Copiers 525 | M88: Second Class | N88: 3 | O88: 885.28 | P88: 0.1 | Q88: 2390.26 | R88: 1495.94 | S88: 894.32 | T88: Refunded | U88: Cancelled | V88: =IF(ISBLANK(P88), 0, P88) -> 0.1 | W88: =N88 * O88 * (1 - P88) -> 2390.256 | X88: =W88-R88 -> 894.316 | Y88: =IFERROR(X88 / W88, 0) -> 0.37415072 | Z88: =IF(OR(ISBLANK(B88), ISBLANK(C88), ISTEXT(B88), ISTEXT(C88)), "", C88 - B88) -> 0 | AA88: =MONTH(B88) -> 7 | AB88: =YEAR(B88) -> 2024 | AC88: =IF(COUNTIF(A:A, A88) > 1, "Conflicting Duplicate Order ID", IF(OR(G88="Unknown", ISBLANK(G88)), "Missing region", IF(OR(M88="Unknown", ISBLANK(M88)), "Missing ship_mode", IF(OR(ISBLANK(B88), ISBLANK(C88)), "Missing Date", IF(OR(ISTEXT(B88), ISTEXT(C88)), "Text Value Not Recognized as Date", IF(C88 < B88, "Invalid shipping record", IF(P88 < 0, "Invalid", IF(P88 > 0.7, "Invalid", "Valid")))))))) -> Valid | AD88: =IF(ABS(Q88 - W88) > 0.01, 1, 0) -> 0 | AE88: =IF(ABS(S88 - X88) > 0.01, 1, 0) -> 0 | AH88: =PROPER(TRIM(E88)) -> Ananya Rao | AI88: =PROPER(TRIM(F88)) -> Small Business | AJ88: =PROPER(TRIM(G88)) -> North | AK88: =PROPER(TRIM(H88)) -> Delhi | AL88: =PROPER(TRIM(I88)) -> New Delhi | AM88: =PROPER(TRIM(J88)) -> Technology | AN88: =PROPER(TRIM(K88)) -> Copiers | AO88: =PROPER(TRIM(M88)) -> Second Class | AP88: =PROPER(TRIM(T88)) -> Refunded | AQ88: =PROPER(TRIM(U88)) -> Cancelled
A89: ORD-2024-10088 | B89: 45330 | C89: 45507 | D89: CUST-5829 | E89: Vikram Iyer | F89: Consumer | G89: East | H89: Assam | I89: Guwahati | J89: Office Supplies | K89: Binders | L89: Eco Binders 258 | M89: Standard Class | N89: 7 | O89: 3345.22 | P89: 0 | Q89: 23416.54 | R89: 15490.89 | S89: 7925.65 | T89: Paid | U89: Completed | V89: =IF(ISBLANK(P89), 0, P89) -> 0 | W89: =N89 * O89 * (1 - P89) -> 23416.54 | X89: =W89-R89 -> 7925.65 | Y89: =IFERROR(X89 / W89, 0) -> 0.33846375 | Z89: =IF(OR(ISBLANK(B89), ISBLANK(C89), ISTEXT(B89), ISTEXT(C89)), "", C89 - B89) -> 177 | AA89: =MONTH(B89) -> 2 | AB89: =YEAR(B89) -> 2024 | AC89: =IF(COUNTIF(A:A, A89) > 1, "Conflicting Duplicate Order ID", IF(OR(G89="Unknown", ISBLANK(G89)), "Missing region", IF(OR(M89="Unknown", ISBLANK(M89)), "Missing ship_mode", IF(OR(ISBLANK(B89), ISBLANK(C89)), "Missing Date", IF(OR(ISTEXT(B89), ISTEXT(C89)), "Text Value Not Recognized as Date", IF(C89 < B89, "Invalid shipping record", IF(P89 < 0, "Invalid", IF(P89 > 0.7, "Invalid", "Valid")))))))) -> Valid | AD89: =IF(ABS(Q89 - W89) > 0.01, 1, 0) -> 0 | AE89: =IF(ABS(S89 - X89) > 0.01, 1, 0) -> 0 | AH89: =PROPER(TRIM(E89)) -> Vikram Iyer | AI89: =PROPER(TRIM(F89)) -> Consumer | AJ89: =PROPER(TRIM(G89)) -> East | AK89: =PROPER(TRIM(H89)) -> Assam | AL89: =PROPER(TRIM(I89)) -> Guwahati | AM89: =PROPER(TRIM(J89)) -> Office Supplies | AN89: =PROPER(TRIM(K89)) -> Binders | AO89: =PROPER(TRIM(M89)) -> Standard Class | AP89: =PROPER(TRIM(T89)) -> Paid | AQ89: =PROPER(TRIM(U89)) -> Completed
A90: ORD-2024-10089 | B90: 45375 | C90: 45378 | D90: CUST-6059 | E90: Rohan Mehta | F90: Small Business | G90: West | H90: Maharashtra | I90: Mumbai | J90: Furniture | K90: Bookcases | L90: Max Bookcases 398 | M90: Standard Class | N90: 2 | O90: 3284.75 | P90: 0.05 | Q90: 6241.02 | R90: 5345.88 | S90: 895.14 | T90: Paid | U90: Completed | V90: =IF(ISBLANK(P90), 0, P90) -> 0.05 | W90: =N90 * O90 * (1 - P90) -> 6241.025 | X90: =W90-R90 -> 895.145 | Y90: =IFERROR(X90 / W90, 0) -> 0.14342916 | Z90: =IF(OR(ISBLANK(B90), ISBLANK(C90), ISTEXT(B90), ISTEXT(C90)), "", C90 - B90) -> 3 | AA90: =MONTH(B90) -> 3 | AB90: =YEAR(B90) -> 2024 | AC90: =IF(COUNTIF(A:A, A90) > 1, "Conflicting Duplicate Order ID", IF(OR(G90="Unknown", ISBLANK(G90)), "Missing region", IF(OR(M90="Unknown", ISBLANK(M90)), "Missing ship_mode", IF(OR(ISBLANK(B90), ISBLANK(C90)), "Missing Date", IF(OR(ISTEXT(B90), ISTEXT(C90)), "Text Value Not Recognized as Date", IF(C90 < B90, "Invalid shipping record", IF(P90 < 0, "Invalid", IF(P90 > 0.7, "Invalid", "Valid")))))))) -> Valid | AD90: =IF(ABS(Q90 - W90) > 0.01, 1, 0) -> 0 | AE90: =IF(ABS(S90 - X90) > 0.01, 1, 0) -> 0 | AH90: =PROPER(TRIM(E90)) -> Rohan Mehta | AI90: =PROPER(TRIM(F90)) -> Small Business | AJ90: =PROPER(TRIM(G90)) -> West | AK90: =PROPER(TRIM(H90)) -> Maharashtra | AL90: =PROPER(TRIM(I90)) -> Mumbai | AM90: =PROPER(TRIM(J90)) -> Furniture | AN90: =PROPER(TRIM(K90)) -> Bookcases | AO90: =PROPER(TRIM(M90)) -> Standard Class | AP90: =PROPER(TRIM(T90)) -> Paid | AQ90: =PROPER(TRIM(U90)) -> Completed
A91: ORD-2024-10090 | B91: 45540 | C91: 45540 | D91: CUST-7744 | E91: Kabir Singh | F91: Consumer | G91: South | H91: Andhra Pradesh | I91: Vijayawada | J91: Furniture | K91: Bookcases | L91: Smart Bookcases 857 | M91: Standard Class | N91: 7 | O91: 3761.09 | P91: 0.2 | Q91: 21062.1 | R91: 12057.13 | S91: 9004.97 | T91: Pending | U91: Cancelled | V91: =IF(ISBLANK(P91), 0, P91) -> 0.2 | W91: =N91 * O91 * (1 - P91) -> 21062.104 | X91: =W91-R91 -> 9004.974 | Y91: =IFERROR(X91 / W91, 0) -> 0.4275439 | Z91: =IF(OR(ISBLANK(B91), ISBLANK(C91), ISTEXT(B91), ISTEXT(C91)), "", C91 - B91) -> 0 | AA91: =MONTH(B91) -> 9 | AB91: =YEAR(B91) -> 2024 | AC91: =IF(COUNTIF(A:A, A91) > 1, "Conflicting Duplicate Order ID", IF(OR(G91="Unknown", ISBLANK(G91)), "Missing region", IF(OR(M91="Unknown", ISBLANK(M91)), "Missing ship_mode", IF(OR(ISBLANK(B91), ISBLANK(C91)), "Missing Date", IF(OR(ISTEXT(B91), ISTEXT(C91)), "Text Value Not Recognized as Date", IF(C91 < B91, "Invalid shipping record", IF(P91 < 0, "Invalid", IF(P91 > 0.7, "Invalid", "Valid")))))))) -> Valid | AD91: =IF(ABS(Q91 - W91) > 0.01, 1, 0) -> 0 | AE91: =IF(ABS(S91 - X91) > 0.01, 1, 0) -> 0 | AH91: =PROPER(TRIM(E91)) -> Kabir Singh | AI91: =PROPER(TRIM(F91)) -> Consumer | AJ91: =PROPER(TRIM(G91)) -> South | AK91: =PROPER(TRIM(H91)) -> Andhra Pradesh | AL91: =PROPER(TRIM(I91)) -> Vijayawada | AM91: =PROPER(TRIM(J91)) -> Furniture | AN91: =PROPER(TRIM(K91)) -> Bookcases | AO91: =PROPER(TRIM(M91)) -> Standard Class | AP91: =PROPER(TRIM(T91)) -> Pending | AQ91: =PROPER(TRIM(U91)) -> Cancelled
A92: ORD-2025-10091 | B92: 45893 | C92: 45898 | D92: CUST-5909 | E92: Aarav Sharma | F92: Small Business | G92: East | H92: Bihar | I92: Patna | J92: Technology | K92: Copiers | L92: Smart Copiers 556 | M92: First Class | N92: 3 | O92: 3703.96 | P92: 0.15 | Q92: 9445.1 | R92: 5586.28 | S92: 3858.82 | T92: Paid | U92: Completed | V92: =IF(ISBLANK(P92), 0, P92) -> 0.15 | W92: =N92 * O92 * (1 - P92) -> 9445.098 | X92: =W92-R92 -> 3858.818 | Y92: =IFERROR(X92 / W92, 0) -> 0.40855246 | Z92: =IF(OR(ISBLANK(B92), ISBLANK(C92), ISTEXT(B92), ISTEXT(C92)), "", C92 - B92) -> 5 | AA92: =MONTH(B92) -> 8 | AB92: =YEAR(B92) -> 2025 | AC92: =IF(COUNTIF(A:A, A92) > 1, "Conflicting Duplicate Order ID", IF(OR(G92="Unknown", ISBLANK(G92)), "Missing region", IF(OR(M92="Unknown", ISBLANK(M92)), "Missing ship_mode", IF(OR(ISBLANK(B92), ISBLANK(C92)), "Missing Date", IF(OR(ISTEXT(B92), ISTEXT(C92)), "Text Value Not Recognized as Date", IF(C92 < B92, "Invalid shipping record", IF(P92 < 0, "Invalid", IF(P92 > 0.7, "Invalid", "Valid")))))))) -> Conflicting Duplicate Order ID | AD92: =IF(ABS(Q92 - W92) > 0.01, 1, 0) -> 0 | AE92: =IF(ABS(S92 - X92) > 0.01, 1, 0) -> 0 | AH92: =PROPER(TRIM(E92)) -> Aarav Sharma | AI92: =PROPER(TRIM(F92)) -> Small Business | AJ92: =PROPER(TRIM(G92)) -> East | AK92: =PROPER(TRIM(H92)) -> Bihar | AL92: =PROPER(TRIM(I92)) -> Patna | AM92: =PROPER(TRIM(J92)) -> Technology | AN92: =PROPER(TRIM(K92)) -> Copiers | AO92: =PROPER(TRIM(M92)) -> First Class | AP92: =PROPER(TRIM(T92)) -> Paid | AQ92: =PROPER(TRIM(U92)) -> Completed
A93: ORD-2025-10092 | B93: 45691 | C93: 45724 | D93: CUST-6409 | E93: Sneha Kapoor | F93: Corporate | G93: West | H93: Madhya Pradesh | I93: Indore | J93: Technology | K93: Copiers | L93: Prime Copiers 575 | M93: Second Class | N93: 9 | O93: 269.68 | P93: 0 | Q93: 2427.12 | R93: 1538.35 | S93: 804.53 | T93: Paid | U93: Completed | V93: =IF(ISBLANK(P93), 0, P93) -> 0 | W93: =N93 * O93 * (1 - P93) -> 2427.12 | X93: =W93-R93 -> 888.77 | Y93: =IFERROR(X93 / W93, 0) -> 0.36618297 | Z93: =IF(OR(ISBLANK(B93), ISBLANK(C93), ISTEXT(B93), ISTEXT(C93)), "", C93 - B93) -> 33 | AA93: =MONTH(B93) -> 2 | AB93: =YEAR(B93) -> 2025 | AC93: =IF(COUNTIF(A:A, A93) > 1, "Conflicting Duplicate Order ID", IF(OR(G93="Unknown", ISBLANK(G93)), "Missing region", IF(OR(M93="Unknown", ISBLANK(M93)), "Missing ship_mode", IF(OR(ISBLANK(B93), ISBLANK(C93)), "Missing Date", IF(OR(ISTEXT(B93), ISTEXT(C93)), "Text Value Not Recognized as Date", IF(C93 < B93, "Invalid shipping record", IF(P93 < 0, "Invalid", IF(P93 > 0.7, "Invalid", "Valid")))))))) -> Valid | AD93: =IF(ABS(Q93 - W93) > 0.01, 1, 0) -> 0 | AE93: =IF(ABS(S93 - X93) > 0.01, 1, 0) -> 1 | AH93: =PROPER(TRIM(E93)) -> Sneha Kapoor | AI93: =PROPER(TRIM(F93)) -> Corporate | AJ93: =PROPER(TRIM(G93)) -> West | AK93: =PROPER(TRIM(H93)) -> Madhya Pradesh | AL93: =PROPER(TRIM(I93)) -> Indore | AM93: =PROPER(TRIM(J93)) -> Technology | AN93: =PROPER(TRIM(K93)) -> Copiers | AO93: =PROPER(TRIM(M93)) -> Second Class | AP93: =PROPER(TRIM(T93)) -> Paid | AQ93: =PROPER(TRIM(U93)) -> Completed
A94: ORD-2025-10093 | B94: 45680 | C94: 45683 | D94: CUST-3014 | E94: Aarav Sharma | F94: Consumer | G94: West | H94: Madhya Pradesh | I94: Indore | J94: Office Supplies | K94: Paper | L94: Elite Paper 669 | M94: Standard Class | N94: 9 | O94: 4458.26 | P94: 0.1 | Q94: 36111.91 | R94: 29194.5 | S94: 6917.41 | T94: Paid | U94: Completed | V94: =IF(ISBLANK(P94), 0, P94) -> 0.1 | W94: =N94 * O94 * (1 - P94) -> 36111.906 | X94: =W94-R94 -> 6917.406 | Y94: =IFERROR(X94 / W94, 0) -> 0.19155472 | Z94: =IF(OR(ISBLANK(B94), ISBLANK(C94), ISTEXT(B94), ISTEXT(C94)), "", C94 - B94) -> 3 | AA94: =MONTH(B94) -> 1 | AB94: =YEAR(B94) -> 2025 | AC94: =IF(COUNTIF(A:A, A94) > 1, "Conflicting Duplicate Order ID", IF(OR(G94="Unknown", ISBLANK(G94)), "Missing region", IF(OR(M94="Unknown", ISBLANK(M94)), "Missing ship_mode", IF(OR(ISBLANK(B94), ISBLANK(C94)), "Missing Date", IF(OR(ISTEXT(B94), ISTEXT(C94)), "Text Value Not Recognized as Date", IF(C94 < B94, "Invalid shipping record", IF(P94 < 0, "Invalid", IF(P94 > 0.7, "Invalid", "Valid")))))))) -> Valid | AD94: =IF(ABS(Q94 - W94) > 0.01, 1, 0) -> 0 | AE94: =IF(ABS(S94 - X94) > 0.01, 1, 0) -> 0 | AH94: =PROPER(TRIM(E94)) -> Aarav Sharma | AI94: =PROPER(TRIM(F94)) -> Consumer | AJ94: =PROPER(TRIM(G94)) -> West | AK94: =PROPER(TRIM(H94)) -> Madhya Pradesh | AL94: =PROPER(TRIM(I94)) -> Indore | AM94: =PROPER(TRIM(J94)) -> Office Supplies | AN94: =PROPER(TRIM(K94)) -> Paper | AO94: =PROPER(TRIM(M94)) -> Standard Class | AP94: =PROPER(TRIM(T94)) -> Paid | AQ94: =PROPER(TRIM(U94)) -> Completed
A95: ORD-2024-10094 | B95: 45298 | C95: 13-01-2024 | D95: CUST-6106 | E95: Rohan Mehta | F95: Corporate | G95: North | H95: Uttar Pradesh | I95: Noida | J95: Office Supplies | K95: Binders | L95: Eco Binders 780 | M95: Standard Class | N95: 7 | O95: 2788.97 | P95: -0.09 | Q95: 19522.79 | R95: 12455.78 | S95: 7067.01 | T95: Paid | U95: Completed | V95: =IF(ISBLANK(P95), 0, P95) -> -0.09 | W95: =N95 * O95 * (1 - P95) -> 21279.841 | X95: =W95-R95 -> 8824.0611 | Y95: =IFERROR(X95 / W95, 0) -> 0.41466762 | Z95: =IF(OR(ISBLANK(B95), ISBLANK(C95), ISTEXT(B95), ISTEXT(C95)), "", C95 - B95) | AA95: =MONTH(B95) -> 1 | AB95: =YEAR(B95) -> 2024 | AC95: =IF(COUNTIF(A:A, A95) > 1, "Conflicting Duplicate Order ID", IF(OR(G95="Unknown", ISBLANK(G95)), "Missing region", IF(OR(M95="Unknown", ISBLANK(M95)), "Missing ship_mode", IF(OR(ISBLANK(B95), ISBLANK(C95)), "Missing Date", IF(OR(ISTEXT(B95), ISTEXT(C95)), "Text Value Not Recognized as Date", IF(C95 < B95, "Invalid shipping record", IF(P95 < 0, "Invalid", IF(P95 > 0.7, "Invalid", "Valid")))))))) -> Text Value Not Recognized as Date | AD95: =IF(ABS(Q95 - W95) > 0.01, 1, 0) -> 1 | AE95: =IF(ABS(S95 - X95) > 0.01, 1, 0) -> 1 | AH95: =PROPER(TRIM(E95)) -> Rohan Mehta | AI95: =PROPER(TRIM(F95)) -> Corporate | AJ95: =PROPER(TRIM(G95)) -> North | AK95: =PROPER(TRIM(H95)) -> Uttar Pradesh | AL95: =PROPER(TRIM(I95)) -> Noida | AM95: =PROPER(TRIM(J95)) -> Office Supplies | AN95: =PROPER(TRIM(K95)) -> Binders | AO95: =PROPER(TRIM(M95)) -> Standard Class | AP95: =PROPER(TRIM(T95)) -> Paid | AQ95: =PROPER(TRIM(U95)) -> Completed
A96: ORD-2024-10095 | B96: 45541 | C96: 45544 | D96: CUST-1926 | E96: Diya Patel | F96: Consumer | G96: North | H96: Haryana | I96: Gurugram | J96: Technology | K96: Phones | L96: Elite Phones 723 | M96: Second Class | N96: 7 | O96: 3781.53 | P96: 0 | Q96: 26470.71 | R96: 21367.6 | S96: 5103.11 | T96: Pending | U96: Cancelled | V96: =IF(ISBLANK(P96), 0, P96) -> 0 | W96: =N96 * O96 * (1 - P96) -> 26470.71 | X96: =W96-R96 -> 5103.11 | Y96: =IFERROR(X96 / W96, 0) -> 0.19278327 | Z96: =IF(OR(ISBLANK(B96), ISBLANK(C96), ISTEXT(B96), ISTEXT(C96)), "", C96 - B96) -> 3 | AA96: =MONTH(B96) -> 9 | AB96: =YEAR(B96) -> 2024 | AC96: =IF(COUNTIF(A:A, A96) > 1, "Conflicting Duplicate Order ID", IF(OR(G96="Unknown", ISBLANK(G96)), "Missing region", IF(OR(M96="Unknown", ISBLANK(M96)), "Missing ship_mode", IF(OR(ISBLANK(B96), ISBLANK(C96)), "Missing Date", IF(OR(ISTEXT(B96), ISTEXT(C96)), "Text Value Not Recognized as Date", IF(C96 < B96, "Invalid shipping record", IF(P96 < 0, "Invalid", IF(P96 > 0.7, "Invalid", "Valid")))))))) -> Valid | AD96: =IF(ABS(Q96 - W96) > 0.01, 1, 0) -> 0 | AE96: =IF(ABS(S96 - X96) > 0.01, 1, 0) -> 0 | AH96: =PROPER(TRIM(E96)) -> Diya Patel | AI96: =PROPER(TRIM(F96)) -> Consumer | AJ96: =PROPER(TRIM(G96)) -> North | AK96: =PROPER(TRIM(H96)) -> Haryana | AL96: =PROPER(TRIM(I96)) -> Gurugram | AM96: =PROPER(TRIM(J96)) -> Technology | AN96: =PROPER(TRIM(K96)) -> Phones | AO96: =PROPER(TRIM(M96)) -> Second Class | AP96: =PROPER(TRIM(T96)) -> Pending | AQ96: =PROPER(TRIM(U96)) -> Cancelled
A97: ORD-2025-10096 | B97: 45786 | C97: 45910 | D97: CUST-2687 | E97: Sneha Kapoor | F97: Corporate | G97: West | H97: Goa | I97: Panaji | J97: Furniture | K97: Bookcases | L97: Classic Bookcases 988 | M97: Same Day | N97: 6 | O97: 1754.13 | P97: 0 | Q97: 10524.78 | R97: 8841.05 | S97: 1683.73 | T97: Paid | U97: Completed | V97: =IF(ISBLANK(P97), 0, P97) -> 0 | W97: =N97 * O97 * (1 - P97) -> 10524.78 | X97: =W97-R97 -> 1683.73 | Y97: =IFERROR(X97 / W97, 0) -> 0.15997769 | Z97: =IF(OR(ISBLANK(B97), ISBLANK(C97), ISTEXT(B97), ISTEXT(C97)), "", C97 - B97) -> 124 | AA97: =MONTH(B97) -> 5 | AB97: =YEAR(B97) -> 2025 | AC97: =IF(COUNTIF(A:A, A97) > 1, "Conflicting Duplicate Order ID", IF(OR(G97="Unknown", ISBLANK(G97)), "Missing region", IF(OR(M97="Unknown", ISBLANK(M97)), "Missing ship_mode", IF(OR(ISBLANK(B97), ISBLANK(C97)), "Missing Date", IF(OR(ISTEXT(B97), ISTEXT(C97)), "Text Value Not Recognized as Date", IF(C97 < B97, "Invalid shipping record", IF(P97 < 0, "Invalid", IF(P97 > 0.7, "Invalid", "Valid")))))))) -> Valid | AD97: =IF(ABS(Q97 - W97) > 0.01, 1, 0) -> 0 | AE97: =IF(ABS(S97 - X97) > 0.01, 1, 0) -> 0 | AH97: =PROPER(TRIM(E97)) -> Sneha Kapoor | AI97: =PROPER(TRIM(F97)) -> Corporate | AJ97: =PROPER(TRIM(G97)) -> West | AK97: =PROPER(TRIM(H97)) -> Goa | AL97: =PROPER(TRIM(I97)) -> Panaji | AM97: =PROPER(TRIM(J97)) -> Furniture | AN97: =PROPER(TRIM(K97)) -> Bookcases | AO97: =PROPER(TRIM(M97)) -> Same Day | AP97: =PROPER(TRIM(T97)) -> Paid | AQ97: =PROPER(TRIM(U97)) -> Completed
A98: ORD-2024-10097 | B98: 45448 | C98: 45479 | D98: CUST-7283 | E98: Rahul Verma | F98: Home Office | G98: East | H98: Odisha | I98: Bhubaneswar | J98: Technology | K98: Copiers | L98: Smart Copiers 547 | M98: Second Class | N98: 2 | O98: 2259.24 | P98: 0.15 | Q98: 3840.71 | R98: 2516.29 | S98: 1324.42 | T98: Paid | U98: Completed | V98: =IF(ISBLANK(P98), 0, P98) -> 0.15 | W98: =N98 * O98 * (1 - P98) -> 3840.708 | X98: =W98-R98 -> 1324.418 | Y98: =IFERROR(X98 / W98, 0) -> 0.34483694 | Z98: =IF(OR(ISBLANK(B98), ISBLANK(C98), ISTEXT(B98), ISTEXT(C98)), "", C98 - B98) -> 31 | AA98: =MONTH(B98) -> 6 | AB98: =YEAR(B98) -> 2024 | AC98: =IF(COUNTIF(A:A, A98) > 1, "Conflicting Duplicate Order ID", IF(OR(G98="Unknown", ISBLANK(G98)), "Missing region", IF(OR(M98="Unknown", ISBLANK(M98)), "Missing ship_mode", IF(OR(ISBLANK(B98), ISBLANK(C98)), "Missing Date", IF(OR(ISTEXT(B98), ISTEXT(C98)), "Text Value Not Recognized as Date", IF(C98 < B98, "Invalid shipping record", IF(P98 < 0, "Invalid", IF(P98 > 0.7, "Invalid", "Valid")))))))) -> Valid | AD98: =IF(ABS(Q98 - W98) > 0.01, 1, 0) -> 0 | AE98: =IF(ABS(S98 - X98) > 0.01, 1, 0) -> 0 | AH98: =PROPER(TRIM(E98)) -> Rahul Verma | AI98: =PROPER(TRIM(F98)) -> Home Office | AJ98: =PROPER(TRIM(G98)) -> East | AK98: =PROPER(TRIM(H98)) -> Odisha | AL98: =PROPER(TRIM(I98)) -> Bhubaneswar | AM98: =PROPER(TRIM(J98)) -> Technology | AN98: =PROPER(TRIM(K98)) -> Copiers | AO98: =PROPER(TRIM(M98)) -> Second Class | AP98: =PROPER(TRIM(T98)) -> Paid | AQ98: =PROPER(TRIM(U98)) -> Completed
A99: ORD-2025-10098 | B99: 45877 | C99: 45880 | D99: CUST-8111 | E99: Diya Patel | F99: Small Business | G99: West | H99: Gujarat | I99: Ahmedabad | J99: Office Supplies | K99: Storage | L99: Basic Storage 656 | M99: Same Day | N99: 5 | O99: 3602.36 | P99: 0.2 | Q99: 14409.44 | R99: 8809.97 | S99: 5599.47 | T99: Pending | U99: Returned | V99: =IF(ISBLANK(P99), 0, P99) -> 0.2 | W99: =N99 * O99 * (1 - P99) -> 14409.44 | X99: =W99-R99 -> 5599.47 | Y99: =IFERROR(X99 / W99, 0) -> 0.38859734 | Z99: =IF(OR(ISBLANK(B99), ISBLANK(C99), ISTEXT(B99), ISTEXT(C99)), "", C99 - B99) -> 3 | AA99: =MONTH(B99) -> 8 | AB99: =YEAR(B99) -> 2025 | AC99: =IF(COUNTIF(A:A, A99) > 1, "Conflicting Duplicate Order ID", IF(OR(G99="Unknown", ISBLANK(G99)), "Missing region", IF(OR(M99="Unknown", ISBLANK(M99)), "Missing ship_mode", IF(OR(ISBLANK(B99), ISBLANK(C99)), "Missing Date", IF(OR(ISTEXT(B99), ISTEXT(C99)), "Text Value Not Recognized as Date", IF(C99 < B99, "Invalid shipping record", IF(P99 < 0, "Invalid", IF(P99 > 0.7, "Invalid", "Valid")))))))) -> Valid | AD99: =IF(ABS(Q99 - W99) > 0.01, 1, 0) -> 0 | AE99: =IF(ABS(S99 - X99) > 0.01, 1, 0) -> 0 | AH99: =PROPER(TRIM(E99)) -> Diya Patel | AI99: =PROPER(TRIM(F99)) -> Small Business | AJ99: =PROPER(TRIM(G99)) -> West | AK99: =PROPER(TRIM(H99)) -> Gujarat | AL99: =PROPER(TRIM(I99)) -> Ahmedabad | AM99: =PROPER(TRIM(J99)) -> Office Supplies | AN99: =PROPER(TRIM(K99)) -> Storage | AO99: =PROPER(TRIM(M99)) -> Same Day | AP99: =PROPER(TRIM(T99)) -> Pending | AQ99: =PROPER(TRIM(U99)) -> Returned
A100: ORD-2024-10099 | B100: 45317 | C100: 45323 | D100: CUST-5434 | E100: Rohan Mehta | F100: Home Office | G100: South | H100: Kerala | I100: Kochi | J100: Technology | K100: Copiers | L100: Elite Copiers 785 | N100: 8 | O100: 2108.93 | P100: 0.1 | Q100: 15184.3 | R100: 11270.74 | S100: 3913.56 | T100: Paid | U100: Completed | V100: =IF(ISBLANK(P100), 0, P100) -> 0.1 | W100: =N100 * O100 * (1 - P100) -> 15184.296 | X100: =W100-R100 -> 3913.556 | Y100: =IFERROR(X100 / W100, 0) -> 0.25773707 | Z100: =IF(OR(ISBLANK(B100), ISBLANK(C100), ISTEXT(B100), ISTEXT(C100)), "", C100 - B100) -> 6 | AA100: =MONTH(B100) -> 1 | AB100: =YEAR(B100) -> 2024 | AC100: =IF(COUNTIF(A:A, A100) > 1, "Conflicting Duplicate Order ID", IF(OR(G100="Unknown", ISBLANK(G100)), "Missing region", IF(OR(M100="Unknown", ISBLANK(M100)), "Missing ship_mode", IF(OR(ISBLANK(B100), ISBLANK(C100)), "Missing Date", IF(OR(ISTEXT(B100), ISTEXT(C100)), "Text Value Not Recognized as Date", IF(C100 < B100, "Invalid shipping record", IF(P100 < 0, "Invalid", IF(P100 > 0.7, "Invalid", "Valid")))))))) -> Missing ship_mode | AD100: =IF(ABS(Q100 - W100) > 0.01, 1, 0) -> 0 | AE100: =IF(ABS(S100 - X100) > 0.01, 1, 0) -> 0 | AH100: =PROPER(TRIM(E100)) -> Rohan Mehta | AI100: =PROPER(TRIM(F100)) -> Home Office | AJ100: =PROPER(TRIM(G100)) -> South | AK100: =PROPER(TRIM(H100)) -> Kerala | AL100: =PROPER(TRIM(I100)) -> Kochi | AM100: =PROPER(TRIM(J100)) -> Technology | AN100: =PROPER(TRIM(K100)) -> Copiers | AO100: Unknown | AP100: =PROPER(TRIM(T100)) -> Paid | AQ100: =PROPER(TRIM(U100)) -> Completed
...
